Workbook

Sheet README
B1: Open Budget Survey (OBS) 2025 – Public Data Statfile (Launch 2 Public Release)
B3: Structure of the workbook
B5: Data_Dictionary: Definitions, types, value coding, and notes for all variables
B6: Question_Map: Mapping of survey questions to their possible responses
B7: OBS_Data_2006-2025: Main dataset containing country identifiers, composite scores, and indicator variables
B8: Summary_3_Pillars: High-level pillar scores for OBS 2025 and OBS 2023 where applicable
B9: Scores + Letters: Expanded view with numeric scores and selected categorical/letter-coded fields used in reporting (Data available for OBS 2017-OBS 2025)
B10: Metadata_UI: Supporting metadata with individual country results including source and comment fields
B11: General_Questions_UI: Unscored general questions for individual countries
B12: Indicator_Change: Change in score for each indicator from OBS 2023 to OBS 2025
B14: About this dataset
B15: The Open Budget Survey (OBS) is an independent, comparative assessment of national budget processes. It evaluates three core dimensions of budget accountability: budget transparency (Open Budget Index – OBI), public participation, and oversight (Legislative + SAI).
... B52: File prepared for public release on 2026-04-14. Release: Launch 2 of 4 Countries included in this file: 31 of 83 OBS year: 2025

Sheet Data_Dictionary
B1: Data Dictionary — This sheet describes the variables included in the OBS dataset, including variable names/patterns, definitions, data types, value coding, and methodological notes. Users should review the README tab for important comparability notes and methodological caveats.
B3: Quick reference: common variable prefixes
B4: • q* — Scored OBS survey indicators
B5: • gq* — General questions (unscored; contextual use)
B6: • obi / *_obi — Transparency and oversight indices and related components
B7: • round* — Round-level composite values
B8: • grade_* / *_cat* — Categorical groupings used in reporting
B10: OBS_Data_2006-2025_Codebook
B12: Variable / Pattern | C12: Description | D12: Type | E12: Values / Coding | F12: Notes
B13: year | C13: OBS survey round year | D13: Number | E13: 2006 - 2025 (in this launch) | F13: Data are available from 2006 onward. If a country does not appear in a given year, it means the country was not included in the survey that year.
B14: region | C14: Broad regional classification | D14: Text
B15: rank | C15: Country rank in the Open Budget Index (OBI) | D15: Number | F15: Rankings are provisional in partial releases. Final rankings will be available only after all participating countries are published.
B16: obi | C16: Open Budget Index (OBI) transparency score | D16: Number (0–100) | E16: Average of q1–q102 and timeliness variables (t3pbs, t3ebp, t3eb, t3iyr, t3myr, t3yer, t3ar) | F16: Calculated as an unweighted average. roundobi is the OBI score rounded to the nearest whole number.
B17: obi_cat | C17: Category based on rounded transparency (OBI) score | D17: Categorical | E17: Scant or None; Minimal; Limited; Substantial; Extensive | F17: Categories are based on the rounded OBI score: • 0–20: Scant or no information • 21–40: Minimal information • 41–60: Limited information • 61–80: Substantial information • 81–100: Extensive information
B18: obi_cat2 | C18: Simplified transparency category based on rounded OBI score | D18: Categorical | E18: Low; Limited; Sufficient | F18: Categories are based on the rounded OBI score: • 0-40: Low • 41-60: Limited • 61-100: Sufficient
B19: obi_cat3 | C19: Binary transparency sufficiency category | D19: Categorical | E19: Insufficient; Sufficient | F19: A score of 61 or higher for the OBI is considered sufficient.
B20: obi_cat4 | C20: Quintile classification of rounded OBI score | D20: Categorical | E20: Bottom Quintile; 2nd Quintile; Middle Quintile; 4th Quintile; Top Quintile | F20: Categories are based on the rounded OBI score: • 0-20: Bottom Quintile • 21-40: 2nd Quintile • 41-60: Middle Quintile • 61-80: 4th Quintile • 81-100: Top Quintile
B21: oversight_obi | C21: Overall oversight score (legislature + SAI) | D21: Number (0–100) | E21: Unweighted average of q107–q124 | F21: Do not compare oversight scores prior to 2017, as the questions and structure changed in earlier rounds. Roundoversight_obi is the rounded value.
B22: leg_obi | C22: Legislature oversight sub-score | D22: Number (0–100) | E22: Unweighted average of q107-q118 | F22: Do not compare prior to 2017. Roundleg_obi is the rounded value.
B23: sai_obi | C23: Supreme Audit Institution (SAI) oversight sub-score | D23: Number (0–100) | E23: Unweighted average of q119-q124 | F23: Do not compare prior to 2017. Roundsai_obi is the rounded value.
B24: ifi_obi | C24: Independent Fiscal Institution (IFI) sub-score | D24: Number (0–100) | E24: Unweighted average of q103-q106 | F24: Exploratory indicator assessing Independent Fiscal Institutions (IFI). Not included in composite indices. roundifi_obi is the rounded value.
B25: grade_oversight, grade_leg, grade_sai, grade_ifi | C25: Category based on rounded oversight sub-scores | D25: Categorical | E25: Weak; Limited; Adequate | F25: • 0-40: Weak • 41-60: Limited • 61-100: Adequate
B26: pub_eng | C26: Public participation score | D26: Number (0–100) | E26: Unweighted average of q125-q142 | F26: Do not compare participation scores prior to 2017 due to questionnaire changes. roundpub_eng is the rounded value.
B27: grade_pub_eng | C27: Public participation category based on rounded score | D27: Categorical | E27: Few or no opportunities; Limited opportunities; Adequate opportunities | F27: • 0-40: Few or no opportunities • 41-60: Limited opportunities • 61-100: Adequate opportunities
... B38: Q1LETTER-Q142LETTER | C38: Letter responses corresponding to indicator scores (available in Scores + Letters tab) | D38: Text | E38: a/b/c/d/e | F38: Data for letters is only present since 2017 OBS as questions as the structure of the questions changed prior to that. Most indicators will have five response options (A through E), while some will have three (A through C) and depending on the option have different scoring conversions. Five-option indicators: • a = 100 • b = 67 • c = 33, • d = 0 • e = Not applicable (and thus not counted) Three-option indicators: • a = 100 • B = 0 • C = Not applicable (and thus not counted)
B41: Metadata_UI_Codebook
B43: Variable / Pattern | C43: Description | D43: Type | E43: Values / Coding | F43: Notes
B44: Q | C44: Indicator identifier | D44: Text | E44: q1–q142; t3pbs, t3ebp, t3eb, t3iyr, t3myr, t3yer, t3ar | F44: Provides information on scored OBS indicators and selected unscored indicators related to independent fiscal institutions.
B45: Group | C45: Composite index/pillar to which the indicator contributes | D45: Category | E45: The Open Budget Index, Unscored (IFI), Role and Effectiveness of Oversight Institutions, Public Participation in the Budget Process | F45: Indicator grouping: • Open Budget Index (Transparency): q1–q102 and timeliness variables ( t3pbs, t3ebp, t3eb, t3iyr, t3myr, t3yer, t3ar) • Unscored (IFI): q103–q106 • Oversight: q107–q124 • Public Participation: q125–q142
B46: Doc | C46: Budget document assessed by the indicator | D46: Category | E46: PBS, EBP, EB, CB, IYR, MYR, YER, AR | F46: Applies only to Open Budget Index (OBI) indicators (q1–q102 and timeliness variables). Document coverage: • PBS: t3pbs and q54–q58 • EBP: t3ebp and q1–q53 • EB: t3eb and q59–q63 • CB: q64–q67 • IYR: t3iyr and q68–q75 • MYR: t3myr and q76–q83 • YER: t3yer and q84–q96 • AR: t3ar and q97–q102
B47: Stage | C47: Stage of the budget cycle assessed by the indicator | D47: Category | E47: All Stages, Formulation, Approval, Execution, Oversight | F47: Stage classification: • All Stages: q64–q67, q131, q135 • Formulation: t3pbs, t3ebp, q1–q58, q107, q125–q127, q132, q134 • Approval: t3eb, q59–q63, q108–q113, q136–q138 • Execution: t3iyr, t3myr, t3yer, q68–q96, q114–q117, q128–q130, q133 • Oversight: t3ar, q97–q102, q103–q106 (IFI), q118–q124, q139–q142c
B48: Topic | C48: Thematic classification of the indicator | D48: Category | E48: Timeliness, Expenditure, Revenue, Debt, Macroeconomic, Policy & Performance, Fiscal Risk, Timetable, Citizens Version, Audit, SAI, Legislature, IFI, Executive, Line Ministries | F48: Topic mapping: • Timeliness: t3pbs, t3ebp, t3eb, t3iyr, t3myr, t3yer, t3ar • Expenditure: q1–q8, q19–q24, q55, q58–q60, q68–q70, q77–q79, q84–q86 • Revenue: q9–q12, q25–q30, q56, q61–q62, q71–q73, q80–q82, q87–q89 • Debt: q13–q14, q31–q32, q57, q63, q74–q75, q83, q90 • Macroeconomic: q15–q16, q54, q76, q91 • Policy & Performance: q17–q18, q36, q47–q52, q92–q94 • Fiscal Risk: q33–q35, q37–q46, q95–q96 • Timetable: q53 • Citizens Version: q64–q67 • Audit: q97–q102 • SAI: q119–q124, q140–q142 • Legislature: q107–q118, q136–q139 • IFI: q103–q106 • Executive: q125–q134 • Line Ministries: q135
B49: Question | C49: Full text of the OBS questionnaire | D49: Text | F49: Multiple-choice response options are not included here. See the question mapping tab for response options.
B50: Country | C50: Country name | D50: Text
B51: ISO | C51: Alpha-3 ISO country code | D51: Text | E51: e.g., ALB, BIH, XKX, MNE, MKD, SRB, TUR
B52: Year | C52: OBS survey year | D52: Number | E52: 2025 (in this launch) | F52: Currently includes only the 2025 round.
B53: Score | C53: Numerical score (0–100) assigned to the indicator | D53: Number (0–100) | F53: Derived from the selected multiple-choice response.
B54: Response | C54: Selected multiple-choice answer | D54: Text | F54: Recorded exactly as selected in the survey instrument.
B55: Source | C55: Source(s) supporting the assigned score | D55: Text | F55: Typically includes URLs, official documents, and page references.
B56: Comment | C56: Researcher’s explanation and evidence supporting the assigned score | D56: Text | F56: The untransformed comment from the researcher prior to external review used to support the score.
B57: GR_Opinion | C57: Government reviewer’s formal position (Agree / Disagree) during the review process | D57: Categorical | E57: Agree, Disagree | F57: Blank values typically indicate no government review was submitted.
B58: GR_Sugg_Answer | C58: Government reviewer’s suggested alternative response | D58: Text | E58: Multiple-choice selection | F58: Completed if the government reviewer disagrees with the original response.
B59: GR_Comment | C59: Government reviewer's supporting comment | D59: Text | F59: May include additional evidence or contextual information, whether agreeing or disagreeing
B60: Res_2nd_Response | C60: Researcher response following external review and internal consistency checks | D60: Text | F60: Original researcher comments are not edited. This field captures post-review clarifications or responses to government feedback.
B61: IBP_Comment | C61: IBP adjudication or final comment | D61: Text | F61: Final IBP comment or adjudication note, documenting the final determination and explaining any score revisions made during the second review phase.
B64: General_Questions_UI_Codebook
B66: Variable / Pattern | C66: Description | D66: Type | E66: Values / Coding | F66: Notes
B67: gq-1a – gq-3 | C67: General questions (not scored) | D67: Varies | F67: Exploratory questions included for informational purposes only. Not scored. Not included in any composite index. Not subject to the same consistency review process as scored indicators.
B68: cb-1a | C68: Which of the 7 key budget documents have a corresponding citizens version | D68: Multi-Choice Selection | F68: Not included in composite indices, for informational purposes only.

Sheet Question_Map
B1: To users as you will notice most indicators will have five response options (A through E), while some will have three (A through C). > ABC_SET = q2-q5, q11, q21, q25, q27, q28, q34, q58, q61, q70, q71, q73, q81, q88, q96, q100, q119, q120, q126, q129, q134, q140, q142 > All else are the five response options (A through E)
B4: Indicator | C4: Topic | D4: Question | E4: A | F4: B | G4: C | H4: D | I4: E
B5: PBS-2 | C5: Transparency - Pre-Budget Statement | D5: When is the Pre-Budget Statement made available to the public? | E5: At least four months in advance of the budget year, and at least one month before the executive’s budget proposal is introduced in the legislature | F5: At least two months, but less than four months, in advance of the budget year, and at least one month before the executive’s budget proposal is introduced in the legislature | G5: Less than two months in advance of the budget year, but at least one month before the executive’s budget proposal is introduced in the legislature | H5: Does not release to the public, or is released less than one month before the executive’s budget proposal is introduced to the legislature
B6: EBP-2 | C6: Transparency - Executive's Budget Proposal | D6: When is the Executive Budget Proposal made available to the public? | E6: At least three months in advance of the budget year, and in advance of the budget being approved by the legislature | F6: At least two months, but less than three months, in advance of the budget year, and in advance of the budget being approved by the legislature | G6: Less than two months in advance of the budget year, but at least in advance of the budget being approved by the legislature | H6: Does not release to the public, or is released after the budget has been approved by the legislature
B7: EB-2 | C7: Transparency - Enacted Budget | D7: When is the Enacted Budget made available to the public? | E7: Two weeks or less after the budget has been enacted | F7: Between two weeks and six weeks after the budget has been enacted | G7: More than six weeks, but less than three months, after the budget has been enacted | H7: Does not release to the public, or is released more than three months after the budget has been enacted
B8: IYRs-2 | C8: Transparency - In-Year Reports | D8: When are In-Year Reports made available to the public? | E8: At least every month, and within one month of the period covered | F8: At least every quarter, and within three months of the period covered | G8: At least semi-annually, and within three months of the period covered | H8: Does not release to the public
B9: MYR-2 | C9: Transparency - Mid-Year Review | D9: How long after the mid-point in the fiscal year (i.e., six months into the fiscal year) is the Mid-Year Review made available to the public? | E9: Six weeks or less after the mid-point | F9: Nine weeks or less, but more than six weeks, after the mid-point | G9: More than nine weeks, but less than three months, after the mid-point | H9: Does not release to the public, or is released more than three months after the mid-point
B10: YER-2 | C10: Transparency - Year-End Report | D10: How long after the end of the budget year is the Year-End Report made available to the public? | E10: Six months or less after the end of the budget year | F10: Nine months or less, but more than six months, after the end of the budget year | G10: More than nine months, but within 12 months, after the end of the budget year | H10: Does not release to the public, or is released more than 12 months after the end of the budget year
B11: AR-2 | C11: Transparency - Audit Report | D11: How long after the end of the fiscal year are the final annual expenditures of national departments audited and released (except for secret programs)? | E11: Six months or less after the end of the budget year | F11: 12 months or less, but more than six months, after the end of the budget year | G11: More than 12 months, but within 18 months, after the end of the budget year | H11: Does not release to the public, or is released more than 18 months after the end of the budget year
B12: 1 | C12: Transparency - Executive's Budget Proposal | D12: Does the Executive’s Budget Proposal or any supporting budget documentation present expenditures for the budget year that are classified by administrative unit (that is, by ministry, department, or agency)? | E12: Yes, administrative units accounting for all expenditures are presented. | F12: Yes, administrative units accounting for at least two-thirds of, but not all, expenditures are presented. | G12: Yes, administrative units accounting for less than two-thirds of expenditures are presented. | H12: No, expenditures are not presented by administrative unit. | I12: Not applicable/other (please comment).
B13: 2 | C13: Transparency - Executive's Budget Proposal | D13: Does the Executive’s Budget Proposal or any supporting budget documentation present expenditures for the budget year by functional classification? | E13: Yes, expenditures are presented by functional classification. | F13: No, expenditures are not presented by functional classification. | G13: Not applicable/other (please comment).
B14: 3 | C14: Transparency - Executive's Budget Proposal | D14: If the Executive’s Budget Proposal or any supporting budget documentation presents expenditures for the budget year by functional classification, is the functional classification compatible with international standards? | E14: Yes, the functional classification is compatible with international standards. | F14: No, the functional classification is not compatible with international standards, or expenditures are not presented by functional classification. | G14: Not applicable/other (please comment).
B15: 4 | C15: Transparency - Executive's Budget Proposal | D15: Does the Executive’s Budget Proposal or any supporting budget documentation present expenditures for the budget year by economic classification? | E15: Yes, expenditures are presented by economic classification. | F15: No, expenditures are not presented by economic classification. | G15: Not applicable/other (please comment).
B16: 5 | C16: Transparency - Executive's Budget Proposal | D16: If the Executive’s Budget Proposal or any supporting budget documentation presents expenditures for the budget year by economic classification, is the economic classification compatible with international standards? | E16: Yes, the economic classification is compatible with international standards. | F16: No, the economic classification is not compatible with international standards, or expenditures are not presented by economic classification. | G16: Not applicable/other (please comment).
B17: 6 | C17: Transparency - Executive's Budget Proposal | D17: Does the Executive’s Budget Proposal or any supporting budget documentation present expenditures for individual programs for the budget year? | E17: Yes, programs accounting for all expenditures are presented. | F17: Yes, programs accounting for at least two-thirds of, but not all, expenditures are presented. | G17: Yes, programs accounting for less than two-thirds of expenditures are presented. | H17: No, expenditures are not presented by program. | I17: Not applicable/other (please comment).
B18: 7 | C18: Transparency - Executive's Budget Proposal | D18: Does the Executive’s Budget Proposal or any supporting budget documentation present expenditure estimates for a multi-year period (at least two-years beyond the budget year) by any of the three expenditure classifications (by administrative, economic, or functional classification)? | E18: Yes, multi-year expenditure estimates are presented by all three expenditure classifications (by administrative, economic, and functional classification). | F18: Yes, multi-year expenditure estimates are presented by two of the three expenditure classifications. | G18: Yes, multi-year expenditure estimates are presented by only one of the three expenditure classifications. | H18: No, multi-year expenditure estimates are not presented by any expenditure classification. | I18: Not applicable/other (please comment).
B19: 8 | C19: Transparency - Executive's Budget Proposal | D19: Does the Executive’s Budget Proposal or any supporting budget documentation present expenditure estimates for a multi-year period (at least two-years beyond the budget year) by program? | E19: Yes, multi-year estimates for programs accounting for all expenditures are presented. | F19: Yes, multi-year estimates for programs accounting for at least two-thirds of, but not all, expenditures are presented. | G19: Yes, multi-year estimates for programs accounting for less than two-thirds of expenditures are presented. | H19: No, multi-year estimates for programs are not presented. | I19: Not applicable/other (please comment).
B20: 9 | C20: Transparency - Executive's Budget Proposal | D20: Does the Executive’s Budget Proposal or any supporting budget documentation present the individual sources of tax revenue (such as income tax or VAT) for the budget year? | E20: Yes, individual sources of tax revenue accounting for all tax revenue are presented. | F20: Yes, individual sources of tax revenue accounting for at least two-thirds of, but not all, tax revenues are presented. | G20: Yes, individual sources of tax revenue accounting for less than two-thirds of all tax revenues are presented. | H20: No, individual sources of tax revenue are not presented. | I20: Not applicable/other (please comment).
B21: 10 | C21: Transparency - Executive's Budget Proposal | D21: Does the Executive’s Budget Proposal or any supporting budget documentation present the individual sources of non-tax revenue (such as grants, property income, and sales of government-produced goods and services) for the budget year? | E21: Yes, individual sources of non-tax revenue accounting for all non-tax revenue are presented. | F21: Yes, individual sources of non-tax revenue accounting for at least two-thirds of, but not all, non-tax revenues are presented. | G21: Yes, individual sources of non-tax revenue accounting for less than two-thirds of all non-tax revenues are presented. | H21: No, individual sources of non-tax revenue are not presented. | I21: Not applicable/other (please comment).
B22: 11 | C22: Transparency - Executive's Budget Proposal | D22: Does the Executive’s Budget Proposal or any supporting budget documentation present revenue estimates by category (such as tax and non-tax) for a multi-year period (at least two-years beyond the budget year)? | E22: Yes, multi-year estimates of revenue are presented by category. | F22: No, multi-year estimates of revenue are not presented by category. | G22: Not applicable/other (please comment).
B23: 12 | C23: Transparency - Executive's Budget Proposal | D23: Does the Executive’s Budget Proposal or any supporting budget documentation present estimates for individual sources of revenue presented for a multi-year period (at least two-years beyond the budget year)? | E23: Yes, multi-year estimates for individual sources of revenue accounting for all revenue are presented. | F23: Yes, multi-year estimates for individual sources of revenue accounting for at least two-thirds of, but not all, revenue are presented. | G23: Yes, multi-year estimates for individual sources of revenue accounting for less than two-thirds of revenue are presented. | H23: No, multi-year estimates for individual sources of revenue are not presented. | I23: Not applicable/other (please comment).
B24: 13 | C24: Transparency - Executive's Budget Proposal | D24: Does the Executive’s Budget Proposal or any supporting budget documentation present three estimates related to government borrowing and debt: the amount of net new borrowing required during the budget year; the total debt outstanding at the end of the budget year; and interest payments on the debt for the budget year? | E24: Yes, all three estimates related to government borrowing and debt are presented. | F24: Yes, two of the three estimates related to government borrowing and debt are presented. | G24: Yes, one of the three estimates related to government borrowing and debt are presented. | H24: No, none of the three estimates related to government borrowing and debt are not presented. | I24: Not applicable/other (please comment).
B25: 14 | C25: Transparency - Executive's Budget Proposal | D25: Does the Executive’s Budget Proposal or any supporting budget documentation present information related to the composition of the total debt outstanding at the end of the budget year? (The core information must include interest rates on the debt instruments; maturity profile of the debt; and whether it is domestic or external debt.) | E25: Yes, information beyond the core elements is presented for the composition of the total debt outstanding. | F25: Yes, the core information is presented for the composition of the total debt outstanding. | G25: Yes, information is presented, but it excludes some core elements. | H25: No, information related to composition of total debt outstanding is not presented. | I25: Not applicable/other (please comment).
B26: 15 | C26: Transparency - Executive's Budget Proposal | D26: Does the Executive’s Budget Proposal or any supporting budget documentation present information on the macroeconomic forecast upon which the budget projections are based? (The core information must include a discussion of the economic outlook with estimates of nominal GDP level, inflation rate, real GDP growth, and interest rates.) | E26: Yes, information beyond the core elements is presented for the macroeconomic forecast. | F26: Yes, the core information is presented for the macroeconomic forecast. | G26: Yes, information is presented, but it excludes some core elements. | H26: No, information related to the macroeconomic forecast is not presented. | I26: Not applicable/other (please comment).
B27: 16 | C27: Transparency - Executive's Budget Proposal | D27: Does the Executive’s Budget Proposal or any supporting budget documentation show the impact of different macroeconomic assumptions (i.e., sensitivity analysis) on the budget? (The core information must include estimates of the impact on expenditures, revenue, and debt of different assumptions for the inflation rate, real GDP growth, and interest rates.) | E27: Yes, information beyond the core elements is presented to show the impact of different macroeconomic assumptions on the budget. | F27: Yes, the core information is presented to show the impact of different macroeconomic assumptions on the budget. | G27: Yes, information is presented, but it excludes some core elements. | H27: No, information related to different macroeconomic assumptions is not presented. | I27: Not applicable/other (please comment).
B28: 17 | C28: Transparency - Executive's Budget Proposal | D28: Does the Executive’s Budget Proposal or any supporting budget documentation present information for at least the budget year that shows how new policy proposals, as distinct from existing policies, affect expenditures? | E28: Yes, estimates that show how all new policy proposals affect expenditures are presented, along with a narrative discussion. | F28: Yes, estimates that show how all new policy proposals affect expenditures are presented, but a narrative discussion is not included. | G28: Yes, information that shows how some but not all new policy proposals affect expenditure is presented. | H28: No, information that shows how new policy proposals affect expenditure is not presented. | I28: Not applicable/other (please comment).
B29: 18 | C29: Transparency - Executive's Budget Proposal | D29: Does the Executive’s Budget Proposal or any supporting budget documentation present information for at least the budget year that shows how new policy proposals, as distinct from existing policies, affect revenues? | E29: Yes, estimates that show how all new policy proposals affect revenues are presented, along with a narrative discussion. | F29: Yes, estimates that show how all new policy proposals affect revenues are presented, but a narrative discussion is not included. | G29: Yes, information that shows how some but not all new policy proposals affect revenues are presented. | H29: No, information that shows how new policy proposals affect revenues is not presented. | I29: Not applicable/other (please comment).
B30: 19 | C30: Transparency - Executive's Budget Proposal | D30: Does the Executive’s Budget Proposal or any supporting budget documentation present expenditures for the year preceding the budget year (BY-1) by any of the three expenditure classifications (by administrative, economic, or functional classification)? | E30: Yes, expenditure estimates for BY-1 are presented by all three expenditure classifications (by administrative, economic, and functional classification). | F30: Yes, expenditure estimates for BY-1 are presented by two of the three expenditure classifications. | G30: Yes, expenditure estimates for BY-1 are presented by only one of the three expenditure classifications. | H30: No, expenditure estimates for BY-1 are not presented by any expenditure classification. | I30: Not applicable/other (please comment).
B31: 20 | C31: Transparency - Executive's Budget Proposal | D31: Does the Executive’s Budget Proposal or any supporting budget documentation present expenditures for individual programs for the year preceding the budget year (BY-1)? | E31: Yes, programs accounting for all expenditures are presented for BY-1. | F31: Yes, programs accounting for at least two-thirds of, but not all, expenditures are presented for BY-1. | G31: Yes, programs accounting for less than two-thirds of expenditures are presented for BY-1. | H31: No, expenditures are not presented by program for BY-1. | I31: Not applicable/other (please comment).
B32: 21 | C32: Transparency - Executive's Budget Proposal | D32: In the Executive’s Budget Proposal or any supporting budget documentation, have expenditure estimates of the year prior to the budget year (BY-1) been updated from the original enacted levels to reflect actual expenditures? | E32: Yes, expenditure estimates for BY-1 have been updated from the original enacted levels. | F32: No, expenditure estimates for BY-1 have not been updated from the original enacted levels. | G32: Not applicable/other (please comment).
B33: 22 | C33: Transparency - Executive's Budget Proposal | D33: Does the Executive’s Budget Proposal or any supporting budget documentation present estimates of expenditure for more than one year prior to the budget year (that is, BY-2 and prior years) by any of the three expenditure classifications (by administrative, economic, or functional classification)? | E33: Yes, expenditure estimates for BY-2 and prior years are presented by all three expenditure classifications (by administrative, economic, and functional classification). | F33: Yes, expenditure estimates for BY-2 and prior years are presented by two of the three expenditure classifications. | G33: Yes, expenditure estimates for BY-2 and prior years are presented by only one of the three expenditure classifications. | H33: No, expenditure estimates for BY-2 and prior years are not presented by any expenditure classification. | I33: Not applicable/other (please comment).
B34: 23 | C34: Transparency - Executive's Budget Proposal | D34: Does the Executive’s Budget Proposal or any supporting budget documentation present expenditures for individual programs for more than one year preceding the budget year (that is, BY-2 and prior years)? | E34: Yes, programs accounting for all expenditures are presented for BY-2 and prior years. | F34: Yes, programs accounting for at least two-thirds of, but not all, expenditures are presented for BY-2 and prior years. | G34: Yes, programs accounting for less than two-thirds of expenditures are presented for BY-2 and prior years. | H34: No, expenditures are not presented by program for BY-2 and prior years. | I34: Not applicable/other (please comment).
B35: 24 | C35: Transparency - Executive's Budget Proposal | D35: In the Executive’s Budget Proposal or any supporting budget documentation, what is the most recent year presented for which all expenditures reflect actual outcomes? | E35: Two years prior to the budget year (BY-2). | F35: Three years prior to the budget year (BY-3). | G35: Before BY-3. | H35: No actual data for all expenditures are presented in the budget or supporting budget documentation. | I35: Not applicable/other (please comment).
B36: 25 | C36: Transparency - Executive's Budget Proposal | D36: Does the Executive’s Budget Proposal or any supporting budget documentation present revenue by category (such as tax and non-tax) for the year preceding the budget year (BY-1)? | E36: Yes, revenue estimates for BY-1 are presented by category. | F36: No, revenue estimates for BY-1 are not presented by category. | G36: Not applicable/other (please comment).
B37: 26 | C37: Transparency - Executive's Budget Proposal | D37: Does the Executive’s Budget Proposal or any supporting budget documentation present individual sources of revenue for the year preceding the budget year (BY-1)? | E37: Yes, individual sources of revenue accounting for all revenue are presented for BY-1. | F37: Yes, individual sources of revenue accounting for at least two-thirds of, but not all, revenue for BY-1 are presented. | G37: Yes, individual sources of revenue accounting for less than two-thirds of all revenues for BY-1 are presented. | H37: No, individual sources of revenue are not presented for BY-1. | I37: Not applicable/other (please comment).
B38: 27 | C38: Transparency - Executive's Budget Proposal | D38: In the Executive’s Budget Proposal or any supporting budget documentation, have the original estimates of revenue for the year prior to the budget year (BY-1) been updated to reflect actual revenue collections? | E38: Yes, revenue estimates for BY-1 have been updated from the original enacted levels. | F38: No, revenue estimates for BY-1 have not been updated from the original enacted levels. | G38: Not applicable/other (please comment).
B39: 28 | C39: Transparency - Executive's Budget Proposal | D39: Does the Executive’s Budget Proposal or any supporting budget documentation present revenue estimates by category (such as tax and non-tax) for more than one year prior to the budget year (that is, BY-2 and prior years)? | E39: Yes, revenue estimates for BY-2 and prior years are presented by category. | F39: No, revenue estimates for BY-2 and prior years are not presented by category. | G39: Not applicable/other (please comment).
B40: 29 | C40: Transparency - Executive's Budget Proposal | D40: Does the Executive’s Budget Proposal or any supporting budget documentation present individual sources of revenue for more than one year prior to the budget year (that is, BY-2 and prior years)? | E40: Yes, individual sources of revenue accounting for all revenue are presented for BY-2 and prior years. | F40: Yes, individual sources of revenue accounting for at least two-thirds of, but not all, revenue are presented for BY-2 and prior years. | G40: Yes, individual sources of revenue accounting for less than two-thirds of all revenues are presented for BY-2 and prior years. | H40: No, individual sources of revenue are not presented for BY-2 and prior years. | I40: Not applicable/other (please comment).
B41: 30 | C41: Transparency - Executive's Budget Proposal | D41: In the Executive’s Budget Proposal or any supporting budget documentation, what is the most recent year presented for which all revenues reflect actual outcomes? | E41: Two years prior to the budget year (BY-2). | F41: Three years prior to the budget year (BY-3). | G41: Before BY-3. | H41: No actual data for all revenues are presented in the budget or supporting budget documentation. | I41: Not applicable/other (please comment).
B42: 31 | C42: Transparency - Executive's Budget Proposal | D42: Does the Executive’s Budget Proposal or any supporting budget documentation present information on government borrowing and debt, including its composition, for the year preceding the budget year (BY-1)? (The core information must include the total debt outstanding at the end of BY-1; the amount of net new borrowing required during BY-1; interest payments on the debt; interest rates on the debt instruments; maturity profile of the debt; and whether it is domestic or external debt.) | E42: Yes, information beyond the core elements is presented for government debt. | F42: Yes, the core information is presented for government debt. | G42: Yes, information is presented, but it excludes some core elements. | H42: No, information related to government debt is not presented. | I42: Not applicable/other (please comment).
B43: 32 | C43: Transparency - Executive's Budget Proposal | D43: In the Executive’s Budget Proposal or any supporting budget documentation, what is the most recent year presented for which the debt figures reflect actual outcomes? | E43: Two years prior to the budget year (BY-2). | F43: Three years prior to the budget year (BY-3). | G43: Before BY-3. | H43: No actual data for government debt are presented in the budget or supporting budget documentation. | I43: Not applicable/other (please comment).
B44: 33 | C44: Transparency - Executive's Budget Proposal | D44: Does the Executive’s Budget Proposal or any supporting budget documentation present information on extra-budgetary funds for at least the budget year? (The core information must include a statement of purpose or policy rationale for the extra-budgetary fund; and complete income, expenditure, and financing data on a gross basis.) | E44: Yes, information beyond the core elements is presented for all extra-budgetary funds. | F44: Yes, the core information is presented for all extra-budgetary funds. | G44: Yes, information is presented, but it excludes some core elements or some extra-budgetary funds. | H44: No, information related to extra-budgetary funds is not presented. | I44: Not applicable/other (please comment).
B45: 34 | C45: Transparency - Executive's Budget Proposal | D45: Does the Executive’s Budget Proposal or any supporting budget documentation present central government finances (both budgetary and extra-budgetary) on a consolidated basis for at least the budget year? | E45: Yes, central government finances are presented on a consolidated basis. | F45: No, central government finances are not presented on a consolidated basis. | G45: Not applicable/other (please comment).
B46: 35 | C46: Transparency - Executive's Budget Proposal | D46: Does the Executive’s Budget Proposal or any supporting budget documentation present estimates of intergovernmental transfers for at least the budget year? | E46: Yes, estimates of all intergovernmental transfers are presented, along with a narrative discussion. | F46: Yes, estimates of all intergovernmental transfers are presented, but a narrative discussion is not included. | G46: Yes, estimates of some but not all intergovernmental transfers are presented. | H46: No, estimates of intergovernmental transfers are not presented. | I46: Not applicable/other (please comment).
B47: 36 | C47: Transparency - Executive's Budget Proposal | D47: Does the Executive’s Budget Proposal or any supporting budget documentation present alternative displays of expenditures (such as by gender, by age, by income, or by region) to illustrate the financial impact of policies on different groups of citizens, for at least the budget year? | E47: Yes, at least three alternative displays of expenditures are presented to illustrate the financial impact of policies on different groups of citizens. | F47: Yes, two alternative displays of expenditures are presented to illustrate the financial impact of policies on different groups of citizens. | G47: Yes, one alternative display of expenditures is presented to illustrate the financial impact of policies on different groups of citizens. | H47: No, alternative displays of expenditures are not presented to illustrate the financial impact of policies on different groups of citizens. | I47: Not applicable/other (please comment).
B48: 37 | C48: Transparency - Executive's Budget Proposal | D48: Does the Executive’s Budget Proposal or any supporting budget documentation present estimates of transfers to public corporations for at least the budget year? | E48: Yes, estimates of all transfers to public corporations are presented, along with a narrative discussion. | F48: Yes, estimates of all transfers to public corporations are presented, but a narrative discussion is not included. | G48: Yes, estimates of some but not all transfers to public corporations are presented. | H48: No, estimates of transfers to public corporations are not presented. | I48: Not applicable/other (please comment).
B49: 38 | C49: Transparency - Executive's Budget Proposal | D49: Does the Executive’s Budget Proposal or any supporting budget documentation present information on quasi-fiscal activities for at least the budget year? (The core information must include a statement of purpose or policy rationale for the quasi-fiscal activity and the intended beneficiaries.) | E49: Yes, information beyond the core elements is presented for all quasi-fiscal activities. | F49: Yes, the core information is presented for all quasi-fiscal activities. | G49: Yes, information is presented, but it excludes some core elements or some quasi-fiscal activities. | H49: No, information related to quasi-fiscal activities is not presented. | I49: Not applicable/other (please comment).
B50: 39 | C50: Transparency - Executive's Budget Proposal | D50: Does the Executive’s Budget Proposal or any supporting budget documentation present information on financial assets held by the government? (The core information must include a listing of the assets, and an estimate of their value.) | E50: Yes, information beyond the core elements is presented for all financial assets. | F50: Yes, the core information is presented for all financial assets. | G50: Yes, information is presented, but it excludes some core elements or some financial assets. | H50: No, information related to financial assets is not presented. | I50: Not applicable/other (please comment).
B51: 40 | C51: Transparency - Executive's Budget Proposal | D51: Does the Executive’s Budget Proposal or any supporting budget documentation present information on nonfinancial assets held by the government? (The core information must include a listing of the assets by category.) | E51: Yes, information beyond the core elements is presented for all nonfinancial assets. | F51: Yes, the core information is presented for all nonfinancial assets. | G51: Yes, information is presented, but it excludes some nonfinancial assets. | H51: No, information related to nonfinancial assets is not presented. | I51: Not applicable/other (please comment).
B52: 41 | C52: Transparency - Executive's Budget Proposal | D52: Does the Executive’s Budget Proposal or any supporting budget documentation present estimates of expenditure arrears for at least the budget year? | E52: Yes, estimates of all expenditure arrears are presented, along with a narrative discussion. | F52: Yes, estimates of all expenditure arrears are presented, but a narrative discussion is not included. | G52: Yes, estimates of some but not all expenditure arrears are presented. | H52: No, estimates of expenditure arrears are not presented. | I52: Not applicable/other (please comment).
B53: 42 | C53: Transparency - Executive's Budget Proposal | D53: Does the Executive’s Budget Proposal or any supporting budget documentation present information on contingent liabilities, such as government loan guarantees or insurance programs? (The core information must include a statement of purpose or policy rationale for each contingent liability; the new guarantees or insurance commitments proposed for the budget year; and the total amount of outstanding guarantees or insurance commitments (the gross exposure) at the end of the budget year.) | E53: Yes, information beyond the core elements is presented for all contingent liabilities. | F53: Yes, the core information is presented for all contingent liabilities. | G53: Yes, information is presented, but it excludes some core elements or some contingent liabilities. | H53: No, information related to contingent liabilities is not presented. | I53: Not applicable/other (please comment).
B54: 43 | C54: Transparency - Executive's Budget Proposal | D54: Does the Executive’s Budget Proposal or any supporting budget documentation present projections that assess the government’s future liabilities and the sustainability of its finances over the longer term? (The core information must cover a period of at least 10 years and include the macroeconomic and demographic assumptions used and a discussion of the fiscal implications and risks highlighted by the projections.) | E54: Yes, information beyond the core elements is presented to assess the government’s future liabilities and the sustainability of its finances over the longer term. | F54: Yes, the core information is presented to assess the government’s future liabilities and the sustainability of its finances over the longer term. | G54: Yes, information is presented, but it excludes some core elements. | H54: No, information related to future liabilities and the sustainability of finances over the longer term is not presented. | I54: Not applicable/other (please comment).
B55: 44 | C55: Transparency - Executive's Budget Proposal | D55: Does the Executive’s Budget Proposal or any supporting budget documentation present estimates of the sources of donor assistance, both financial and in-kind? | E55: Yes, estimates of all sources of donor assistance are presented, along with a narrative discussion. | F55: Yes, estimates of all sources of donor assistance are presented, but a narrative discussion is not included. | G55: Yes, estimates of some but not all sources of donor assistance are presented. | H55: No, estimates of the sources of donor assistance are not presented. | I55: Not applicable/other (please comment).
B56: 45 | C56: Transparency - Executive's Budget Proposal | D56: Does the Executive’s Budget Proposal or any supporting budget documentation present information on tax expenditures for at least the budget year? (The core information must include a statement of purpose or policy rationale for each tax expenditure, the intended beneficiaries, and an estimate of the revenue foregone.) | E56: Yes, information beyond the core elements is presented for all tax expenditures. | F56: Yes, the core information is presented for all tax expenditures. | G56: Yes, information is presented, but it excludes some core elements or some tax expenditures. | H56: No, information related to tax expenditures is not presented. | I56: Not applicable/other (please comment).
B57: 46 | C57: Transparency - Executive's Budget Proposal | D57: Does the Executive’s Budget Proposal or any supporting budget documentation present estimates of earmarked revenues? | E57: Yes, estimates of all earmarked revenues are presented, along with a narrative discussion. | F57: Yes, estimates of all earmarked revenues are presented, but a narrative discussion is not included. | G57: Yes, estimates of some but not all earmarked revenues are presented. | H57: No, estimates of earmarked revenues are not presented. | I57: Not applicable/other (please comment).
... B68: 57 | C68: Transparency - Pre-Budget Statement | D68: Does Pre-Budget Statement present three estimates related to government borrowing and debt: the amount of net new borrowing required during the budget year; the total debt outstanding at the end of the budget year; and interest payments on the debt for the budget year? | E68: Yes, all three estimates related to government borrowing and debt are presented. | F68: Yes, two of the three estimates related to government borrowing and debt are presented. | G68: Yes, one of the three estimates related to government borrowing and debt are presented. | H68: No, none of the three estimates related to government borrowing and debt are not presented. | I68: Not applicable/other (please comment).
B69: 58 | C69: Transparency - Pre-Budget Statement | D69: Does the Pre-Budget Statement present estimates of total expenditures for a multi-year period (at least two-years beyond the budget year)? | E69: Yes, multi-year expenditure estimates are presented. | F69: No, multi-year expenditure estimates are not presented. | G69: Not applicable/other (please comment).
B70: 59 | C70: Transparency - Enacted Budget | D70: Does the Enacted Budget present expenditure estimates by any of the three expenditure classifications (by administrative, economic, or functional classification)? | E70: Yes, the Enacted Budget presents expenditure estimates by all three expenditure classifications (by administrative, economic, and functional classification). | F70: Yes, the Enacted Budget presents expenditure estimates by two of the three expenditure classifications. | G70: Yes, the Enacted Budget presents expenditure estimates by only one of the three expenditure classifications. | H70: No, the Enacted Budget does not present expenditure estimates by any expenditure classification. | I70: Not applicable/other (please comment).
B71: 60 | C71: Transparency - Enacted Budget | D71: Does the Enacted Budget present expenditure estimates for individual programs? | E71: Yes, the Enacted Budget presents estimates for programs accounting for all expenditures. | F71: Yes, the Enacted Budget presents estimates for programs accounting for at least two-thirds of, but not all, expenditures. | G71: Yes, the Enacted Budget presents estimates for programs accounting for less than two-thirds of expenditures. | H71: No, the Enacted Budget does not present expenditure estimates by program. | I71: Not applicable/other (please comment).
B72: 61 | C72: Transparency - Enacted Budget | D72: Does the Enacted Budget present revenue estimates by category (such as tax and non-tax)? | E72: Yes, the Enacted Budget presents revenue estimates by category. | F72: No, the Enacted Budget does not present revenue estimates by category. | G72: Not applicable/other (please comment).
B73: 62 | C73: Transparency - Enacted Budget | D73: Does the Enacted Budget present individual sources of revenue? | E73: Yes, the Enacted Budget presents individual sources of revenue accounting for all revenue. | F73: Yes, the Enacted Budget presents individual sources of revenue accounting for at least two-thirds of, but not all, revenue. | G73: Yes, the Enacted Budget presents individual sources of revenue accounting for less than two-thirds of all revenues. | H73: No, the Enacted Budget does not present individual sources of revenue. | I73: Not applicable/other (please comment).
B74: 63 | C74: Transparency - Enacted Budget | D74: Does the Enacted Budget present three estimates related to government borrowing and debt: the amount of net new borrowing required during the budget year; the total debt outstanding at the end of the budget year; and interest payments on the debt for the budget year? | E74: Yes, all three estimates related to government borrowing and debt are presented. | F74: Yes, two of the three estimates related to government borrowing and debt are presented. | G74: Yes, one of the three estimates related to government borrowing and debt are presented. | H74: No, none of the three estimates related to government borrowing and debt are not presented. | I74: Not applicable/other (please comment).
B75: 64 | C75: Transparency - Citizens Budget | D75: What information is provided in the Citizens Budget? (The core information must include expenditure and revenue totals, the main policy initiatives in the budget, the macroeconomic forecast upon which the budget is based, and contact information for follow-up by citizens.) | E75: The Citizens Budget provides information beyond the core elements. | F75: The Citizens Budget provides the core information. | G75: The Citizens Budget provides information, but it excludes some core elements. | H75: The Citizens Budget is not published. | I75: Not applicable/other (please comment).
B76: 65 | C76: Transparency - Citizens Budget | D76: How is the Citizens Budget disseminated to the public? | E76: A Citizens Budget is disseminated widely through a combination of at least three different appropriate tools and media (such as the Internet, billboards, radio programs, newspapers, etc.). | F76: A Citizens Budget is published by using at least two, but less than three, means of dissemination, but no other dissemination efforts are undertaken by the executive. | G76: A Citizens Budget is disseminated only by using one means of dissemination. | H76: A Citizens Budget is not published. | I76: Not applicable/other (please comment).
B77: 66 | C77: Transparency - Citizens Budget | D77: Has the executive established mechanisms to identify the public’s requirements for budget information prior to publishing the Citizens Budget? | E77: Yes, the executive has established mechanisms to identify the public’s requirements for budget information in the Citizen’s Budget, and these mechanisms are accessible and widely used by the public. | F77: Yes, the executive has established mechanisms to identify the public’s requirements for budget information in the Citizen’s Budget; while these mechanisms are accessible they are not widely used by the public. | G77: Yes, the executive has established mechanisms to identify the public’s requirements for budget information in the Citizen’s Budget, but these mechanisms are not accessible. | H77: No, the executive has not established any mechanisms to identify the public’s requirements for budget information in the Citizen’s Budget. | I77: Not applicable/other (please comment).
B78: 67 | C78: Transparency - Citizens Budget | D78: Are “citizens” versions of budget documents published throughout the budget process? | E78: A citizens version of budget documents is published for each of the four stages of the budget process (budget formulation, enactment, execution, and audit). | F78: A citizens version of budget documents is published for at least two of the four stages of the budget process. | G78: A citizens version of budget documents is published for at least one stage of the budget process. | H78: No citizens version of budget documents is published. | I78: Not applicable/other (please comment).
B79: 68 | C79: Transparency - In-Year Reports | D79: Do the In-Year Reports present actual expenditures by any of the three expenditure classifications (by administrative, economic, or functional classification)? | E79: Yes, the In-Year Reports present actual expenditures by all three expenditure classifications (by administrative, economic, and functional classification). | F79: Yes, the In-Year Reports present actual expenditures by two of the three expenditure classifications. | G79: Yes, the In-Year Reports present actual expenditures by only one of the three expenditure classifications. | H79: No, the In-Year Reports do not present actual expenditures by any expenditure classification. | I79: Not applicable/other (please comment).
B80: 69 | C80: Transparency - In-Year Reports | D80: Do the In-Year Reports present actual expenditures for individual programs? | E80: Yes, the In-Year Reports present actual expenditures for programs accounting for all expenditures. | F80: Yes, the In-Year Reports present actual expenditures for programs accounting for at least two-thirds of, but not all, expenditures. | G80: Yes, the In-Year Reports present actual expenditures for programs accounting for less than two-thirds of expenditures. | H80: No, the In-Year Reports do not present actual expenditures by program. | I80: Not applicable/other (please comment).
B81: 70 | C81: Transparency - In-Year Reports | D81: Do the In-Year Reports compare actual year-to-date expenditures with either the original estimate for that period (based on the enacted budget) or the same period in the previous year? | E81: Yes, comparisons are made for expenditures presented in the In-Year Reports. | F81: No, comparisons are not made for expenditures presented in the In-Year Reports. | G81: Not applicable/other (please comment).
B82: 71 | C82: Transparency - In-Year Reports | D82: Do In-Year Reports present actual revenue by category (such as tax and non-tax)? | E82: Yes, In-Year Reports present actual revenue by category. | F82: No, In-Year Reports do not present actual revenue by category. | G82: Not applicable/other (please comment).
B83: 72 | C83: Transparency - In-Year Reports | D83: Do In-Year Reports present the individual sources of revenue for actual revenues collected? | E83: Yes, In-Year Reports present individual sources of actual revenue accounting for all revenue. | F83: Yes, In-Year Reports present individual sources of actual revenue accounting for at least two-thirds of, but not all, revenue. | G83: Yes, In-Year Reports present individual sources of actual revenue accounting for less than two-thirds of all revenue. | H83: No, In-Year Reports do not present individual sources of actual revenue. | I83: Not applicable/other (please comment).
B84: 73 | C84: Transparency - In-Year Reports | D84: Do the In-Year Reports compare actual year-to-date revenues with either the original estimate for that period (based on the enacted budget) or the same period in the previous year? | E84: Yes, comparisons are made for revenues presented in the In-Year Reports. | F84: No, comparisons are not made for revenues presented in the In-Year Reports. | G84: Not applicable/other (please comment).
B85: 74 | C85: Transparency - In-Year Reports | D85: Do In-Year Reports present three estimates related to actual government borrowing and debt: the amount of net new borrowing; the total debt outstanding; and interest payments? | E85: Yes, all three estimates related to government borrowing and debt are presented. | F85: Yes, two of the three estimates related to government borrowing and debt are presented. | G85: Yes, one of the three estimates related to government borrowing and debt are presented. | H85: No, none of the three estimates related to government borrowing and debt are not presented. | I85: Not applicable/other (please comment).
B86: 75 | C86: Transparency - In-Year Reports | D86: Do In-Year Reports present information related to the composition of the total actual debt outstanding? (The core information must include interest rates on the debt instruments; maturity profile of the debt; and whether it is domestic or external debt.) | E86: Yes, information beyond the core elements is presented for the composition of the total actual debt outstanding. | F86: Yes, the core information is presented for the composition of the total actual debt outstanding. | G86: Yes, information is presented, but it excludes some core elements. | H86: No, information related to composition of total actual debt outstanding is not presented. | I86: Not applicable/other (please comment).
B87: 76 | C87: Transparency - Mid-Year Review | D87: Does the Mid-Year Review of the budget include an updated macroeconomic forecast for the budget year underway? | E87: Yes, the estimates for the macroeconomic forecast have been updated, and an explanation of all of the differences between the original and updated forecasts is presented. | F87: Yes, the estimates for macroeconomic forecast have been updated, and an explanation of some of the differences between the original and updated forecasts is presented. | G87: Yes, the estimates for macroeconomic forecast have been updated, but an explanation of the differences between the original and updated forecast is not presented. | H87: No, the estimates for macroeconomic forecast have not been updated. | I87: Not applicable/other (please comment).
B88: 77 | C88: Transparency - Mid-Year Review | D88: Does the Mid-Year Review of the budget include updated expenditure estimates for the budget year underway? | E88: Yes, expenditure estimates have been updated, and an explanation of all of the differences between the original and updated expenditure estimates is presented. | F88: Yes, expenditure estimates have been updated, and an explanation of some of the differences between the original and updated expenditure estimates is presented. | G88: Yes, expenditure estimates have been updated, but an explanation of the differences between the original and updated expenditure estimates is not presented. | H88: No, expenditure estimates have not been updated. | I88: Not applicable/other (please comment).
B89: 78 | C89: Transparency - Mid-Year Review | D89: Does the Mid-Year Review of the budget present expenditure estimates by any of the three expenditure classifications (by administrative, economic, or functional classification)? | E89: Yes, the Mid-Year Review presents expenditure estimates by all three expenditure classifications (by administrative, economic, and functional classification). | F89: Yes, the Mid-Year Review presents expenditure estimates by two of the three expenditure classifications. | G89: Yes, the Mid-Year Review presents expenditure estimates by only one of the three expenditure classifications. | H89: No, the Mid-Year Review does not present expenditure estimates by any expenditure classification. | I89: Not applicable/other (please comment).
B90: 79 | C90: Transparency - Mid-Year Review | D90: Does the Mid-Year Review of the budget present expenditure estimates for individual programs? | E90: Yes, the Mid-Year Review presents estimates for programs accounting for all expenditures. | F90: Yes, the Mid-Year Review presents estimates for programs accounting for at least two-thirds of, but not all, expenditures. | G90: Yes, the Mid-Year Review presents estimates for programs accounting for less than two-thirds of expenditures. | H90: No, the Mid-Year Review does not present expenditure estimates by program. | I90: Not applicable/other (please comment).
B91: 80 | C91: Transparency - Mid-Year Review | D91: Does the Mid-Year Review of the budget include updated revenue estimates for the budget year underway? | E91: Yes, revenue estimates have been updated, and an explanation of all of the differences between the original and updated revenue estimates is presented. | F91: Yes, revenue estimates have been updated, and an explanation of some of the differences between the original and updated revenue estimates is presented. | G91: Yes, revenue estimates have been updated, but an explanation of the differences between the original and updated revenue estimates is not presented. | H91: No, revenue estimates have not been updated. | I91: Not applicable/other (please comment).
B92: 81 | C92: Transparency - Mid-Year Review | D92: Does the Mid-Year Review of the budget present revenue estimates by category (such as tax and non-tax)? | E92: Yes, the Mid-Year Review presents revenue estimates by category. | F92: No, the Mid-Year Review does not present revenue estimates by category. | G92: Not applicable/other (please comment).
B93: 82 | C93: Transparency - Mid-Year Review | D93: Does the Mid-Year Review of the budget present individual sources of revenue? | E93: Yes, the Mid-Year Review presents individual sources of revenue accounting for all revenue. | F93: Yes, the Mid-Year Review presents individual sources of revenue accounting for at least two-thirds of, but not all, revenue. | G93: Yes, the Mid-Year Review presents individual sources of revenue accounting for less than two-thirds of all revenues. | H93: No, the Mid-Year Review does not present individual sources of revenue. | I93: Not applicable/other (please comment).
B94: 83 | C94: Transparency - Mid-Year Review | D94: Does the Mid-Year Review of the budget include updated estimates of government borrowing and debt, including its composition, for the budget year underway? | E94: Yes, estimates of government borrowing and debt have been updated, and information on all of the differences between the original and updated estimates is presented. | F94: Yes, estimates of government borrowing and debt have been updated, and information on some of the differences between the original and updated estimates is presented. | G94: Yes, estimates of government borrowing and debt have been updated, but information on the differences between the original and updated estimates is not presented. | H94: No, estimates of government borrowing and debt have not been updated. | I94: Not applicable/other (please comment).
B95: 84 | C95: Transparency - Year-End Report | D95: Does the Year-End Report present the differences between the enacted levels (including in-year changes approved by the legislature) and the actual outcome for expenditures? | E95: Yes, estimates of the differences between the enacted levels and the actual outcome for all expenditures are presented, along with a narrative discussion. | F95: Yes, estimates of the differences between the enacted levels and the actual outcome for all expenditures are presented, but a narrative discussion is not included. | G95: Yes, estimates of the differences between the enacted levels and the actual outcome for some but not all expenditures are presented. | H95: No, estimates of the differences between the enacted levels and the actual outcome for expenditures are not presented. | I95: Not applicable/other (please comment).
B96: 85 | C96: Transparency - Year-End Report | D96: Does the Year-End Report present expenditure estimates by any of the three expenditure classifications (by administrative, economic, or functional classification)? | E96: Yes, the Year-End Report presents expenditure estimates by all three expenditure classifications (by administrative, economic, and functional classification). | F96: Yes, the Year-End Report presents expenditure estimates by two of the three expenditure classifications. | G96: Yes, the Year-End Report presents expenditure estimates by only one of the three expenditure classifications. | H96: No, the Year-End Report does not present expenditure estimates by any expenditure classification. | I96: Not applicable/other (please comment).
B97: 86 | C97: Transparency - Year-End Report | D97: Does the Year-End Report present expenditure estimates for individual programs? | E97: Yes, the Year-End Report presents estimates for programs accounting for all expenditures. | F97: Yes, the Year-End Report presents estimates for programs accounting for at least two-thirds of, but not all, expenditures. | G97: Yes, the Year-End Report presents estimates for programs accounting for less than two-thirds of expenditures. | H97: No, the Year-End Report does not present expenditure estimates by program. | I97: Not applicable/other (please comment).
B98: 87 | C98: Transparency - Year-End Report | D98: Does the Year-End Report present the differences between the enacted levels (including in-year changes approved by the legislature) and the actual outcome for revenues? | E98: Yes, estimates of the differences between the enacted levels and the actual outcome for all revenues are presented, along with a narrative discussion. | F98: Yes, estimates of the differences between the enacted levels and the actual outcome for all revenues are presented, but a narrative discussion is not included. | G98: Yes, estimates of the differences between the enacted levels and the actual outcome for some but not all revenues are presented. | H98: No, estimates of the differences between the enacted levels and the actual outcome for revenues are not presented. | I98: Not applicable/other (please comment).
B99: 88 | C99: Transparency - Year-End Report | D99: Does the Year-End Report present revenue estimates by category (such as tax and non-tax)? | E99: Yes, the Year-End Report presents revenue estimates by category. | F99: No, the Year-End Report does not present revenue estimates by category. | G99: Not applicable/other (please comment).
B100: 89 | C100: Transparency - Year-End Report | D100: Does the Year-End Report present individual sources of revenue? | E100: Yes, the Year-End Report presents individual sources of revenue accounting for all revenue. | F100: Yes, the Year-End Report presents individual sources of revenue accounting for at least two-thirds of, but not all, revenue. | G100: Yes, the Year-End Report presents individual sources of revenue accounting for less than two-thirds of all revenues. | H100: No, the Year-End Report does not present individual sources of revenue. | I100: Not applicable/other (please comment).
B101: 90 | C101: Transparency - Year-End Report | D101: Does the Year-End Report present the differences between the original estimates of government borrowing and debt, including its composition, for the fiscal year and the actual outcome for that year? | E101: Yes, estimates of the differences between all of the original estimates of government borrowing and debt for the fiscal year and the actual outcome for that year are presented, along with a narrative discussion. | F101: Yes, estimates of the differences between all the original estimates of government borrowing and debt for the fiscal year and the actual outcome for that year are presented, but a narrative discussion is not included. | G101: Yes, estimates of the differences between some but not all of the original estimates of government borrowing and debt for the fiscal year and the actual outcome for that year are presented. | H101: No, estimates of the differences between the original estimates of government borrowing and debt for the fiscal year and the actual outcome for that year is not presented. | I101: Not applicable/other (please comment).
B102: 91 | C102: Transparency - Year-End Report | D102: Does the Year-End Report present the differences between the original macroeconomic forecast for the fiscal year and the actual outcome for that year? | E102: Yes, estimates of the differences between all of the original macroeconomic assumptions for the fiscal year and the actual outcome for that year are presented, along with a narrative discussion. | F102: Yes, estimates of the differences between all the original macroeconomic assumptions for the fiscal year and the actual outcome for that year are presented, but a narrative discussion is not included. | G102: Yes, estimates of the differences between some but not all of the original macroeconomic assumptions for the fiscal year and the actual outcome for that year are presented. | H102: No, estimates of the differences between the original macroeconomic forecast for the fiscal year and the actual outcome for that year is not presented. | I102: Not applicable/other (please comment).
B103: 92 | C103: Transparency - Year-End Report | D103: Does the Year-End Report present the differences between the original estimates of nonfinancial data on inputs and the actual outcome? | E103: Yes, estimates of the differences between all of the original estimates of nonfinancial data on inputs and the actual outcome are presented, along with a narrative discussion. | F103: Yes, estimates of the differences between all of the original estimates of nonfinancial data on inputs and the actual outcome are presented, but a narrative discussion is not included. | G103: Yes, estimate of the differences between some but not all of the original estimates of nonfinancial data on inputs and the actual outcome are presented. | H103: No, estimates of the differences between the original estimates of nonfinancial data on inputs and the actual outcome are not presented. | I103: Not applicable/other (please comment).
B104: 93 | C104: Transparency - Year-End Report | D104: Does the Year-End Report present the differences between the original estimates of nonfinancial data on results and the actual outcome? | E104: Yes, estimates of the differences between all of the original estimates of nonfinancial data on results and the actual outcome are presented, along with a narrative discussion. | F104: Yes, estimates of the differences between all of the original estimates of nonfinancial data on results and the actual outcome are presented, but a narrative discussion is not included. | G104: Yes, estimate of the differences between some but not all of the original estimates of nonfinancial data on results and the actual outcome are presented. | H104: No, estimates of the differences between the original estimates of nonfinancial data on results and the actual outcome are not presented. | I104: Not applicable/other (please comment).
B105: 94 | C105: Transparency - Year-End Report | D105: Does the Year-End Report present the differences between the enacted level of funds for policies (both new proposals and existing policies) that are intended to benefit directly the country’s most impoverished populations and the actual outcome? | E105: Yes, estimates of the differences between the enacted level for all policies that are intended to benefit directly the country’s most impoverished populations and the actual outcome are presented, along with a narrative discussion. | F105: Yes, estimates of the differences between the enacted level for all policies that are intended to benefit directly the country’s most impoverished populations and the actual outcome are presented, but a narrative discussion is not included. | G105: Yes, estimates of the differences between the enacted level for some but not all of the policies that are intended to benefit directly the country’s most impoverished populations and the actual outcome are presented. | H105: No, estimates of the differences between the enacted level for policies that are intended to benefit directly the country’s most impoverished populations and the actual outcome are not presented. | I105: Not applicable/other (please comment).
B106: 95 | C106: Transparency - Year-End Report | D106: Does the Year-End Report present the differences between the original estimates of extra-budgetary funds and the actual outcome? | E106: Yes, estimates of the differences between all of the original estimates of extra-budgetary funds and the actual outcome are presented, along with a narrative discussion. | F106: Yes, estimates of the differences between all of the original estimates of extra-budgetary funds and the actual outcome are presented, but a narrative discussion is not included. | G106: Yes, estimates of the differences between some but not all of the original estimates of extra-budgetary funds and the actual outcome are presented. | H106: No, estimates of the differences between the original estimates of extra-budgetary funds and the actual outcome is not presented. | I106: Not applicable/other (please comment).
B107: 96 | C107: Transparency - Year-End Report | D107: Is a financial statement included as part of the Year-End Report or released as a separate report? | E107: Yes, a financial statement is part of the Year-End Report or is released as a separate report. | F107: No, a financial statement is neither part of the Year-End Report nor released as a separate report. | G107: Not applicable/other (please comment).
B108: 97 | C108: Transparency - Audit Report | D108: What type of audits (compliance, financial, or performance) has the Supreme Audit Institution (SAI) conducted and made available to the public? | E108: The SAI has conducted all three types of audits (compliance, financial, or performance) and made them available to the public. | F108: The SAI has conducted two of the three types of audits, and made them available to the public. | G108: The SAI has conducted one of the three types of audits, and made them available to the public. | H108: The SAI has not conducted any of the three types of audits, or has not made them available to the public. | I108: Not applicable/other (please comment).
B109: 98 | C109: Transparency - Audit Report | D109: What percentage of expenditures within the mandate of the Supreme Audit Institution (SAI) has been audited? | E109: All expenditures within the SAI’s mandate have been audited. | F109: Expenditures representing at least two-thirds of, but not all, expenditures within the SAI’s mandate have been audited. | G109: Expenditures representing less than two-thirds of expenditures within the SAI’s mandate have been audited. | H109: No expenditures have been audited. | I109: Not applicable/other (please comment).
B110: 99 | C110: Transparency - Audit Report | D110: What percentage of extra-budgetary funds within the mandate of the Supreme Audit Institution (SAI) has been audited? | E110: All extra-budgetary funds within the SAI’s mandate have been audited. | F110: Extra-budgetary funds accounting for at least two-thirds of, but not all, expenditures associated with extra-budgetary funds within the SAI’s mandate have been audited. | G110: Extra-budgetary funds accounting for less than two-thirds of expenditures associated with extra-budgetary funds within the SAI’s mandate have been audited. | H110: No extra-budgetary funds have been audited. | I110: Not applicable/other (please comment).
B111: 100 | C111: Transparency - Audit Report | D111: Does the annual Audit Report(s) prepared by the Supreme Audit Institution (SAI) include an executive summary? | E111: Yes, the annual Audit Report(s) includes one or more executive summaries summarizing the report’s content. | F111: No, the annual Audit Report(s) does not include an executive summary. | G111: Not applicable/other (please comment).
B112: 101 | C112: Transparency - Audit Report | D112: Does the executive make available to the public a report on what steps it has taken to address audit recommendations or findings that indicate a need for remedial action? | E112: Yes, the executive reports publicly on what steps it has taken to address audit findings. | F112: Yes, the executive reports publicly on most audit findings. | G112: Yes, the executive reports publicly on some audit findings. | H112: No, the executive does not report on steps it has taken to address audit findings. | I112: Not applicable/other (please comment).
...

Sheet OBS_Data_2006-2025
A1: country | B1: ISO | C1: year | D1: region | E1: comp_region | F1: obi | G1: roundobi | H1: obi_cat | I1: obi_cat2 | J1: obi_cat3 | K1: obi_cat4 | L1: oversight_obi | M1: roundoversight_obi | N1: grade_oversight | O1: leg_obi | P1: roundleg_obi | Q1: grade_leg | R1: sai_obi | S1: roundsai_obi | T1: grade_sai | U1: ifi_obi | V1: roundifi_obi | W1: grade_ifi | X1: pub_eng | Y1: roundpub_eng | Z1: grade_pub_eng | AA1: pbs | AB1: ebp | AC1: eb | AD1: iyr | AE1: myr | AF1: yer | AG1: ar | AH1: cb | AI1: pub_pbs | AJ1: pub_ebp | AK1: pub_eb | AL1: pub_cb | AM1: pub_iyr | AN1: pub_myr | AO1: pub_yer | AP1: pub_ar | AQ1: obi_pbs | AR1: roundobi_pbs | AS1: obi_pbs_cat | AT1: obi_ebp | AU1: roundobi_ebp | AV1: obi_ebp_cat | AW1: obi_eb | AX1: roundobi_eb | AY1: obi_eb_cat | AZ1: obi_cb | BA1: roundobi_cb | BB1: obi_cb_cat | BC1: obi_iyr | BD1: roundobi_iyr | BE1: obi_iyr_cat | BF1: obi_myr | BG1: roundobi_myr | BH1: obi_myr_cat | BI1: obi_yer | BJ1: roundobi_yer | BK1: obi_yer_cat | BL1: obi_ar | BM1: roundobi_ar | BN1: obi_ar_cat | BO1: pbs2 | BP1: ebp2 | BQ1: eb2 | BR1: iyrs2 | BS1: myr2 | BT1: yer2 | BU1: ar2 | BV1: pbs5a | BW1: ebp5a | BX1: eb5a | BY1: iyr5a | BZ1: myr5a | CA1: yer5a | CB1: ar5a | CC1: cb5a | CD1: q1 | CE1: q2 | CF1: q3 | CG1: q4 | CH1: q5 | CI1: q6 | CJ1: q7 | CK1: q8 | CL1: q9 | CM1: q10 | CN1: q11 | CO1: q12 | CP1: q13 | CQ1: q14 | CR1: q15 | CS1: q16 | CT1: q17 | CU1: q18 | CV1: q19 | CW1: q20 | CX1: q21 | CY1: q22 | CZ1: q23 | DA1: q24 | DB1: q25 | DC1: q26 | DD1: q27 | DE1: q28 | DF1: q29 | DG1: q30 | DH1: q31 | DI1: q32 | DJ1: q33 | DK1: q34 | DL1: q35 | DM1: q36 | DN1: q37 | DO1: q38 | DP1: q39 | DQ1: q40 | DR1: q41 | DS1: q42 | DT1: q43 | DU1: q44 | DV1: q45 | DW1: q46 | DX1: q47 | DY1: q48 | DZ1: q49 | EA1: q50 | EB1: q51 | EC1: q52 | ED1: q53 | EE1: q54 | EF1: q55 | EG1: q56 | EH1: q57 | EI1: q58 | EJ1: q59 | EK1: q60 | EL1: q61 | EM1: q62 | EN1: q63 | EO1: q64 | EP1: q65 | EQ1: q66 | ER1: q67 | ES1: q68 | ET1: q69 | EU1: q70 | EV1: q71 | EW1: q72 | EX1: q73 | EY1: q74 | EZ1: q75 | FA1: q76 | FB1: q77 | FC1: q78 | FD1: q79 | FE1: q80 | FF1: q81 | FG1: q82 | FH1: q83 | FI1: q84 | FJ1: q85 | FK1: q86 | FL1: q87 | FM1: q88 | FN1: q89 | FO1: q90 | FP1: q91 | FQ1: q92 | FR1: q93 | FS1: q94 | FT1: q95 | FU1: q96 | FV1: q97 | FW1: q98 | FX1: q99 | FY1: q100 | FZ1: q101 | GA1: q102 | GB1: q103 | GC1: q104 | GD1: q105 | GE1: q106 | GF1: q107 | GG1: q108 | GH1: q109 | GI1: q110 | GJ1: q111 | GK1: q112 | GL1: q113 | GM1: q114 | GN1: q115 | GO1: q116 | GP1: q117 | GQ1: q118 | GR1: q119 | GS1: q120 | GT1: q121 | GU1: q122 | GV1: q123 | GW1: q124 | GX1: q125 | GY1: q126 | GZ1: q127 | HA1: q128 | HB1: q129 | HC1: q130 | HD1: q131 | HE1: q132 | HF1: q133 | HG1: q134 | HH1: q135 | HI1: q136 | HJ1: q137 | HK1: q138 | HL1: q139 | HM1: q140 | HN1: q141 | HO1: q142 | HP1: t3pbs | HQ1: t3ebp | HR1: t3eb | HS1: t3iyr | HT1: t3myr | HU1: t3yer | HV1: t3ar | HW1: new25 | HX1: comp0612 | HY1: comp0812 | HZ1: comp1012 | IA1: comp1215 | IB1: comp1517 | IC1: comp1719 | ID1: comp1921 | IE1: comp2123 | IF1: comp2325
A2: Albania | B2: ALB | C2: 2025 | D2: Eastern Europe & Central Asia | E2: Western Balkans & Turkiye | F2: 64.229358 | G2: 64 | H2: Substantial (61-80) | I2: Sufficient (61-100) | J2: Sufficient (61-100) | K2: 4th Quintile | L2: 68.555556 | M2: 69 | N2: Adequate (61-100) | O2: 63.916667 | P2: 64 | Q2: Adequate (61-100) | R2: 77.833333 | S2: 78 | T2: Adequate (61-100) | U2: 0 | V2: 0 | W2: Weak (0-40) | X2: 16.611111 | Y2: 17 | Z2: Few or no opportunities (0-40) | AA2: PW | AB2: PW | AC2: PW | AD2: PW | AE2: PW | AF2: PW | AG2: PW | AH2: PW | AI2: 1 | AJ2: 1 | AK2: 1 | AL2: 1 | AM2: 1 | AN2: 1 | AO2: 1 | AP2: 1 | AQ2: 94.5 | AR2: 95 | AS2: Extensive (81-100) | AT2: 61.703704 | AU2: 62 | AV2: Substantial (61-80) | AW2: 94.5 | AX2: 95 | AY2: Extensive (81-100) | AZ2: 33.25 | BA2: 33 | BB2: Minimal (21-40) | BC2: 81.555556 | BD2: 82 | BE2: Extensive (81-100) | BF2: 51.888889 | BG2: 52 | BH2: Limited (41-60) | BI2: 54.785714 | BJ2: 55 | BK2: Limited (41-60) | BL2: 62 | BM2: 62 | BN2: Substantial (61-80) | BO2: a | BP2: b | BQ2: b | BR2: b | BS2: a | BT2: a | BU2: b | BV2: e | BW2: e | BX2: e | BY2: e | BZ2: e | CA2: e | CB2: e | CC2: e | CD2: 100 | CE2: 100 | CF2: 100 | CG2: 100 | CH2: 100 | CI2: 100 | CJ2: 67 | CK2: 100 | CL2: 100 | CM2: 67 | CN2: 100 | CO2: 67 | CP2: 100 | CQ2: 33 | CR2: 67 | CS2: 0 | CT2: 0 | CU2: 100 | CV2: 33 | CW2: 0 | CX2: 100 | CY2: 33 | CZ2: 0 | DA2: 100 | DB2: 100 | DC2: 100 | DD2: 100 | DE2: 100 | DF2: 100 | DG2: 100 | DH2: 33 | DI2: 100 | DJ2: 33 | DK2: 100 | DL2: 100 | DM2: 33 | DN2: 33 | DO2: 0 | DP2: 0 | DQ2: 0 | DR2: 0 | DS2: 33 | DT2: 0 | DU2: 67 | DV2: 33 | DW2: 33 | DX2: 67 | DY2: 67 | DZ2: 33 | EA2: 33 | EB2: 67 | EC2: 33 | ED2: 100 | EE2: 100 | EF2: 67 | EG2: 100 | EH2: 100 | EI2: 100 | EJ2: 100 | EK2: 100 | EL2: 100 | EM2: 100 | EN2: 100 | EO2: 67 | EP2: 33 | EQ2: 0 | ER2: 33 | ES2: 100 | ET2: 0 | EU2: 100 | EV2: 100 | EW2: 100 | EX2: 100 | EY2: 100 | EZ2: 67 | FA2: 0 | FB2: 33 | FC2: 33 | FD2: 67 | FE2: 67 | FF2: 100 | FG2: 67 | FH2: 0 | FI2: 100 | FJ2: 100 | FK2: 100 | FL2: 100 | FM2: 100 | FN2: 100 | FO2: 0 | FP2: 0 | FQ2: 0 | FR2: 0 | FS2: 0 | FT2: 67 | FU2: 0 | FV2: 67 | FW2: 33 | FX2: 100 | FY2: 100 | FZ2: 0 | GA2: 67 | GB2: 0 | GC2: 0 | GD2: 0 | GE2: 0 | GF2: 33 | GG2: 67 | GH2: 100 | GI2: 100 | GJ2: 100 | GK2: 67 | GL2: 67 | GM2: 0 | GN2: 0 | GO2: 100 | GP2: 100 | GQ2: 33 | GR2: 100 | GS2: 100 | GT2: 100 | GU2: 100 | GV2: 0 | GW2: 67 | GX2: 33 | GY2: 0 | GZ2: 33 | HA2: 0 | HB2: 0 | HC2: 0 | HD2: 0 | HE2: 0 | HF2: 0 | HG2: 100 | HH2: 33 | HI2: 67 | HJ2: 33 | HK2: 0 | HL2: 0 | HM2: 0 | HN2: 0 | HO2: 0 | HP2: 100 | HQ2: 67 | HR2: 67 | HS2: 67 | HT2: 100 | HU2: 100 | HV2: 67 | HW2: 0 | HX2: 1 | HY2: 1 | HZ2: 1 | IA2: 1 | IB2: 1 | IC2: 1 | ID2: 1 | IE2: 1 | IF2: 1
A3: Albania | B3: ALB | C3: 2023 | D3: Eastern Europe & Central Asia | E3: Western Balkans & Turkiye | F3: 57.477064 | G3: 57 | H3: Limited (41-60) | I3: Limited (41-60) | J3: Insufficient (0-60) | K3: Middle Quintile | L3: 66.666667 | M3: 67 | N3: Adequate (61-100) | O3: 63.916667 | P3: 64 | Q3: Adequate (61-100) | R3: 72.166667 | S3: 72 | T3: Adequate (61-100) | U3: 0 | V3: 0 | W3: Weak (0-40) | X3: 9.1666667 | Y3: 9 | Z3: Few or no opportunities (0-40) | AA3: PW | AB3: PW | AC3: PW | AD3: PW | AE3: PW | AF3: PW | AG3: PW | AH3: IU | AI3: 1 | AJ3: 1 | AK3: 1 | AL3: 0 | AM3: 1 | AN3: 1 | AO3: 1 | AP3: 1 | AQ3: 94.5 | AR3: 95 | AS3: Extensive (81-100) | AT3: 58.592593 | AU3: 59 | AV3: Limited (41-60) | AW3: 94.5 | AX3: 95 | AY3: Extensive (81-100) | AZ3: 0 | BA3: 0 | BB3: Scant or None (0-20) | BC3: 74 | BD3: 74 | BE3: Substantial (61-80 | BF3: 18.555556 | BG3: 19 | BH3: Scant or None (0-20) | BI3: 50 | BJ3: 50 | BK3: Limited (41-60) | BL3: 62 | BM3: 62 | BN3: Substantial (61-80 | BO3: a | BP3: b | BQ3: b | BR3: c | BS3: a | BT3: c | BU3: b | BV3: e | BW3: e | BX3: e | BY3: e | BZ3: e | CA3: e | CB3: e | CD3: 100 | CE3: 100 | CF3: 100 | CG3: 100 | CH3: 100 | CI3: 100 | CJ3: 67 | CK3: 100 | CL3: 100 | CM3: 67 | CN3: 100 | CO3: 67 | CP3: 100 | CQ3: 33 | CR3: 33 | CS3: 0 | CT3: 0 | CU3: 100 | CV3: 33 | CW3: 0 | CX3: 100 | CY3: 33 | CZ3: 0 | DA3: 100 | DB3: 100 | DC3: 100 | DD3: 100 | DE3: 100 | DF3: 100 | DG3: 100 | DH3: 33 | DI3: 100 | DJ3: 33 | DK3: 100 | DL3: 100 | DM3: 33 | DN3: 33 | DO3: 0 | DP3: 0 | DQ3: 0 | DR3: 0 | DS3: 33 | DT3: 0 | DU3: 67 | DV3: 33 | DW3: 0 | DX3: 33 | DY3: 33 | DZ3: 0 | EA3: 33 | EB3: 67 | EC3: 33 | ED3: 100 | EE3: 100 | EF3: 67 | EG3: 100 | EH3: 100 | EI3: 100 | EJ3: 100 | EK3: 100 | EL3: 100 | EM3: 100 | EN3: 100 | EO3: 0 | EP3: 0 | EQ3: 0 | ER3: 0 | ES3: 100 | ET3: 0 | EU3: 100 | EV3: 100 | EW3: 100 | EX3: 100 | EY3: 100 | EZ3: 33 | FA3: 0 | FB3: 0 | FC3: 0 | FD3: 0 | FE3: 67 | FF3: 0 | FG3: 0 | FH3: 0 | FI3: 100 | FJ3: 100 | FK3: 100 | FL3: 100 | FM3: 100 | FN3: 100 | FO3: 0 | FP3: 0 | FQ3: 0 | FR3: 0 | FS3: 0 | FT3: 67 | FU3: 0 | FV3: 67 | FW3: 33 | FX3: 100 | FY3: 100 | FZ3: 0 | GA3: 67 | GB3: 0 | GC3: 0 | GD3: 0 | GE3: 0 | GF3: 33 | GG3: 67 | GH3: 100 | GI3: 100 | GJ3: 100 | GK3: 67 | GL3: 67 | GM3: 0 | GN3: 0 | GO3: 100 | GP3: 100 | GQ3: 33 | GR3: 100 | GS3: 100 | GT3: 100 | GU3: 100 | GV3: 0 | GW3: 33 | GX3: 33 | GY3: 0 | GZ3: 33 | HA3: 0 | HB3: 0 | HC3: 0 | HD3: 0 | HE3: 0 | HF3: 0 | HG3: 0 | HH3: 33 | HI3: 33 | HJ3: 33 | HK3: 0 | HL3: 0 | HM3: 0 | HN3: 0 | HO3: 0 | HP3: 100 | HQ3: 67 | HR3: 67 | HS3: 33 | HT3: 100 | HU3: 33 | HV3: 67 | HW3: 0 | HX3: 1 | HY3: 1 | HZ3: 1 | IA3: 1 | IB3: 1 | IC3: 1 | ID3: 1 | IE3: 1 | IF3: 1
A4: Albania | B4: ALB | C4: 2021 | D4: Eastern Europe & Central Asia | E4: Western Balkans & Turkiye | F4: 51.651376 | G4: 52 | H4: Limited (41-60) | I4: Limited (41-60) | J4: Insufficient (0-60) | K4: Middle Quintile | L4: 66.666667 | M4: 67 | N4: Adequate (61-100) | O4: 63.916667 | P4: 64 | Q4: Adequate (61-100) | R4: 72.166667 | S4: 72 | T4: Adequate (61-100) | U4: 0 | V4: 0 | W4: Weak (0-40) | X4: 5.5 | Y4: 6 | Z4: Few or no opportunities (0-40) | AA4: PW | AB4: PW | AC4: PW | AD4: PW | AE4: PW | AF4: PW | AG4: PL | AH4: PW | AI4: 1 | AJ4: 1 | AK4: 1 | AL4: 1 | AM4: 1 | AN4: 1 | AO4: 1 | AP4: 0 | AQ4: 94.5 | AR4: 95 | AS4: Extensive (81-100) | AT4: 53.037037 | AU4: 53 | AV4: Limited (41-60) | AW4: 94.5 | AX4: 95 | AY4: Extensive (81-100) | AZ4: 33.25 | BA4: 33 | BB4: Minimal (21-40) | BC4: 74 | BD4: 74 | BE4: Substantial (61-80 | BF4: 18.555556 | BG4: 19 | BH4: Scant or None (0-20) | BI4: 42.785714 | BJ4: 43 | BK4: Limited (41-60) | BL4: 9.5714286 | BM4: 10 | BN4: Scant or None (0-20) | BO4: a | BP4: b | BQ4: b | BR4: c | BS4: a | BT4: c | BU4: d | BV4: e | BW4: e | BX4: e | BY4: e | BZ4: e | CA4: e | CB4: a | CD4: 100 | CE4: 100 | CF4: 100 | CG4: 100 | CH4: 100 | CI4: 100 | CJ4: 67 | CK4: 33 | CL4: 100 | CM4: 67 | CN4: 100 | CO4: 67 | CP4: 100 | CQ4: 33 | CR4: 33 | CS4: 0 | CT4: 0 | CU4: 0 | CV4: 33 | CW4: 0 | CX4: 100 | CY4: 33 | CZ4: 0 | DA4: 100 | DB4: 100 | DC4: 100 | DD4: 100 | DE4: 100 | DF4: 100 | DG4: 100 | DH4: 33 | DI4: 0 | DJ4: 33 | DK4: 100 | DL4: 100 | DM4: 0 | DN4: 33 | DO4: 0 | DP4: 0 | DQ4: 0 | DR4: 0 | DS4: 33 | DT4: 0 | DU4: 67 | DV4: 33 | DW4: 0 | DX4: 33 | DY4: 33 | DZ4: 0 | EA4: 33 | EB4: 67 | EC4: 33 | ED4: 100 | EE4: 100 | EF4: 67 | EG4: 100 | EH4: 100 | EI4: 100 | EJ4: 100 | EK4: 100 | EL4: 100 | EM4: 100 | EN4: 100 | EO4: 67 | EP4: 33 | EQ4: 0 | ER4: 33 | ES4: 100 | ET4: 0 | EU4: 100 | EV4: 100 | EW4: 100 | EX4: 100 | EY4: 100 | EZ4: 33 | FA4: 0 | FB4: 0 | FC4: 0 | FD4: 0 | FE4: 67 | FF4: 0 | FG4: 0 | FH4: 0 | FI4: 100 | FJ4: 100 | FK4: 33 | FL4: 100 | FM4: 100 | FN4: 100 | FO4: 0 | FP4: 0 | FQ4: 0 | FR4: 0 | FS4: 0 | FT4: 33 | FU4: 0 | FV4: 0 | FW4: 0 | FX4: 0 | FY4: 0 | FZ4: 0 | GA4: 67 | GB4: 0 | GC4: 0 | GD4: 0 | GE4: 0 | GF4: 33 | GG4: 67 | GH4: 100 | GI4: 100 | GJ4: 100 | GK4: 67 | GL4: 67 | GM4: 0 | GN4: 0 | GO4: 100 | GP4: 100 | GQ4: 33 | GR4: 100 | GS4: 100 | GT4: 100 | GU4: 100 | GV4: 0 | GW4: 33 | GX4: 0 | GY4: 0 | GZ4: 0 | HA4: 0 | HB4: 0 | HC4: 0 | HD4: 0 | HE4: 0 | HF4: 0 | HG4: 0 | HH4: 33 | HI4: 33 | HJ4: 33 | HK4: 0 | HL4: 0 | HM4: 0 | HN4: 0 | HO4: 0 | HP4: 100 | HQ4: 67 | HR4: 67 | HS4: 33 | HT4: 100 | HU4: 33 | HV4: 0 | HW4: 0 | HX4: 1 | HY4: 1 | HZ4: 1 | IA4: 1 | IB4: 1 | IC4: 1 | ID4: 1 | IE4: 1 | IF4: 1
A5: Albania | B5: ALB | C5: 2019 | D5: Eastern Europe & Central Asia | E5: Western Balkans & Turkiye | F5: 54.715596 | G5: 55 | H5: Limited (41-60) | I5: Limited (41-60) | J5: Insufficient (0-60) | K5: Middle Quintile | L5: 64.777778 | M5: 65 | N5: Adequate (61-100) | O5: 61.083333 | P5: 61 | Q5: Adequate (61-100) | R5: 72.166667 | S5: 72 | T5: Adequate (61-100) | U5: 0 | V5: 0 | W5: Weak (0-40) | X5: 7.3333333 | Y5: 7 | Z5: Few or no opportunities (0-40) | AA5: PW | AB5: PW | AC5: PW | AD5: PW | AE5: PW | AF5: PW | AG5: PW | AH5: PW | AI5: 1 | AJ5: 1 | AK5: 1 | AL5: 1 | AM5: 1 | AN5: 1 | AO5: 1 | AP5: 1 | AQ5: 94.5 | AR5: 95 | AS5: Extensive (81-100) | AT5: 49.351852 | AU5: 49 | AV5: Limited (41-60) | AW5: 100 | AX5: 100 | AY5: Extensive (81-100) | AZ5: 33.25 | BA5: 33 | BB5: Minimal (21-40) | BC5: 81.444444 | BD5: 81 | BE5: Extensive (81-100) | BF5: 18.444444 | BG5: 18 | BH5: Scant or None (0-20) | BI5: 42.857143 | BJ5: 43 | BK5: Limited (41-60) | BL5: 71.428571 | BM5: 71 | BN5: Substantial (61-80 | BO5: a | BP5: b | BQ5: a | BR5: a | BS5: a | BT5: b | BU5: b | BV5: e | BW5: e | BX5: e | BY5: e | BZ5: e | CA5: e | CB5: e | CD5: 100 | CE5: 100 | CF5: 100 | CG5: 100 | CH5: 0 | CI5: 100 | CJ5: 67 | CK5: 67 | CL5: 100 | CM5: 67 | CN5: 100 | CO5: 67 | CP5: 100 | CQ5: 33 | CR5: 33 | CS5: 0 | CT5: 67 | CU5: 0 | CV5: 33 | CW5: 0 | CX5: 100 | CY5: 33 | CZ5: 0 | DA5: 100 | DB5: 100 | DC5: 100 | DD5: 100 | DE5: 100 | DF5: 100 | DG5: 100 | DH5: 33 | DI5: 0 | DJ5: 33 | DK5: 100 | DL5: 100 | DM5: 0 | DN5: 33 | DO5: 0 | DP5: 0 | DQ5: 0 | DR5: 0 | DS5: 33 | DT5: 0 | DU5: 0 | DV5: 33 | DW5: 0 | DX5: 33 | DY5: 33 | DZ5: 0 | EA5: 0 | EB5: 0 | EC5: 0 | ED5: 100 | EE5: 100 | EF5: 67 | EG5: 100 | EH5: 100 | EI5: 100 | EJ5: 100 | EK5: 100 | EL5: 100 | EM5: 100 | EN5: 100 | EO5: 67 | EP5: 33 | EQ5: 0 | ER5: 33 | ES5: 100 | ET5: 0 | EU5: 100 | EV5: 100 | EW5: 100 | EX5: 100 | EY5: 100 | EZ5: 33 | FA5: 33 | FB5: 0 | FC5: 0 | FD5: 0 | FE5: 33 | FF5: 0 | FG5: 0 | FH5: 0 | FI5: 100 | FJ5: 67 | FK5: 33 | FL5: 100 | FM5: 100 | FN5: 100 | FO5: 0 | FP5: 0 | FQ5: 0 | FR5: 0 | FS5: 0 | FT5: 33 | FU5: 0 | FV5: 100 | FW5: 100 | FX5: 100 | FY5: 100 | FZ5: 0 | GA5: 33 | GB5: 0 | GC5: 0 | GD5: 0 | GE5: 0 | GF5: 33 | GG5: 33 | GH5: 67 | GI5: 100 | GJ5: 100 | GK5: 67 | GL5: 33 | GM5: 0 | GN5: 0 | GO5: 100 | GP5: 100 | GQ5: 100 | GR5: 100 | GS5: 100 | GT5: 100 | GU5: 100 | GV5: 0 | GW5: 33 | GX5: 0 | GY5: 0 | GZ5: 0 | HA5: 0 | HB5: 0 | HC5: 0 | HD5: 0 | HE5: 0 | HF5: 0 | HG5: 0 | HH5: 33 | HI5: 33 | HJ5: 33 | HK5: 33 | HL5: 0 | HM5: 0 | HN5: 0 | HO5: 0 | HP5: 100 | HQ5: 67 | HR5: 100 | HS5: 100 | HT5: 100 | HU5: 67 | HV5: 67 | HW5: 0 | HX5: 1 | HY5: 1 | HZ5: 1 | IA5: 1 | IB5: 1 | IC5: 1 | ID5: 1 | IE5: 1 | IF5: 1
A6: Albania | B6: ALB | C6: 2017 | D6: Eastern Europe & Central Asia | E6: Western Balkans & Turkiye | F6: 49.657407 | G6: 50 | H6: Limited (41-60) | I6: Limited (41-60) | J6: Insufficient (0-60) | K6: Middle Quintile | L6: 68.5 | M6: 69 | N6: Adequate (61-100) | O6: 66.666667 | P6: 67 | Q6: Adequate (61-100) | R6: 72.166667 | S6: 72 | T6: Adequate (61-100) | U6: 0 | V6: 0 | W6: Weak (0-40) | X6: 1.8333333 | Y6: 2 | Z6: Few or No (0-40) | AA6: PW | AB6: PW | AC6: PW | AD6: PW | AE6: NP | AF6: PW | AG6: PW | AH6: PW | AI6: 1 | AJ6: 1 | AK6: 1 | AL6: 1 | AM6: 1 | AN6: 0 | AO6: 1 | AP6: 1 | AQ6: 94.5 | AR6: 95 | AS6: Extensive (81-100) | AT6: 49 | AU6: 49 | AV6: Limited (41-60) | AW6: 89 | AX6: 89 | AY6: Extensive (81-100) | AZ6: 33.25 | BA6: 33 | BB6: Minimal (21-40) | BC6: 74 | BD6: 74 | BE6: Substantial (61-80 | BF6: 0 | BG6: 0 | BH6: Scant or None (0-20) | BI6: 26.142857 | BJ6: 26 | BK6: Minimal (21-40) | BL6: 71.428571 | BM6: 71 | BN6: Substantial (61-80 | BO6: a | BP6: c | BQ6: b | BR6: c | BS6: d | BT6: c | BU6: b | CD6: 100 | CE6: 100 | CF6: 100 | CG6: 100 | CH6: 0 | CI6: 100 | CJ6: 33 | CK6: 0 | CL6: 100 | CM6: 67 | CN6: 100 | CO6: 67 | CP6: 100 | CQ6: 33 | CR6: 33 | CS6: 0 | CT6: 0 | CU6: 0 | CV6: 33 | CW6: 0 | CX6: 100 | CY6: 33 | CZ6: 0 | DA6: 100 | DB6: 100 | DC6: 100 | DD6: 100 | DE6: 100 | DF6: 100 | DG6: 100 | DH6: 33 | DI6: 100 | DJ6: 33 | DK6: 100 | DL6: 100 | DM6: 0 | DN6: 33 | DO6: 67 | DP6: 0 | DQ6: 0 | DS6: 33 | DT6: 0 | DU6: 0 | DV6: 33 | DW6: 0 | DX6: 33 | DY6: 0 | DZ6: 0 | EA6: 0 | EB6: 0 | EC6: 0 | ED6: 100 | EE6: 100 | EF6: 67 | EG6: 100 | EH6: 100 | EI6: 100 | EJ6: 100 | EK6: 100 | EL6: 100 | EM6: 100 | EN6: 67 | EO6: 67 | EP6: 33 | EQ6: 0 | ER6: 33 | ES6: 100 | ET6: 0 | EU6: 100 | EV6: 100 | EW6: 100 | EX6: 100 | EY6: 100 | EZ6: 33 | FA6: 0 | FB6: 0 | FC6: 0 | FD6: 0 | FE6: 0 | FF6: 0 | FG6: 0 | FH6: 0 | FI6: 33 | FJ6: 0 | FK6: 0 | FL6: 100 | FM6: 100 | FN6: 100 | FO6: 0 | FP6: 0 | FQ6: 0 | FR6: 0 | FS6: 0 | FT6: 0 | FU6: 0 | FV6: 100 | FW6: 100 | FX6: 100 | FY6: 100 | FZ6: 0 | GA6: 33 | GB6: 0 | GC6: 0 | GD6: 0 | GE6: 0 | GF6: 33 | GG6: 67 | GH6: 67 | GI6: 100 | GJ6: 100 | GK6: 67 | GL6: 33 | GM6: 33 | GN6: 0 | GO6: 100 | GP6: 100 | GQ6: 100 | GR6: 100 | GS6: 100 | GT6: 100 | GU6: 100 | GV6: 0 | GW6: 33 | GX6: 0 | GY6: 0 | GZ6: 0 | HA6: 0 | HB6: 0 | HC6: 0 | HD6: 0 | HE6: 0 | HF6: 0 | HG6: 0 | HH6: 0 | HI6: 33 | HJ6: 0 | HK6: 0 | HL6: 0 | HM6: 0 | HN6: 0 | HO6: 0 | HP6: 100 | HQ6: 33 | HR6: 67 | HS6: 33 | HT6: 0 | HU6: 33 | HV6: 67 | HW6: 0 | HX6: 1 | HY6: 1 | HZ6: 1 | IA6: 1 | IB6: 1 | IC6: 1 | ID6: 1 | IE6: 1 | IF6: 1
A7: Albania | B7: ALB | C7: 2015 | D7: Eastern Europe & Central Asia | E7: Western Balkans & Turkiye | F7: 38.2202 | G7: 38 | H7: Minimal (21-40) | I7: Low (0-40) | J7: Insufficient (0-60) | K7: 2nd Quintile | O7: 48.545502 | P7: 49 | Q7: Moderate | R7: 91.75 | S7: 92 | T7: Strong | X7: 14.5625 | Y7: 15 | Z7: Minimal | AA7: PW | AB7: PW | AC7: PW | AD7: PW | AE7: NP | AF7: IU | AG7: PW | AH7: NP | AI7: 1 | AJ7: 1 | AK7: 1 | AL7: 0 | AM7: 1 | AN7: 0 | AO7: 0 | AP7: 1 | AQ7: 72.166702 | AR7: 72 | AS7: Substantial (61-80 | AT7: 40.092602 | AU7: 40 | AV7: Minimal (21-40) | AW7: 94.5 | AX7: 95 | AY7: Extensive (81-100) | AZ7: 0 | BA7: 0 | BB7: Scant or None (0-20) | BC7: 77.777802 | BD7: 78 | BE7: Substantial (61-80 | BF7: 0 | BG7: 0 | BH7: Scant or None (0-20) | BI7: 0 | BJ7: 0 | BK7: Scant or None (0-20) | BL7: 43 | BM7: 43 | BN7: Limited (41-60) | CD7: 100 | CE7: 100 | CF7: 100 | CG7: 100 | CH7: 0 | CI7: 100 | CJ7: 0 | CK7: 0 | CL7: 100 | CM7: 100 | CN7: 0 | CO7: 0 | CP7: 100 | CQ7: 100 | CR7: 33 | CS7: 0 | CT7: 0 | CU7: 0 | CV7: 0 | CW7: 0 | CX7: 100 | CY7: 0 | CZ7: 0 | DA7: 100 | DB7: 100 | DC7: 67 | DD7: 100 | DE7: 0 | DF7: 0 | DG7: 0 | DH7: 100 | DI7: 100 | DJ7: 33 | DK7: 100 | DL7: 100 | DM7: 0 | DN7: 33 | DO7: 0 | DP7: 0 | DQ7: 0 | DR7: 100 | DS7: 33 | DT7: 0 | DU7: 0 | DV7: 33 | DW7: 0 | DX7: 0 | DY7: 0 | DZ7: 0 | EA7: 0 | EB7: 0 | EC7: 0 | ED7: 100 | EE7: 67 | EF7: 33 | EG7: 33 | EH7: 100 | EI7: 100 | EJ7: 100 | EK7: 100 | EL7: 100 | EM7: 100 | EN7: 67 | EO7: 0 | EP7: 0 | EQ7: 0 | ER7: 0 | ES7: 100 | ET7: 0 | EU7: 100 | EV7: 100 | EW7: 100 | EX7: 100 | EY7: 67 | EZ7: 33 | FA7: 0 | FB7: 0 | FC7: 0 | FD7: 0 | FE7: 0 | FF7: 0 | FG7: 0 | FH7: 0 | FI7: 0 | FJ7: 0 | FK7: 0 | FL7: 0 | FM7: 0 | FN7: 0 | FO7: 0 | FP7: 0 | FQ7: 0 | FR7: 0 | FS7: 0 | FT7: 0 | FU7: 0 | FV7: 67 | FW7: 67 | FX7: 100 | FY7: 0 | FZ7: 0 | GA7: 0 | GB7: 0 | GC7: 67 | GD7: 67 | GE7: 33 | GF7: 67 | GG7: 100 | GH7: 0 | GI7: 0 | GJ7: 100 | GK7: 100 | GL7: 0 | GM7: 100 | GN7: 100 | GO7: 67 | GP7: 100 | GQ7: 100 | GR7: 0 | GS7: 0 | GT7: 0 | GU7: 0 | GV7: 0 | GW7: 0 | GX7: 0 | GY7: 33 | GZ7: 67 | HA7: 33 | HB7: 0 | HC7: 0 | HD7: 0 | HE7: 0 | HF7: 0 | HP7: 100 | HQ7: 33 | HR7: 100 | HS7: 100 | HT7: 0 | HU7: 0 | HV7: 67 | HW7: 0 | HX7: 1 | HY7: 1 | HZ7: 1 | IA7: 1 | IB7: 1 | IC7: 1 | ID7: 1 | IE7: 1 | IF7: 1
A8: Albania | B8: ALB | C8: 2012 | D8: Eastern Europe & Central Asia | E8: Western Balkans & Turkiye | F8: 46.694698 | G8: 47 | H8: Limited (41-60) | I8: Limited (41-60) | J8: Insufficient (0-60) | K8: Middle Quintile | O8: 51.545502 | P8: 52 | Q8: Moderate | R8: 100 | S8: 100 | T8: Strong | X8: 11.0833 | Y8: 11 | Z8: Weak | AA8: PW | AB8: PW | AC8: PW | AD8: PW | AE8: NP | AF8: IU | AG8: PW | AH8: NP | AI8: 1 | AJ8: 1 | AK8: 1 | AL8: 0 | AM8: 1 | AN8: 0 | AO8: 0 | AP8: 1 | AQ8: 100 | AR8: 100 | AS8: Extensive (81-100) | AT8: 50.0172 | AU8: 50 | AV8: Limited (41-60) | AW8: 100 | AX8: 100 | AY8: Extensive (81-100) | AZ8: 0 | BA8: 0 | BB8: Scant or None (0-20) | BC8: 95.875 | BD8: 96 | BE8: Extensive (81-100) | BF8: 0 | BG8: 0 | BH8: Scant or None (0-20) | BI8: 0 | BJ8: 0 | BK8: Scant or None (0-20) | BL8: 52.5714 | BM8: 53 | BN8: Limited (41-60) | CD8: 100 | CI8: 100 | CL8: 100 | CM8: 67 | CQ8: 100 | CR8: 100 | CS8: 0 | CT8: 0 | CU8: 0 | CW8: 0 | CX8: 100 | DA8: 100 | DD8: 100 | DG8: 100 | DH8: 33 | DI8: 100 | DJ8: 67 | DL8: 100 | DN8: 67 | DO8: 0 | DP8: 0 | DQ8: 0 | DR8: 0 | DS8: 33 | DT8: 0 | DU8: 0 | DV8: 0 | DW8: 0 | DX8: 0 | DY8: 0 | EA8: 0 | EB8: 0 | EC8: 0 | ED8: 100 | EE8: 100 | EO8: 0 | EP8: 0 | EQ8: 0 | ER8: 0 | EU8: 100 | EW8: 100 | EX8: 100 | EZ8: 67 | FA8: 0 | FB8: 0 | FE8: 0 | FI8: 0 | FL8: 0 | FP8: 0 | FQ8: 0 | FR8: 0 | FS8: 0 | FT8: 0 | FW8: 67 | FX8: 67 | FY8: 0 | FZ8: 0 | GA8: 67 | GB8: 0 | GC8: 67 | GD8: 67 | GE8: 67 | GG8: 100 | GH8: 33 | GI8: 33 | GJ8: 100 | GK8: 0 | GL8: 0 | GM8: 100 | GN8: 100 | GP8: 100 | GQ8: 100 | GR8: 0 | GS8: 0 | GT8: 0 | GV8: 0 | GW8: 0 | GX8: 0 | GY8: 33 | GZ8: 67 | HA8: 33 | HB8: 0 | HE8: 0 | HF8: 0 | HP8: 100 | HQ8: 67 | HS8: 100 | HU8: 0 | HV8: 67 | HW8: 0 | HX8: 1 | HY8: 1 | HZ8: 1 | IA8: 1 | IB8: 1 | IC8: 1 | ID8: 1 | IE8: 1 | IF8: 1
A9: Albania | B9: ALB | C9: 2010 | D9: Eastern Europe & Central Asia | E9: Western Balkans & Turkiye | F9: 32.9674 | G9: 33 | H9: Minimal (21-40) | I9: Low (0-40) | J9: Insufficient (0-60) | K9: 2nd Quintile | O9: 44.5 | P9: 45 | Q9: Moderate | R9: 50 | S9: 50 | T9: Moderate | AA9: IU | AB9: PW | AC9: PW | AD9: PW | AE9: IU | AF9: PW | AG9: HC | AH9: NP | AI9: 0 | AJ9: 1 | AK9: 1 | AL9: 0 | AM9: 1 | AN9: 0 | AO9: 1 | AP9: 1 | AQ9: 0 | AR9: 0 | AS9: Scant or None (0-20) | AT9: 30.8909 | AU9: 31 | AV9: Minimal (21-40) | AW9: 67 | AX9: 67 | AY9: Substantial (61-80 | AZ9: 0 | BA9: 0 | BB9: Scant or None (0-20) | BC9: 79.25 | BD9: 79 | BE9: Substantial (61-80 | BF9: 0 | BG9: 0 | BH9: Scant or None (0-20) | BI9: 16.6 | BJ9: 17 | BK9: Scant or None (0-20) | BL9: 23.8571 | BM9: 24 | BN9: Minimal (21-40) | CD9: 67 | CI9: 67 | CL9: 67 | CM9: 33 | CQ9: 33 | CR9: 33 | CS9: 0 | CT9: 33 | CU9: 33 | CW9: 0 | CX9: 0 | DA9: 0 | DD9: 0 | DG9: 0 | DH9: 33 | DI9: 0 | DJ9: 100 | DL9: 67 | DN9: 0 | DO9: 0 | DP9: 0 | DQ9: 0 | DR9: 0 | DS9: 0 | DT9: 0 | DU9: 0 | DV9: 0 | DW9: 0 | DX9: 33 | DY9: 67 | EA9: 67 | EB9: 0 | EC9: 0 | ED9: 100 | EE9: 0 | EO9: 0 | EU9: 100 | EW9: 100 | EX9: 100 | EZ9: 33 | FA9: 0 | FB9: 0 | FE9: 0 | FI9: 33 | FL9: 0 | FP9: 0 | FQ9: 33 | FR9: 0 | FS9: 0 | FT9: 0 | FW9: 67 | FX9: 0 | FY9: 0 | FZ9: 0 | GA9: 0 | GD9: 67 | GE9: 67 | GG9: 67 | GH9: 33 | GK9: 100 | GL9: 0 | GM9: 67 | GN9: 100 | GP9: 100 | GQ9: 100 | GR9: 100 | GY9: 33 | GZ9: 67 | HA9: 33 | HB9: 0 | HP9: 0 | HQ9: 67 | HS9: 67 | HU9: 67 | HV9: 67 | HW9: 0 | HX9: 1 | HY9: 1 | HZ9: 1 | IA9: 1 | IB9: 1 | IC9: 1 | ID9: 1 | IE9: 1 | IF9: 1
A10: Albania | B10: ALB | C10: 2008 | D10: Eastern Europe & Central Asia | E10: Western Balkans & Turkiye | F10: 37.3297 | G10: 37 | H10: Minimal (21-40) | I10: Low (0-40) | J10: Insufficient (0-60) | K10: 2nd Quintile | O10: 41.583302 | P10: 42 | Q10: Moderate | R10: 66.800003 | S10: 67 | T10: Strong | AA10: IU | AB10: PW | AC10: PW | AD10: PW | AE10: IU | AF10: IU | AG10: PW | AH10: NP | AI10: 0 | AJ10: 1 | AK10: 1 | AL10: 0 | AM10: 1 | AN10: 0 | AO10: 0 | AP10: 1 | AQ10: 0 | AR10: 0 | AS10: Scant or None (0-20) | AT10: 40.055599 | AU10: 40 | AV10: Minimal (21-40) | AW10: 33 | AX10: 33 | AY10: Minimal (21-40) | AZ10: 0 | BA10: 0 | BB10: Scant or None (0-20) | BC10: 91.625 | BD10: 92 | BE10: Extensive (81-100) | BF10: 0 | BG10: 0 | BH10: Scant or None (0-20) | BI10: 0 | BJ10: 0 | BK10: Scant or None (0-20) | BL10: 28.7143 | BM10: 29 | BN10: Minimal (21-40) | CD10: 33 | CI10: 0 | CL10: 67 | CM10: 33 | CQ10: 33 | CR10: 33 | CS10: 0 | CT10: 0 | CU10: 33 | CW10: 0 | CX10: 33 | DA10: 100 | DD10: 67 | DG10: 0 | DH10: 33 | DI10: 100 | DJ10: 100 | DL10: 67 | DN10: 33 | DO10: 0 | DP10: 0 | DQ10: 0 | DR10: 33 | DS10: 33 | DT10: 33 | DU10: 0 | DV10: 0 | DX10: 33 | DY10: 33 | EA10: 33 | EB10: 0 | EC10: 0 | ED10: 100 | EE10: 0 | EO10: 0 | EU10: 100 | EW10: 100 | EX10: 100 | EZ10: 33 | FA10: 0 | FB10: 0 | FE10: 0 | FI10: 0 | FL10: 0 | FP10: 0 | FQ10: 0 | FR10: 0 | FS10: 0 | FT10: 0 | FW10: 67 | FX10: 0 | FY10: 0 | FZ10: 0 | GA10: 0 | GD10: 0 | GE10: 33 | GG10: 100 | GH10: 0 | GK10: 100 | GL10: 0 | GM10: 67 | GN10: 100 | GP10: 100 | GQ10: 100 | GR10: 0 | GY10: 33 | GZ10: 67 | HA10: 33 | HB10: 0 | HP10: 0 | HQ10: 33 | HS10: 100 | HU10: 0 | HV10: 67 | HW10: 0 | HX10: 1 | HY10: 1 | HZ10: 1 | IA10: 1 | IB10: 1 | IC10: 1 | ID10: 1 | IE10: 1 | IF10: 1
A11: Albania | B11: ALB | C11: 2006 | D11: Eastern Europe & Central Asia | E11: Western Balkans & Turkiye | F11: 24.8901 | G11: 25 | H11: Minimal (21-40) | I11: Low (0-40) | J11: Insufficient (0-60) | K11: 2nd Quintile | O11: 47.166698 | P11: 47 | Q11: Moderate | R11: 62.625 | S11: 63 | T11: Moderate | AA11: IU | AB11: PW | AC11: PW | AD11: PW | AE11: IU | AF11: PW | AG11: PW | AH11: NP | AI11: 0 | AJ11: 1 | AK11: 1 | AL11: 0 | AM11: 1 | AN11: 0 | AO11: 1 | AP11: 1 | AQ11: 0 | AR11: 0 | AS11: Scant or None (0-20) | AT11: 17.2407 | AU11: 17 | AV11: Scant or None (0-20) | AW11: 67 | AX11: 67 | AY11: Substantial (61-80 | AZ11: 0 | BA11: 0 | BB11: Scant or None (0-20) | BC11: 75 | BD11: 75 | BE11: Substantial (61-80 | BF11: 0 | BG11: 0 | BH11: Scant or None (0-20) | BI11: 19.9 | BJ11: 20 | BK11: Scant or None (0-20) | BL11: 33.5 | BM11: 34 | BN11: Minimal (21-40) | CD11: 33 | CI11: 33 | CL11: 67 | CM11: 33 | CQ11: 33 | CR11: 33 | CS11: 0 | CT11: 0 | CU11: 0 | CW11: 0 | CX11: 0 | DA11: 0 | DD11: 0 | DG11: 0 | DH11: 33 | DI11: 0 | DJ11: 100 | DL11: 67 | DN11: 33 | DO11: 0 | DP11: 0 | DQ11: 0 | DR11: 33 | DS11: 33 | DT11: 33 | DU11: 0 | DV11: 0 | DX11: 33 | DY11: 0 | EA11: 0 | EB11: 0 | EC11: 0 | ED11: 100 | EE11: 0 | EO11: 0 | EU11: 100 | EW11: 67 | EX11: 100 | EZ11: 33 | FA11: 0 | FB11: 0 | FE11: 0 | FI11: 33 | FL11: 33 | FP11: 0 | FQ11: 0 | FR11: 0 | FS11: 0 | FT11: 33 | FW11: 67 | FX11: 0 | FY11: 0 | FZ11: 0 | GA11: 0 | GD11: 33 | GE11: 33 | GG11: 100 | GH11: 33 | GK11: 100 | GL11: 0 | GM11: 67 | GN11: 100 | GP11: 100 | GQ11: 100 | GR11: 0 | GY11: 33 | GZ11: 67 | HA11: 33 | HB11: 0 | HP11: 0 | HQ11: 33 | HS11: 67 | HU11: 67 | HV11: 67 | HW11: 0 | HX11: 1 | HY11: 1 | HZ11: 1 | IA11: 1 | IB11: 1 | IC11: 1 | ID11: 1 | IE11: 1 | IF11: 1
A12: Algeria | B12: DZA | C12: 2025 | D12: Middle East & North Africa | E12: North Africa | F12: 22.321101 | G12: 22 | H12: Minimal (21-40) | I12: Low (0-40) | J12: Insufficient (0-60) | K12: 2nd Quintile | L12: 25.944444 | M12: 26 | N12: Weak (0-40) | O12: 30.583333 | P12: 31 | Q12: Weak (0-40) | R12: 16.666667 | S12: 17 | T12: Weak (0-40) | U12: 0 | V12: 0 | W12: Weak (0-40) | X12: 0 | Y12: 0 | Z12: Few or no opportunities (0-40) | AA12: IU | AB12: PW | AC12: PW | AD12: IU | AE12: NP | AF12: NP | AG12: NP | AH12: PL | AI12: 0 | AJ12: 1 | AK12: 1 | AL12: 0 | AM12: 0 | AN12: 0 | AO12: 0 | AP12: 0 | AQ12: 0 | AR12: 0 | AS12: Scant or None (0-20) | AT12: 37.648148 | AU12: 38 | AV12: Minimal (21-40) | AW12: 55.5 | AX12: 56 | AY12: Limited (41-60) | AZ12: 0 | BA12: 0 | BB12: Scant or None (0-20) | BC12: 0 | BD12: 0 | BE12: Scant or None (0-20) | BF12: 0 | BG12: 0 | BH12: Scant or None (0-20) | BI12: 0 | BJ12: 0 | BK12: Scant or None (0-20) | BL12: 9.5714286 | BM12: 10 | BN12: Scant or None (0-20) | BO12: d | BP12: b | BQ12: c | BR12: d | BS12: d | BT12: d | BU12: d | BV12: c | BW12: e | BX12: e | BY12: c | BZ12: d | CA12: d | CB12: d | CC12: a | CD12: 100 | CE12: 0 | CF12: 0 | CG12: 100 | CH12: 0 | CI12: 33 | CJ12: 33 | CK12: 0 | CL12: 100 | CM12: 67 | CN12: 100 | CO12: 67 | CP12: 67 | CQ12: 0 | CR12: 33 | CS12: 0 | CT12: 100 | CU12: 100 | CV12: 0 | CW12: 0 | CX12: 100 | CY12: 33 | CZ12: 0 | DA12: 100 | DB12: 100 | DC12: 67 | DD12: 100 | DE12: 100 | DF12: 67 | DG12: 100 | DH12: 33 | DI12: 0 | DJ12: 0 | DK12: 0 | DL12: 33 | DM12: 0 | DN12: 0 | DO12: 0 | DP12: 0 | DQ12: 0 | DR12: 0 | DS12: 0 | DT12: 0 | DU12: 0 | DV12: 33 | DW12: 67 | DX12: 100 | DY12: 33 | DZ12: 0 | EA12: 0 | EB12: 0 | EC12: 0 | ED12: 0 | EE12: 0 | EF12: 0 | EG12: 0 | EH12: 0 | EI12: 0 | EJ12: 33 | EK12: 100 | EL12: 100 | EM12: 67 | EN12: 0 | EO12: 0 | EP12: 0 | EQ12: 0 | ER12: 0 | ES12: 0 | ET12: 0 | EU12: 0 | EV12: 0 | EW12: 0 | EX12: 0 | EY12: 0 | EZ12: 0 | FA12: 0 | FB12: 0 | FC12: 0 | FD12: 0 | FE12: 0 | FF12: 0 | FG12: 0 | FH12: 0 | FI12: 0 | FJ12: 0 | FK12: 0 | FL12: 0 | FM12: 0 | FN12: 0 | FO12: 0 | FP12: 0 | FQ12: 0 | FR12: 0 | FS12: 0 | FT12: 0 | FU12: 0 | FV12: 0 | FW12: 0 | FX12: 0 | FY12: 0 | FZ12: 0 | GA12: 67 | GB12: 0 | GC12: 0 | GD12: 0 | GE12: 0 | GF12: 0 | GG12: 67 | GH12: 100 | GI12: 67 | GJ12: 100 | GK12: 33 | GL12: 0 | GM12: 0 | GN12: 0 | GO12: 0 | GP12: 0 | GQ12: 0 | GR12: 0 | GS12: 0 | GT12: 67 | GU12: 33 | GV12: 0 | GW12: 0 | GX12: 0 | GY12: 0 | GZ12: 0 | HA12: 0 | HB12: 0 | HC12: 0 | HD12: 0 | HE12: 0 | HF12: 0 | HG12: 0 | HH12: 0 | HI12: 0 | HJ12: 0 | HK12: 0 | HL12: 0 | HM12: 0 | HN12: 0 | HO12: 0 | HP12: 0 | HQ12: 67 | HR12: 33 | HS12: 0 | HT12: 0 | HU12: 0 | HV12: 0 | HW12: 0 | HX12: 0 | HY12: 1 | HZ12: 1 | IA12: 1 | IB12: 1 | IC12: 1 | ID12: 1 | IE12: 1 | IF12: 1
A13: Algeria | B13: DZA | C13: 2023 | D13: Middle East & North Africa | E13: North Africa | F13: 14.678899 | G13: 15 | H13: Scant or None (0-20) | I13: Low (0-40) | J13: Insufficient (0-60) | K13: Bottom Quintile | L13: 27.777778 | M13: 28 | N13: Weak (0-40) | O13: 27.75 | P13: 28 | Q13: Weak (0-40) | R13: 27.833333 | S13: 28 | T13: Weak (0-40) | U13: 0 | V13: 0 | W13: Weak (0-40) | X13: 0 | Y13: 0 | Z13: Few or no opportunities (0-40) | AA13: IU | AB13: PW | AC13: PW | AD13: IU | AE13: NP | AF13: IU | AG13: NP | AH13: PL | AI13: 0 | AJ13: 1 | AK13: 1 | AL13: 0 | AM13: 0 | AN13: 0 | AO13: 0 | AP13: 0 | AQ13: 0 | AR13: 0 | AS13: Scant or None (0-20) | AT13: 22.833333 | AU13: 23 | AV13: Minimal (21-40) | AW13: 61.166667 | AX13: 61 | AY13: Substantial (61-80 | AZ13: 0 | BA13: 0 | BB13: Scant or None (0-20) | BC13: 0 | BD13: 0 | BE13: Scant or None (0-20) | BF13: 0 | BG13: 0 | BH13: Scant or None (0-20) | BI13: 0 | BJ13: 0 | BK13: Scant or None (0-20) | BL13: 0 | BM13: 0 | BN13: Scant or None (0-20) | BO13: d | BP13: c | BQ13: b | BR13: d | BS13: d | BT13: d | BU13: d | BV13: c | BW13: e | BX13: e | BY13: c | BZ13: d | CA13: c | CB13: d | CD13: 0 | CE13: 0 | CF13: 0 | CG13: 100 | CH13: 0 | CI13: 0 | CJ13: 0 | CK13: 0 | CL13: 100 | CM13: 33 | CN13: 100 | CO13: 67 | CP13: 67 | CQ13: 0 | CR13: 67 | CS13: 0 | CT13: 33 | CU13: 0 | CV13: 0 | CW13: 0 | CX13: 100 | CY13: 0 | CZ13: 0 | DA13: 100 | DB13: 100 | DC13: 67 | DD13: 100 | DE13: 0 | DF13: 0 | DG13: 0 | DH13: 33 | DI13: 0 | DJ13: 0 | DK13: 0 | DL13: 0 | DM13: 0 | DN13: 33 | DO13: 0 | DP13: 0 | DQ13: 0 | DR13: 0 | DS13: 0 | DT13: 0 | DU13: 0 | DV13: 0 | DW13: 0 | DX13: 100 | DY13: 0 | DZ13: 0 | EA13: 0 | EB13: 0 | EC13: 0 | ED13: 0 | EE13: 0 | EF13: 0 | EG13: 0 | EH13: 0 | EI13: 0 | EJ13: 33 | EK13: 100 | EL13: 100 | EM13: 67 | EN13: 0 | EO13: 0 | EP13: 0 | EQ13: 0 | ER13: 0 | ES13: 0 | ET13: 0 | EU13: 0 | EV13: 0 | EW13: 0 | EX13: 0 | EY13: 0 | EZ13: 0 | FA13: 0 | FB13: 0 | FC13: 0 | FD13: 0 | FE13: 0 | FF13: 0 | FG13: 0 | FH13: 0 | FI13: 0 | FJ13: 0 | FK13: 0 | FL13: 0 | FM13: 0 | FN13: 0 | FO13: 0 | FP13: 0 | FQ13: 0 | FR13: 0 | FS13: 0 | FT13: 0 | FU13: 0 | FV13: 0 | FW13: 0 | FX13: 0 | FY13: 0 | FZ13: 0 | GA13: 0 | GB13: 0 | GC13: 0 | GD13: 0 | GE13: 0 | GF13: 0 | GG13: 33 | GH13: 100 | GI13: 67 | GJ13: 100 | GK13: 33 | GL13: 0 | GM13: 0 | GN13: 0 | GO13: 0 | GP13: 0 | GQ13: 0 | GR13: 0 | GS13: 0 | GT13: 67 | GU13: 67 | GV13: 0 | GW13: 33 | GX13: 0 | GY13: 0 | GZ13: 0 | HA13: 0 | HB13: 0 | HC13: 0 | HD13: 0 | HE13: 0 | HF13: 0 | HG13: 0 | HH13: 0 | HI13: 0 | HJ13: 0 | HK13: 0 | HL13: 0 | HM13: 0 | HN13: 0 | HO13: 0 | HP13: 0 | HQ13: 33 | HR13: 67 | HS13: 0 | HT13: 0 | HU13: 0 | HV13: 0 | HW13: 0 | HX13: 0 | HY13: 1 | HZ13: 1 | IA13: 1 | IB13: 1 | IC13: 1 | ID13: 1 | IE13: 1 | IF13: 1
A14: Algeria | B14: DZA | C14: 2021 | D14: Middle East & North Africa | E14: North Africa | F14: 3.3669725 | G14: 3 | H14: Scant or None (0-20) | I14: Low (0-40) | J14: Insufficient (0-60) | K14: Bottom Quintile | L14: 31.5 | M14: 32 | N14: Weak (0-40) | O14: 33.333333 | P14: 33 | Q14: Weak (0-40) | R14: 27.833333 | S14: 28 | T14: Weak (0-40) | U14: 0 | V14: 0 | W14: Weak (0-40) | X14: 0 | Y14: 0 | Z14: Few or no opportunities (0-40) | AA14: NP | AB14: HC | AC14: PW | AD14: NP | AE14: IU | AF14: NP | AG14: PL | AH14: PW | AI14: 0 | AJ14: 0 | AK14: 1 | AL14: 1 | AM14: 0 | AN14: 0 | AO14: 0 | AP14: 0 | AQ14: 0 | AR14: 0 | AS14: Scant or None (0-20) | AT14: 0 | AU14: 0 | AV14: Scant or None (0-20) | AW14: 39 | AX14: 39 | AY14: Minimal (21-40) | AZ14: 33.25 | BA14: 33 | BB14: Minimal (21-40) | BC14: 0 | BD14: 0 | BE14: Scant or None (0-20) | BF14: 0 | BG14: 0 | BH14: Scant or None (0-20) | BI14: 0 | BJ14: 0 | BK14: Scant or None (0-20) | BL14: 0 | BM14: 0 | BN14: Scant or None (0-20) | BO14: d | BP14: d | BQ14: b | BR14: d | BS14: d | BT14: d | BU14: d | BV14: d | BW14: b | BX14: e | BY14: d | BZ14: c | CA14: d | CB14: a | CD14: 0 | CE14: 0 | CF14: 0 | CG14: 0 | CH14: 0 | CI14: 0 | CJ14: 0 | CK14: 0 | CL14: 0 | CM14: 0 | CN14: 0 | CO14: 0 | CP14: 0 | CQ14: 0 | CR14: 0 | CS14: 0 | CT14: 0 | CU14: 0 | CV14: 0 | CW14: 0 | CX14: 0 | CY14: 0 | CZ14: 0 | DA14: 0 | DB14: 0 | DC14: 0 | DD14: 0 | DE14: 0 | DF14: 0 | DG14: 0 | DH14: 0 | DI14: 0 | DJ14: 0 | DK14: 0 | DL14: 0 | DM14: 0 | DN14: 0 | DO14: 0 | DP14: 0 | DQ14: 0 | DR14: 0 | DS14: 0 | DT14: 0 | DU14: 0 | DV14: 0 | DW14: 0 | DX14: 0 | DY14: 0 | DZ14: 0 | EA14: 0 | EB14: 0 | EC14: 0 | ED14: 0 | EE14: 0 | EF14: 0 | EG14: 0 | EH14: 0 | EI14: 0 | EJ14: 67 | EK14: 0 | EL14: 100 | EM14: 0 | EN14: 0 | EO14: 67 | EP14: 33 | EQ14: 0 | ER14: 33 | ES14: 0 | ET14: 0 | EU14: 0 | EV14: 0 | EW14: 0 | EX14: 0 | EY14: 0 | EZ14: 0 | FA14: 0 | FB14: 0 | FC14: 0 | FD14: 0 | FE14: 0 | FF14: 0 | FG14: 0 | FH14: 0 | FI14: 0 | FJ14: 0 | FK14: 0 | FL14: 0 | FM14: 0 | FN14: 0 | FO14: 0 | FP14: 0 | FQ14: 0 | FR14: 0 | FS14: 0 | FT14: 0 | FU14: 0 | FV14: 0 | FW14: 0 | FX14: 0 | FY14: 0 | FZ14: 0 | GA14: 0 | GB14: 0 | GC14: 0 | GD14: 0 | GE14: 0 | GF14: 0 | GG14: 67 | GH14: 100 | GI14: 67 | GJ14: 100 | GK14: 33 | GL14: 0 | GM14: 0 | GN14: 0 | GO14: 0 | GP14: 0 | GQ14: 33 | GR14: 0 | GS14: 0 | GT14: 67 | GU14: 67 | GV14: 0 | GW14: 33 | GX14: 0 | GY14: 0 | GZ14: 0 | HA14: 0 | HB14: 0 | HC14: 0 | HD14: 0 | HE14: 0 | HF14: 0 | HG14: 0 | HH14: 0 | HI14: 0 | HJ14: 0 | HK14: 0 | HL14: 0 | HM14: 0 | HN14: 0 | HO14: 0 | HP14: 0 | HQ14: 0 | HR14: 67 | HS14: 0 | HT14: 0 | HU14: 0 | HV14: 0 | HW14: 0 | HX14: 0 | HY14: 1 | HZ14: 1 | IA14: 1 | IB14: 1 | IC14: 1 | ID14: 1 | IE14: 1 | IF14: 1
A15: Algeria | B15: DZA | C15: 2019 | D15: Middle East & North Africa | E15: North Africa | F15: 2.146789 | G15: 2 | H15: Scant or None (0-20) | I15: Low (0-40) | J15: Insufficient (0-60) | K15: Bottom Quintile | L15: 35.166667 | M15: 35 | N15: Weak (0-40) | O15: 38.833333 | P15: 39 | Q15: Weak (0-40) | R15: 27.833333 | S15: 28 | T15: Weak (0-40) | U15: 0 | V15: 0 | W15: Weak (0-40) | X15: 0 | Y15: 0 | Z15: Few or no opportunities (0-40) | AA15: NP | AB15: IU | AC15: PW | AD15: IU | AE15: IU | AF15: NP | AG15: IU | AH15: NP | AI15: 0 | AJ15: 0 | AK15: 1 | AL15: 0 | AM15: 0 | AN15: 0 | AO15: 0 | AP15: 0 | AQ15: 0 | AR15: 0 | AS15: Scant or None (0-20) | AT15: 0 | AU15: 0 | AV15: Scant or None (0-20) | AW15: 39 | AX15: 39 | AY15: Minimal (21-40) | AZ15: 0 | BA15: 0 | BB15: Scant or None (0-20) | BC15: 0 | BD15: 0 | BE15: Scant or None (0-20) | BF15: 0 | BG15: 0 | BH15: Scant or None (0-20) | BI15: 0 | BJ15: 0 | BK15: Scant or None (0-20) | BL15: 0 | BM15: 0 | BN15: Scant or None (0-20) | BO15: d | BP15: d | BQ15: b | BR15: d | BS15: d | BT15: d | BU15: d | BV15: d | BW15: c | BX15: e | BY15: c | BZ15: c | CA15: d | CB15: c | CD15: 0 | CE15: 0 | CF15: 0 | CG15: 0 | CH15: 0 | CI15: 0 | CJ15: 0 | CK15: 0 | CL15: 0 | CM15: 0 | CN15: 0 | CO15: 0 | CP15: 0 | CQ15: 0 | CR15: 0 | CS15: 0 | CT15: 0 | CU15: 0 | CV15: 0 | CW15: 0 | CX15: 0 | CY15: 0 | CZ15: 0 | DA15: 0 | DB15: 0 | DC15: 0 | DD15: 0 | DE15: 0 | DF15: 0 | DG15: 0 | DH15: 0 | DI15: 0 | DJ15: 0 | DK15: 0 | DL15: 0 | DM15: 0 | DN15: 0 | DO15: 0 | DP15: 0 | DQ15: 0 | DR15: 0 | DS15: 0 | DT15: 0 | DU15: 0 | DV15: 0 | DW15: 0 | DX15: 0 | DY15: 0 | DZ15: 0 | EA15: 0 | EB15: 0 | EC15: 0 | ED15: 0 | EE15: 0 | EF15: 0 | EG15: 0 | EH15: 0 | EI15: 0 | EJ15: 67 | EK15: 0 | EL15: 100 | EM15: 0 | EN15: 0 | EO15: 0 | EP15: 0 | EQ15: 0 | ER15: 0 | ES15: 0 | ET15: 0 | EU15: 0 | EV15: 0 | EW15: 0 | EX15: 0 | EY15: 0 | EZ15: 0 | FA15: 0 | FB15: 0 | FC15: 0 | FD15: 0 | FE15: 0 | FF15: 0 | FG15: 0 | FH15: 0 | FI15: 0 | FJ15: 0 | FK15: 0 | FL15: 0 | FM15: 0 | FN15: 0 | FO15: 0 | FP15: 0 | FQ15: 0 | FR15: 0 | FS15: 0 | FT15: 0 | FU15: 0 | FV15: 0 | FW15: 0 | FX15: 0 | FY15: 0 | FZ15: 0 | GA15: 0 | GB15: 0 | GC15: 0 | GD15: 0 | GE15: 0 | GF15: 0 | GG15: 67 | GH15: 100 | GI15: 67 | GJ15: 100 | GK15: 33 | GL15: 33 | GM15: 33 | GN15: 0 | GO15: 0 | GP15: 0 | GQ15: 33 | GR15: 0 | GS15: 0 | GT15: 67 | GU15: 67 | GV15: 0 | GW15: 33 | GX15: 0 | GY15: 0 | GZ15: 0 | HA15: 0 | HB15: 0 | HC15: 0 | HD15: 0 | HE15: 0 | HF15: 0 | HG15: 0 | HH15: 0 | HI15: 0 | HJ15: 0 | HK15: 0 | HL15: 0 | HM15: 0 | HN15: 0 | HO15: 0 | HP15: 0 | HQ15: 0 | HR15: 67 | HS15: 0 | HT15: 0 | HU15: 0 | HV15: 0 | HW15: 0 | HX15: 0 | HY15: 1 | HZ15: 1 | IA15: 1 | IB15: 1 | IC15: 1 | ID15: 1 | IE15: 1 | IF15: 1
A16: Algeria | B16: DZA | C16: 2017 | D16: Middle East & North Africa | E16: North Africa | F16: 3.0642202 | G16: 3 | H16: Scant or None (0-20) | I16: Low (0-40) | J16: Insufficient (0-60) | K16: Bottom Quintile | L16: 31.444444 | M16: 31 | N16: Weak (0-40) | O16: 41.583333 | P16: 42 | Q16: Limited (41-60) | R16: 11.166667 | S16: 11 | T16: Weak (0-40) | U16: 0 | V16: 0 | W16: Weak (0-40) | X16: 0 | Y16: 0 | Z16: Few or No (0-40) | AA16: IU | AB16: IU | AC16: PW | AD16: NP | AE16: IU | AF16: IU | AG16: IU | AH16: NP | AI16: 0 | AJ16: 0 | AK16: 1 | AL16: 0 | AM16: 0 | AN16: 0 | AO16: 0 | AP16: 0 | AQ16: 0 | AR16: 0 | AS16: Scant or None (0-20) | AT16: 0 | AU16: 0 | AV16: Scant or None (0-20) | AW16: 55.666667 | AX16: 56 | AY16: Limited (41-60) | AZ16: 0 | BA16: 0 | BB16: Scant or None (0-20) | BC16: 0 | BD16: 0 | BE16: Scant or None (0-20) | BF16: 0 | BG16: 0 | BH16: Scant or None (0-20) | BI16: 0 | BJ16: 0 | BK16: Scant or None (0-20) | BL16: 0 | BM16: 0 | BN16: Scant or None (0-20) | BO16: d | BP16: d | BQ16: a | BR16: d | BS16: d | BT16: d | BU16: d | CD16: 0 | CE16: 0 | CF16: 0 | CG16: 0 | CH16: 0 | CI16: 0 | CJ16: 0 | CK16: 0 | CL16: 0 | CM16: 0 | CN16: 0 | CO16: 0 | CP16: 0 | CQ16: 0 | CR16: 0 | CS16: 0 | CT16: 0 | CU16: 0 | CV16: 0 | CW16: 0 | CX16: 0 | CY16: 0 | CZ16: 0 | DA16: 0 | DB16: 0 | DC16: 0 | DD16: 0 | DE16: 0 | DF16: 0 | DG16: 0 | DH16: 0 | DI16: 0 | DJ16: 0 | DK16: 0 | DL16: 0 | DM16: 0 | DN16: 0 | DO16: 0 | DP16: 0 | DQ16: 0 | DR16: 0 | DS16: 0 | DT16: 0 | DU16: 0 | DV16: 0 | DW16: 0 | DX16: 0 | DY16: 0 | DZ16: 0 | EA16: 0 | EB16: 0 | EC16: 0 | ED16: 0 | EE16: 0 | EF16: 0 | EG16: 0 | EH16: 0 | EI16: 0 | EJ16: 67 | EK16: 0 | EL16: 100 | EM16: 67 | EN16: 0 | EO16: 0 | EP16: 0 | EQ16: 0 | ER16: 0 | ES16: 0 | ET16: 0 | EU16: 0 | EV16: 0 | EW16: 0 | EX16: 0 | EY16: 0 | EZ16: 0 | FA16: 0 | FB16: 0 | FC16: 0 | FD16: 0 | FE16: 0 | FF16: 0 | FG16: 0 | FH16: 0 | FI16: 0 | FJ16: 0 | FK16: 0 | FL16: 0 | FM16: 0 | FN16: 0 | FO16: 0 | FP16: 0 | FQ16: 0 | FR16: 0 | FS16: 0 | FT16: 0 | FU16: 0 | FV16: 0 | FW16: 0 | FX16: 0 | FY16: 0 | FZ16: 0 | GA16: 0 | GB16: 0 | GC16: 0 | GD16: 0 | GE16: 0 | GF16: 0 | GG16: 100 | GH16: 100 | GI16: 67 | GJ16: 100 | GK16: 33 | GL16: 33 | GM16: 33 | GN16: 0 | GO16: 0 | GP16: 0 | GQ16: 33 | GR16: 0 | GS16: 0 | GT16: 0 | GU16: 67 | GV16: 0 | GW16: 0 | GX16: 0 | GY16: 0 | GZ16: 0 | HA16: 0 | HB16: 0 | HC16: 0 | HD16: 0 | HE16: 0 | HF16: 0 | HG16: 0 | HH16: 0 | HI16: 0 | HJ16: 0 | HK16: 0 | HL16: 0 | HM16: 0 | HN16: 0 | HO16: 0 | HP16: 0 | HQ16: 0 | HR16: 100 | HS16: 0 | HT16: 0 | HU16: 0 | HV16: 0 | HW16: 0 | HX16: 0 | HY16: 1 | HZ16: 1 | IA16: 1 | IB16: 1 | IC16: 1 | ID16: 1 | IE16: 1 | IF16: 1
A17: Algeria | B17: DZA | C17: 2015 | D17: Middle East & North Africa | E17: North Africa | F17: 18.963301 | G17: 19 | H17: Scant or None (0-20) | I17: Low (0-40) | J17: Insufficient (0-60) | K17: Bottom Quintile | O17: 36.272701 | P17: 36 | Q17: Weak | R17: 33.5 | S17: 34 | T17: Moderate | X17: 0 | Y17: 0 | Z17: No | AA17: IU | AB17: PW | AC17: PW | AD17: PW | AE17: NP | AF17: NP | AG17: NP | AH17: NP | AI17: 0 | AJ17: 1 | AK17: 1 | AL17: 0 | AM17: 1 | AN17: 0 | AO17: 0 | AP17: 0 | AQ17: 0 | AR17: 0 | AS17: Scant or None (0-20) | AT17: 30.8519 | AU17: 31 | AV17: Minimal (21-40) | AW17: 50.166698 | AX17: 50 | AY17: Limited (41-60) | AZ17: 0 | BA17: 0 | BB17: Scant or None (0-20) | BC17: 11.1111 | BD17: 11 | BE17: Scant or None (0-20) | BF17: 0 | BG17: 0 | BH17: Scant or None (0-20) | BI17: 0 | BJ17: 0 | BK17: Scant or None (0-20) | BL17: 0 | BM17: 0 | BN17: Scant or None (0-20) | CD17: 100 | CE17: 100 | CF17: 0 | CG17: 0 | CH17: 0 | CI17: 0 | CJ17: 0 | CK17: 0 | CL17: 100 | CM17: 67 | CN17: 0 | CO17: 0 | CP17: 0 | CQ17: 0 | CR17: 67 | CS17: 0 | CT17: 33 | CU17: 33 | CV17: 0 | CW17: 0 | CX17: 100 | CY17: 0 | CZ17: 0 | DA17: 100 | DB17: 100 | DC17: 33 | DD17: 100 | DE17: 100 | DF17: 33 | DG17: 100 | DH17: 0 | DI17: 100 | DJ17: 33 | DK17: 0 | DL17: 67 | DM17: 33 | DN17: 67 | DO17: 33 | DP17: 0 | DQ17: 0 | DR17: 0 | DS17: 0 | DT17: 0 | DU17: 0 | DV17: 0 | DW17: 0 | DX17: 0 | DY17: 0 | DZ17: 0 | EA17: 0 | EB17: 0 | EC17: 67 | ED17: 0 | EE17: 0 | EF17: 0 | EG17: 0 | EH17: 0 | EI17: 0 | EJ17: 67 | EK17: 0 | EL17: 100 | EM17: 67 | EN17: 0 | EO17: 0 | EP17: 0 | EQ17: 0 | ER17: 0 | ES17: 0 | ET17: 0 | EU17: 0 | EV17: 0 | EW17: 0 | EX17: 0 | EY17: 33 | EZ17: 0 | FA17: 0 | FB17: 0 | FC17: 0 | FD17: 0 | FE17: 0 | FF17: 0 | FG17: 0 | FH17: 0 | FI17: 0 | FJ17: 0 | FK17: 0 | FL17: 0 | FM17: 0 | FN17: 0 | FO17: 0 | FP17: 0 | FQ17: 0 | FR17: 0 | FS17: 0 | FT17: 0 | FU17: 0 | FV17: 0 | FW17: 0 | FX17: 0 | FY17: 0 | FZ17: 0 | GA17: 0 | GB17: 0 | GC17: 67 | GD17: 33 | GE17: 100 | GF17: 100 | GG17: 33 | GH17: 33 | GI17: 0 | GJ17: 33 | GK17: 0 | GL17: 0 | GM17: 0 | GN17: 67 | GO17: 0 | GP17: 0 | GQ17: 67 | GR17: 0 | GS17: 0 | GT17: 0 | GU17: 0 | GV17: 0 | GW17: 0 | GX17: 0 | GY17: 0 | GZ17: 0 | HA17: 0 | HB17: 0 | HC17: 0 | HD17: 0 | HE17: 0 | HF17: 0 | HP17: 0 | HQ17: 100 | HR17: 67 | HS17: 67 | HT17: 0 | HU17: 0 | HV17: 0 | HW17: 0 | HX17: 0 | HY17: 1 | HZ17: 1 | IA17: 1 | IB17: 1 | IC17: 1 | ID17: 1 | IE17: 1 | IF17: 1
A18: Algeria | B18: DZA | C18: 2012 | D18: Middle East & North Africa | E18: North Africa | F18: 13.3263 | G18: 13 | H18: Scant or None (0-20) | I18: Low (0-40) | J18: Insufficient (0-60) | K18: Bottom Quintile | O18: 21.181801 | P18: 21 | Q18: Weak | R18: 33.5 | S18: 34 | T18: Moderate | X18: 13.8333 | Y18: 14 | Z18: Weak | AA18: IU | AB18: PW | AC18: PW | AD18: IU | AE18: IU | AF18: IU | AG18: IU | AH18: NP | AI18: 0 | AJ18: 1 | AK18: 1 | AL18: 0 | AM18: 0 | AN18: 0 | AO18: 0 | AP18: 0 | AQ18: 0 | AR18: 0 | AS18: Scant or None (0-20) | AT18: 20.103399 | AU18: 20 | AV18: Scant or None (0-20) | AW18: 100 | AX18: 100 | AY18: Extensive (81-100) | AZ18: 0 | BA18: 0 | BB18: Scant or None (0-20) | BC18: 0 | BD18: 0 | BE18: Scant or None (0-20) | BF18: 0 | BG18: 0 | BH18: Scant or None (0-20) | BI18: 0 | BJ18: 0 | BK18: Scant or None (0-20) | BL18: 0 | BM18: 0 | BN18: Scant or None (0-20) | CD18: 33 | CI18: 0 | CL18: 100 | CM18: 100 | CQ18: 0 | CR18: 67 | CS18: 0 | CT18: 0 | CU18: 0 | CW18: 0 | CX18: 100 | DA18: 33 | DD18: 0 | DG18: 67 | DH18: 0 | DI18: 0 | DJ18: 0 | DL18: 0 | DN18: 0 | DO18: 0 | DP18: 0 | DQ18: 0 | DR18: 0 | DS18: 0 | DT18: 0 | DU18: 0 | DV18: 0 | DW18: 0 | DX18: 0 | DY18: 0 | EA18: 0 | EB18: 0 | EC18: 0 | ED18: 0 | EE18: 0 | EO18: 0 | EP18: 0 | EQ18: 0 | ER18: 0 | EU18: 0 | EW18: 0 | EX18: 0 | EZ18: 0 | FA18: 0 | FB18: 0 | FE18: 0 | FI18: 0 | FL18: 0 | FP18: 0 | FQ18: 0 | FR18: 0 | FS18: 0 | FT18: 0 | FW18: 0 | FX18: 0 | FY18: 0 | FZ18: 0 | GA18: 0 | GB18: 0 | GC18: 0 | GD18: 0 | GE18: 100 | GG18: 33 | GH18: 0 | GI18: 0 | GJ18: 0 | GK18: 0 | GL18: 100 | GM18: 0 | GN18: 67 | GP18: 0 | GQ18: 67 | GR18: 0 | GS18: 33 | GT18: 33 | GV18: 33 | GW18: 0 | GX18: 67 | GY18: 0 | GZ18: 0 | HA18: 0 | HB18: 0 | HE18: 0 | HF18: 0 | HP18: 0 | HQ18: 100 | HS18: 0 | HU18: 0 | HV18: 0 | HW18: 0 | HX18: 0 | HY18: 1 | HZ18: 1 | IA18: 1 | IB18: 1 | IC18: 1 | ID18: 1 | IE18: 1 | IF18: 1
A19: Algeria | B19: DZA | C19: 2010 | D19: Middle East & North Africa | E19: North Africa | F19: 0.72826099 | G19: 1 | H19: Scant or None (0-20) | I19: Low (0-40) | J19: Insufficient (0-60) | K19: Bottom Quintile | O19: 33.333302 | P19: 33 | Q19: Weak | R19: 13.4 | S19: 13 | T19: Weak | AA19: IU | AB19: IU | AC19: PW | AD19: NP | AE19: IU | AF19: IU | AG19: IU | AH19: NP | AI19: 0 | AJ19: 0 | AK19: 1 | AL19: 0 | AM19: 0 | AN19: 0 | AO19: 0 | AP19: 0 | AQ19: 0 | AR19: 0 | AS19: Scant or None (0-20) | AT19: 0 | AU19: 0 | AV19: Scant or None (0-20) | AW19: 67 | AX19: 67 | AY19: Substantial (61-80 | AZ19: 0 | BA19: 0 | BB19: Scant or None (0-20) | BC19: 0 | BD19: 0 | BE19: Scant or None (0-20) | BF19: 0 | BG19: 0 | BH19: Scant or None (0-20) | BI19: 0 | BJ19: 0 | BK19: Scant or None (0-20) | BL19: 0 | BM19: 0 | BN19: Scant or None (0-20) | CD19: 0 | CI19: 0 | CL19: 0 | CM19: 0 | CQ19: 0 | CR19: 0 | CS19: 0 | CT19: 0 | CU19: 0 | CW19: 0 | CX19: 0 | DA19: 0 | DD19: 0 | DG19: 0 | DH19: 0 | DI19: 0 | DJ19: 0 | DL19: 0 | DN19: 0 | DO19: 0 | DP19: 0 | DQ19: 0 | DR19: 0 | DS19: 0 | DT19: 0 | DU19: 0 | DV19: 0 | DW19: 0 | DX19: 0 | DY19: 0 | EA19: 0 | EB19: 0 | EC19: 0 | ED19: 0 | EE19: 0 | EO19: 0 | EU19: 0 | EW19: 0 | EX19: 0 | EZ19: 0 | FA19: 0 | FB19: 0 | FE19: 0 | FI19: 0 | FL19: 0 | FP19: 0 | FQ19: 0 | FR19: 0 | FS19: 0 | FT19: 0 | FW19: 0 | FX19: 0 | FY19: 0 | FZ19: 0 | GA19: 0 | GD19: 0 | GE19: 100 | GG19: 67 | GH19: 0 | GK19: 0 | GL19: 100 | GM19: 0 | GN19: 67 | GP19: 0 | GQ19: 67 | GR19: 0 | GY19: 33 | GZ19: 33 | HA19: 0 | HB19: 0 | HP19: 0 | HQ19: 100 | HS19: 0 | HU19: 0 | HV19: 0 | HW19: 0 | HX19: 0 | HY19: 1 | HZ19: 1 | IA19: 1 | IB19: 1 | IC19: 1 | ID19: 1 | IE19: 1 | IF19: 1
A20: Algeria | B20: DZA | C20: 2008 | D20: Middle East & North Africa | E20: North Africa | F20: 1.81522 | G20: 2 | H20: Scant or None (0-20) | I20: Low (0-40) | J20: Insufficient (0-60) | K20: Bottom Quintile | O20: 30.5 | P20: 31 | Q20: Weak | R20: 16.700001 | S20: 17 | T20: Weak | AA20: IU | AB20: IU | AC20: PW | AD20: IU | AE20: IU | AF20: IU | AG20: IU | AH20: NP | AI20: 0 | AJ20: 0 | AK20: 1 | AL20: 0 | AM20: 0 | AN20: 0 | AO20: 0 | AP20: 0 | AQ20: 0 | AR20: 0 | AS20: Scant or None (0-20) | AT20: 0 | AU20: 0 | AV20: Scant or None (0-20) | AW20: 67 | AX20: 67 | AY20: Substantial (61-80 | AZ20: 0 | BA20: 0 | BB20: Scant or None (0-20) | BC20: 0 | BD20: 0 | BE20: Scant or None (0-20) | BF20: 0 | BG20: 0 | BH20: Scant or None (0-20) | BI20: 0 | BJ20: 0 | BK20: Scant or None (0-20) | BL20: 0 | BM20: 0 | BN20: Scant or None (0-20) | CD20: 0 | CI20: 0 | CL20: 0 | CM20: 0 | CQ20: 0 | CR20: 0 | CS20: 0 | CT20: 0 | CU20: 0 | CW20: 0 | CX20: 0 | DA20: 0 | DD20: 0 | DG20: 0 | DH20: 0 | DI20: 0 | DJ20: 0 | DL20: 0 | DN20: 0 | DO20: 0 | DP20: 0 | DQ20: 0 | DR20: 0 | DS20: 0 | DT20: 0 | DU20: 0 | DV20: 0 | DW20: 0 | DX20: 0 | DY20: 0 | EA20: 0 | EB20: 0 | EC20: 0 | ED20: 0 | EE20: 0 | EO20: 0 | EU20: 0 | EW20: 0 | EX20: 0 | EZ20: 0 | FA20: 0 | FB20: 0 | FE20: 0 | FI20: 0 | FL20: 0 | FP20: 0 | FQ20: 0 | FR20: 0 | FS20: 0 | FT20: 0 | FW20: 0 | FX20: 0 | FY20: 0 | FZ20: 0 | GA20: 0 | GD20: 33 | GE20: 100 | GG20: 33 | GH20: 0 | GK20: 100 | GL20: 0 | GM20: 0 | GN20: 100 | GP20: 0 | GQ20: 67 | GR20: 0 | GY20: 0 | GZ20: 33 | HA20: 0 | HB20: 0 | HP20: 0 | HQ20: 100 | HS20: 0 | HU20: 0 | HV20: 0 | HW20: 0 | HX20: 0 | HY20: 1 | HZ20: 1 | IA20: 1 | IB20: 1 | IC20: 1 | ID20: 1 | IE20: 1 | IF20: 1
A21: Algeria | B21: DZA | C21: 2006 | D21: Middle East & North Africa | E21: North Africa | F21: 28.1957 | G21: 28 | H21: Minimal (21-40) | I21: Low (0-40) | J21: Insufficient (0-60) | K21: 2nd Quintile | O21: 38.833302 | P21: 39 | Q21: Weak | R21: 12.5 | S21: 13 | T21: Weak | AA21: IU | AB21: HC | AC21: PW | AD21: IU | AE21: IU | AF21: PW | AG21: IU | AH21: NP | AI21: 0 | AJ21: 1 | AK21: 1 | AL21: 0 | AM21: 0 | AN21: 0 | AO21: 1 | AP21: 0 | AQ21: 0 | AR21: 0 | AS21: Scant or None (0-20) | AT21: 40.527302 | AU21: 41 | AV21: Limited (41-60) | AW21: 67 | AX21: 67 | AY21: Substantial (61-80 | AZ21: 0 | BA21: 0 | BB21: Scant or None (0-20) | BC21: 0 | BD21: 0 | BE21: Scant or None (0-20) | BF21: 0 | BG21: 0 | BH21: Scant or None (0-20) | BI21: 29.799999 | BJ21: 30 | BK21: Minimal (21-40) | BL21: 0 | BM21: 0 | BN21: Scant or None (0-20) | CD21: 67 | CI21: 33 | CL21: 100 | CM21: 33 | CQ21: 0 | CR21: 67 | CS21: 0 | CT21: 33 | CU21: 33 | CW21: 33 | CX21: 33 | DA21: 100 | DD21: 33 | DG21: 100 | DH21: 67 | DI21: 100 | DJ21: 67 | DL21: 67 | DN21: 33 | DO21: 33 | DP21: 33 | DQ21: 0 | DR21: 0 | DS21: 0 | DT21: 0 | DU21: 0 | DV21: 0 | DW21: 0 | DX21: 67 | DY21: 67 | EA21: 0 | EB21: 0 | EC21: 33 | ED21: 0 | EE21: 0 | EO21: 0 | EU21: 0 | EW21: 0 | EX21: 0 | EZ21: 0 | FA21: 0 | FB21: 0 | FE21: 0 | FI21: 33 | FL21: 33 | FP21: 33 | FQ21: 0 | FR21: 0 | FS21: 33 | FT21: 33 | FW21: 0 | FX21: 0 | FY21: 0 | FZ21: 0 | GA21: 0 | GD21: 100 | GE21: 100 | GG21: 33 | GH21: 0 | GK21: 100 | GL21: 0 | GM21: 0 | GN21: 33 | GP21: 0 | GQ21: 67 | GR21: 0 | GY21: 0 | GZ21: 33 | HA21: 0 | HB21: 0 | HP21: 0 | HQ21: 100 | HS21: 0 | HU21: 33 | HV21: 0 | HW21: 0 | HX21: 0 | HY21: 1 | HZ21: 1 | IA21: 1 | IB21: 1 | IC21: 1 | ID21: 1 | IE21: 1 | IF21: 1
A22: Argentina | B22: ARG | C22: 2025 | D22: Latin America & Caribbean | E22: South America | F22: 46.146789 | G22: 46 | H22: Limited (41-60) | I22: Limited (41-60) | J22: Insufficient (0-60) | K22: Middle Quintile | L22: 44.333333 | M22: 44 | N22: Limited (41-60) | O22: 27.666667 | P22: 28 | Q22: Weak (0-40) | R22: 77.666667 | S22: 78 | T22: Adequate (61-100) | U22: 50 | V22: 50 | W22: Limited (41-60) | X22: 18.5 | Y22: 19 | Z22: Few or no opportunities (0-40) | AA22: PW | AB22: PW | AC22: PW | AD22: PW | AE22: NP | AF22: PW | AG22: NP | AH22: PW | AI22: 1 | AJ22: 1 | AK22: 1 | AL22: 1 | AM22: 1 | AN22: 0 | AO22: 1 | AP22: 0 | AQ22: 27.666667 | AR22: 28 | AS22: Minimal (21-40) | AT22: 53.685185 | AU22: 54 | AV22: Limited (41-60) | AW22: 33.333333 | AX22: 33 | AY22: Minimal (21-40) | AZ22: 50 | BA22: 50 | BB22: Limited (41-60) | BC22: 70.222222 | BD22: 70 | BE22: Substantial (61-80) | BF22: 0 | BG22: 0 | BH22: Scant or None (0-20) | BI22: 59.5 | BJ22: 60 | BK22: Limited (41-60) | BL22: 14.285714 | BM22: 14 | BN22: Scant or None (0-20) | BO22: a | BP22: a | BQ22: c | BR22: c | BS22: d | BT22: b | BU22: d | BV22: e | BW22: e | BX22: e | BY22: e | BZ22: d | CA22: e | CB22: d | CC22: e | CD22: 100 | CE22: 100 | CF22: 0 | CG22: 100 | CH22: 100 | CI22: 100 | CJ22: 0 | CK22: 0 | CL22: 100 | CM22: 100 | CN22: 0 | CO22: 0 | CP22: 100 | CQ22: 67 | CR22: 33 | CS22: 33 | CT22: 100 | CU22: 100 | CV22: 100 | CW22: 0 | CX22: 100 | CY22: 0 | CZ22: 0 | DA22: 0 | DB22: 100 | DC22: 100 | DD22: 100 | DE22: 0 | DF22: 0 | DG22: 0 | DH22: 33 | DI22: 0 | DJ22: 100 | DK22: 100 | DL22: 100 | DM22: 0 | DN22: 100 | DO22: 33 | DP22: 0 | DQ22: 0 | DR22: 0 | DS22: 67 | DT22: 0 | DU22: 100 | DV22: 100 | DW22: 33 | DX22: 33 | DY22: 0 | DZ22: 33 | EA22: 67 | EB22: 67 | EC22: 100 | ED22: 100 | EE22: 0 | EF22: 33 | EG22: 33 | EH22: 0 | EI22: 0 | EJ22: 0 | EK22: 100 | EL22: 0 | EM22: 0 | EN22: 67 | EO22: 100 | EP22: 33 | EQ22: 0 | ER22: 67 | ES22: 33 | ET22: 100 | EU22: 100 | EV22: 100 | EW22: 100 | EX22: 100 | EY22: 33 | EZ22: 33 | FA22: 0 | FB22: 0 | FC22: 0 | FD22: 0 | FE22: 0 | FF22: 0 | FG22: 0 | FH22: 0 | FI22: 67 | FJ22: 100 | FK22: 100 | FL22: 67 | FM22: 100 | FN22: 100 | FO22: 33 | FP22: 0 | FQ22: 33 | FR22: 33 | FS22: 33 | FT22: 0 | FU22: 100 | FV22: 100 | FW22: 0 | FX22: 0 | FY22: 0 | FZ22: 0 | GA22: 0 | GB22: 67 | GC22: 33 | GD22: 67 | GE22: 33 | GF22: 0 | GG22: 100 | GH22: 0 | GI22: 100 | GJ22: 33 | GK22: 33 | GL22: 33 | GM22: 0 | GN22: 0 | GO22: 33 | GP22: 0 | GQ22: 0 | GR22: 100 | GS22: 100 | GT22: 100 | GU22: 100 | GV22: 33 | GW22: 33 | GX22: 0 | GY22: 0 | GZ22: 0 | HA22: 0 | HB22: 0 | HC22: 0 | HD22: 0 | HE22: 0 | HF22: 0 | HG22: 0 | HH22: 0 | HI22: 33 | HJ22: 67 | HK22: 33 | HL22: 0 | HM22: 100 | HN22: 100 | HO22: 0 | HP22: 100 | HQ22: 100 | HR22: 33 | HS22: 33 | HT22: 0 | HU22: 67 | HV22: 0 | HW22: 0 | HX22: 1 | HY22: 1 | HZ22: 1 | IA22: 1 | IB22: 1 | IC22: 1 | ID22: 1 | IE22: 1 | IF22: 1
A23: Argentina | B23: ARG | C23: 2023 | D23: Latin America & Caribbean | E23: South America | F23: 51.045872 | G23: 51 | H23: Limited (41-60) | I23: Limited (41-60) | J23: Insufficient (0-60) | K23: Middle Quintile | L23: 59.222222 | M23: 59 | N23: Limited (41-60) | O23: 44.416667 | P23: 44 | Q23: Limited (41-60) | R23: 88.833333 | S23: 89 | T23: Adequate (61-100) | U23: 50 | V23: 50 | W23: Limited (41-60) | X23: 16.611111 | Y23: 17 | Z23: Few or no opportunities (0-40) | AA23: PW | AB23: PW | AC23: PW | AD23: PW | AE23: NP | AF23: PW | AG23: NP | AH23: PW | AI23: 1 | AJ23: 1 | AK23: 1 | AL23: 1 | AM23: 1 | AN23: 0 | AO23: 1 | AP23: 0 | AQ23: 27.666667 | AR23: 28 | AS23: Minimal (21-40) | AT23: 54.296296 | AU23: 54 | AV23: Limited (41-60) | AW23: 100 | AX23: 100 | AY23: Extensive (81-100) | AZ23: 50 | BA23: 50 | BB23: Limited (41-60) | BC23: 70.333333 | BD23: 70 | BE23: Substantial (61-80 | BF23: 0 | BG23: 0 | BH23: Scant or None (0-20) | BI23: 66.642857 | BJ23: 67 | BK23: Substantial (61-80 | BL23: 14.285714 | BM23: 14 | BN23: Scant or None (0-20) | BO23: a | BP23: a | BQ23: a | BR23: c | BS23: d | BT23: b | BU23: d | BV23: e | BW23: e | BX23: e | BY23: e | BZ23: d | CA23: e | CB23: d | CD23: 100 | CE23: 100 | CF23: 0 | CG23: 100 | CH23: 100 | CI23: 100 | CJ23: 0 | CK23: 0 | CL23: 100 | CM23: 100 | CN23: 0 | CO23: 0 | CP23: 100 | CQ23: 67 | CR23: 33 | CS23: 0 | CT23: 100 | CU23: 33 | CV23: 100 | CW23: 0 | CX23: 100 | CY23: 0 | CZ23: 0 | DA23: 0 | DB23: 100 | DC23: 100 | DD23: 100 | DE23: 0 | DF23: 0 | DG23: 0 | DH23: 33 | DI23: 100 | DJ23: 100 | DK23: 100 | DL23: 67 | DM23: 100 | DN23: 100 | DO23: 67 | DP23: 0 | DQ23: 0 | DR23: 0 | DS23: 33 | DT23: 0 | DU23: 100 | DV23: 100 | DW23: 33 | DX23: 33 | DY23: 0 | DZ23: 33 | EA23: 67 | EB23: 33 | EC23: 100 | ED23: 100 | EE23: 33 | EF23: 33 | EG23: 0 | EH23: 0 | EI23: 0 | EJ23: 100 | EK23: 100 | EL23: 100 | EM23: 100 | EN23: 100 | EO23: 100 | EP23: 33 | EQ23: 0 | ER23: 67 | ES23: 100 | ET23: 100 | EU23: 100 | EV23: 100 | EW23: 100 | EX23: 100 | EY23: 0 | EZ23: 0 | FA23: 0 | FB23: 0 | FC23: 0 | FD23: 0 | FE23: 0 | FF23: 0 | FG23: 0 | FH23: 0 | FI23: 100 | FJ23: 100 | FK23: 100 | FL23: 100 | FM23: 100 | FN23: 67 | FO23: 33 | FP23: 0 | FQ23: 33 | FR23: 33 | FS23: 33 | FT23: 67 | FU23: 100 | FV23: 100 | FW23: 0 | FX23: 0 | FY23: 0 | FZ23: 0 | GA23: 0 | GB23: 67 | GC23: 33 | GD23: 67 | GE23: 33 | GF23: 0 | GG23: 100 | GH23: 100 | GI23: 100 | GJ23: 100 | GK23: 100 | GL23: 33 | GM23: 0 | GN23: 0 | GO23: 0 | GP23: 0 | GQ23: 0 | GR23: 100 | GS23: 100 | GT23: 100 | GU23: 100 | GV23: 100 | GW23: 33 | GX23: 0 | GY23: 0 | GZ23: 0 | HA23: 0 | HB23: 0 | HC23: 0 | HD23: 0 | HE23: 0 | HF23: 0 | HG23: 0 | HH23: 0 | HI23: 33 | HJ23: 33 | HK23: 33 | HL23: 0 | HM23: 100 | HN23: 100 | HO23: 0 | HP23: 100 | HQ23: 100 | HR23: 100 | HS23: 33 | HT23: 0 | HU23: 67 | HV23: 0 | HW23: 0 | HX23: 1 | HY23: 1 | HZ23: 1 | IA23: 1 | IB23: 1 | IC23: 1 | ID23: 1 | IE23: 1 | IF23: 1
A24: Argentina | B24: ARG | C24: 2021 | D24: Latin America & Caribbean | E24: South America | F24: 50.146789 | G24: 50 | H24: Limited (41-60) | I24: Limited (41-60) | J24: Insufficient (0-60) | K24: Middle Quintile | L24: 53.666667 | M24: 54 | N24: Limited (41-60) | O24: 41.666667 | P24: 42 | Q24: Limited (41-60) | R24: 77.666667 | S24: 78 | T24: Adequate (61-100) | U24: 75.25 | V24: 75 | W24: Adequate (61-100) | X24: 14.777778 | Y24: 15 | Z24: Few or no opportunities (0-40) | AA24: PW | AB24: PW | AC24: PW | AD24: PW | AE24: NP | AF24: PW | AG24: IU | AH24: PW | AI24: 1 | AJ24: 1 | AK24: 1 | AL24: 1 | AM24: 1 | AN24: 0 | AO24: 1 | AP24: 0 | AQ24: 22.166667 | AR24: 22 | AS24: Minimal (21-40) | AT24: 53.074074 | AU24: 53 | AV24: Limited (41-60) | AW24: 94.5 | AX24: 95 | AY24: Extensive (81-100) | AZ24: 58.5 | BA24: 59 | BB24: Limited (41-60) | BC24: 74 | BD24: 74 | BE24: Substantial (61-80 | BF24: 0 | BG24: 0 | BH24: Scant or None (0-20) | BI24: 64.285714 | BJ24: 64 | BK24: Substantial (61-80 | BL24: 14.285714 | BM24: 14 | BN24: Scant or None (0-20) | BO24: a | BP24: a | BQ24: a | BR24: c | BS24: d | BT24: b | BU24: d | BV24: e | BW24: e | BX24: e | BY24: e | BZ24: d | CA24: e | CB24: c | CD24: 100 | CE24: 100 | CF24: 0 | CG24: 100 | CH24: 100 | CI24: 100 | CJ24: 0 | CK24: 0 | CL24: 100 | CM24: 100 | CN24: 0 | CO24: 0 | CP24: 100 | CQ24: 67 | CR24: 67 | CS24: 0 | CT24: 100 | CU24: 0 | CV24: 100 | CW24: 0 | CX24: 100 | CY24: 33 | CZ24: 0 | DA24: 0 | DB24: 100 | DC24: 100 | DD24: 100 | DE24: 0 | DF24: 0 | DG24: 0 | DH24: 33 | DI24: 100 | DJ24: 100 | DK24: 100 | DL24: 67 | DM24: 100 | DN24: 100 | DO24: 67 | DP24: 0 | DQ24: 0 | DR24: 0 | DS24: 33 | DT24: 0 | DU24: 67 | DV24: 100 | DW24: 33 | DX24: 33 | DY24: 0 | DZ24: 0 | EA24: 33 | EB24: 33 | EC24: 100 | ED24: 100 | EE24: 0 | EF24: 33 | EG24: 0 | EH24: 0 | EI24: 0 | EJ24: 100 | EK24: 100 | EL24: 100 | EM24: 100 | EN24: 67 | EO24: 100 | EP24: 67 | EQ24: 0 | ER24: 67 | ES24: 100 | ET24: 100 | EU24: 100 | EV24: 100 | EW24: 100 | EX24: 100 | EY24: 33 | EZ24: 0 | FA24: 0 | FB24: 0 | FC24: 0 | FD24: 0 | FE24: 0 | FF24: 0 | FG24: 0 | FH24: 0 | FI24: 100 | FJ24: 100 | FK24: 100 | FL24: 100 | FM24: 100 | FN24: 67 | FO24: 33 | FP24: 0 | FQ24: 0 | FR24: 33 | FS24: 33 | FT24: 67 | FU24: 100 | FV24: 100 | FW24: 0 | FX24: 0 | FY24: 0 | FZ24: 0 | GA24: 0 | GB24: 67 | GC24: 67 | GD24: 67 | GE24: 100 | GF24: 0 | GG24: 100 | GH24: 100 | GI24: 67 | GJ24: 100 | GK24: 100 | GL24: 33 | GM24: 0 | GN24: 0 | GO24: 0 | GP24: 0 | GQ24: 0 | GR24: 100 | GS24: 100 | GT24: 100 | GU24: 100 | GV24: 33 | GW24: 33 | GX24: 0 | GY24: 0 | GZ24: 0 | HA24: 0 | HB24: 0 | HC24: 0 | HD24: 0 | HE24: 0 | HF24: 0 | HG24: 0 | HH24: 0 | HI24: 33 | HJ24: 33 | HK24: 0 | HL24: 0 | HM24: 100 | HN24: 100 | HO24: 0 | HP24: 100 | HQ24: 100 | HR24: 100 | HS24: 33 | HT24: 0 | HU24: 67 | HV24: 0 | HW24: 0 | HX24: 1 | HY24: 1 | HZ24: 1 | IA24: 1 | IB24: 1 | IC24: 1 | ID24: 1 | IE24: 1 | IF24: 1
A25: Argentina | B25: ARG | C25: 2019 | D25: Latin America & Caribbean | E25: South America | F25: 57.788991 | G25: 58 | H25: Limited (41-60) | I25: Limited (41-60) | J25: Insufficient (0-60) | K25: Middle Quintile | L25: 53.666667 | M25: 54 | N25: Limited (41-60) | O25: 41.666667 | P25: 42 | Q25: Limited (41-60) | R25: 77.666667 | S25: 78 | T25: Adequate (61-100) | U25: 50 | V25: 50 | W25: Limited (41-60) | X25: 14.777778 | Y25: 15 | Z25: Few or no opportunities (0-40) | AA25: PW | AB25: PW | AC25: PW | AD25: PW | AE25: NP | AF25: PW | AG25: PL | AH25: PW | AI25: 1 | AJ25: 1 | AK25: 1 | AL25: 1 | AM25: 1 | AN25: 0 | AO25: 1 | AP25: 0 | AQ25: 27.666667 | AR25: 28 | AS25: Minimal (21-40) | AT25: 66.055556 | AU25: 66 | AV25: Substantial (61-80 | AW25: 94.5 | AX25: 95 | AY25: Extensive (81-100) | AZ25: 75 | BA25: 75 | BB25: Substantial (61-80 | BC25: 74 | BD25: 74 | BE25: Substantial (61-80 | BF25: 0 | BG25: 0 | BH25: Scant or None (0-20) | BI25: 66.642857 | BJ25: 67 | BK25: Substantial (61-80 | BL25: 14.285714 | BM25: 14 | BN25: Scant or None (0-20) | BO25: a | BP25: a | BQ25: a | BR25: c | BS25: d | BT25: b | BU25: d | BV25: e | BW25: e | BX25: e | BY25: e | BZ25: d | CA25: e | CB25: a | CD25: 100 | CE25: 100 | CF25: 0 | CG25: 100 | CH25: 100 | CI25: 100 | CJ25: 0 | CK25: 0 | CL25: 100 | CM25: 100 | CN25: 0 | CO25: 0 | CP25: 100 | CQ25: 33 | CR25: 33 | CS25: 0 | CT25: 67 | CU25: 0 | CV25: 100 | CW25: 100 | CX25: 100 | CY25: 100 | CZ25: 100 | DA25: 100 | DB25: 100 | DC25: 100 | DD25: 100 | DE25: 100 | DF25: 100 | DG25: 100 | DH25: 33 | DI25: 100 | DJ25: 100 | DK25: 100 | DL25: 67 | DM25: 67 | DN25: 100 | DO25: 67 | DP25: 0 | DQ25: 0 | DR25: 0 | DS25: 33 | DT25: 0 | DU25: 67 | DV25: 100 | DW25: 33 | DX25: 33 | DY25: 100 | DZ25: 0 | EA25: 67 | EB25: 67 | EC25: 100 | ED25: 100 | EE25: 33 | EF25: 33 | EG25: 0 | EH25: 0 | EI25: 0 | EJ25: 100 | EK25: 100 | EL25: 100 | EM25: 100 | EN25: 67 | EO25: 100 | EP25: 100 | EQ25: 33 | ER25: 67 | ES25: 100 | ET25: 100 | EU25: 100 | EV25: 100 | EW25: 100 | EX25: 100 | EY25: 33 | EZ25: 0 | FA25: 0 | FB25: 0 | FC25: 0 | FD25: 0 | FE25: 0 | FF25: 0 | FG25: 0 | FH25: 0 | FI25: 100 | FJ25: 100 | FK25: 100 | FL25: 100 | FM25: 100 | FN25: 100 | FO25: 33 | FP25: 0 | FQ25: 0 | FR25: 33 | FS25: 33 | FT25: 67 | FU25: 100 | FV25: 100 | FW25: 0 | FX25: 0 | FY25: 0 | FZ25: 0 | GA25: 0 | GB25: 67 | GC25: 33 | GD25: 67 | GE25: 33 | GF25: 0 | GG25: 100 | GH25: 100 | GI25: 100 | GJ25: 100 | GK25: 100 | GL25: 0 | GM25: 0 | GN25: 0 | GO25: 0 | GP25: 0 | GQ25: 0 | GR25: 100 | GS25: 100 | GT25: 100 | GU25: 100 | GV25: 33 | GW25: 33 | GX25: 0 | GY25: 0 | GZ25: 0 | HA25: 0 | HB25: 0 | HC25: 0 | HD25: 0 | HE25: 0 | HF25: 0 | HG25: 0 | HH25: 0 | HI25: 33 | HJ25: 33 | HK25: 0 | HL25: 0 | HM25: 100 | HN25: 100 | HO25: 0 | HP25: 100 | HQ25: 100 | HR25: 100 | HS25: 33 | HT25: 0 | HU25: 67 | HV25: 0 | HW25: 0 | HX25: 1 | HY25: 1 | HZ25: 1 | IA25: 1 | IB25: 1 | IC25: 1 | ID25: 1 | IE25: 1 | IF25: 1
A26: Argentina | B26: ARG | C26: 2017 | D26: Latin America & Caribbean | E26: South America | F26: 49.825688 | G26: 50 | H26: Limited (41-60) | I26: Limited (41-60) | J26: Insufficient (0-60) | K26: Middle Quintile | L26: 55.5 | M26: 56 | N26: Limited (41-60) | O26: 44.416667 | P26: 44 | Q26: Limited (41-60) | R26: 77.666667 | S26: 78 | T26: Adequate (61-100) | U26: 0 | V26: 0 | W26: Weak (0-40) | X26: 12.944444 | Y26: 13 | Z26: Few or No (0-40) | AA26: PW | AB26: PW | AC26: PW | AD26: PW | AE26: NP | AF26: PW | AG26: PW | AH26: NP | AI26: 1 | AJ26: 1 | AK26: 1 | AL26: 0 | AM26: 1 | AN26: 0 | AO26: 1 | AP26: 1 | AQ26: 27.666667 | AR26: 28 | AS26: Minimal (21-40) | AT26: 49.37037 | AU26: 49 | AV26: Limited (41-60) | AW26: 77.833333 | AX26: 78 | AY26: Substantial (61-80 | AZ26: 8.25 | BA26: 8 | BB26: Scant or None (0-20) | BC26: 85.111111 | BD26: 85 | BE26: Extensive (81-100) | BF26: 0 | BG26: 0 | BH26: Scant or None (0-20) | BI26: 73.857143 | BJ26: 74 | BK26: Substantial (61-80 | BL26: 42.714286 | BM26: 43 | BN26: Limited (41-60) | BO26: a | BP26: a | BQ26: b | BR26: c | BS26: d | BT26: b | BU26: c | CD26: 100 | CE26: 100 | CF26: 0 | CG26: 100 | CH26: 100 | CI26: 100 | CJ26: 0 | CK26: 0 | CL26: 100 | CM26: 100 | CN26: 0 | CO26: 0 | CP26: 100 | CQ26: 33 | CR26: 33 | CS26: 0 | CT26: 67 | CU26: 0 | CV26: 100 | CW26: 0 | CX26: 100 | CY26: 0 | CZ26: 0 | DA26: 0 | DB26: 100 | DC26: 100 | DD26: 100 | DE26: 0 | DF26: 0 | DG26: 0 | DH26: 33 | DI26: 0 | DJ26: 67 | DK26: 100 | DL26: 67 | DM26: 67 | DN26: 100 | DO26: 33 | DP26: 33 | DQ26: 33 | DR26: 0 | DS26: 33 | DT26: 0 | DU26: 0 | DV26: 100 | DW26: 67 | DX26: 33 | DY26: 0 | DZ26: 67 | EA26: 67 | EB26: 33 | EC26: 100 | ED26: 100 | EE26: 33 | EF26: 33 | EG26: 0 | EH26: 0 | EI26: 0 | EJ26: 100 | EK26: 100 | EL26: 100 | EM26: 0 | EN26: 100 | EO26: 0 | EP26: 0 | EQ26: 0 | ER26: 33 | ES26: 100 | ET26: 100 | EU26: 100 | EV26: 100 | EW26: 100 | EX26: 100 | EY26: 33 | EZ26: 100 | FA26: 0 | FB26: 0 | FC26: 0 | FD26: 0 | FE26: 0 | FF26: 0 | FG26: 0 | FH26: 0 | FI26: 100 | FJ26: 100 | FK26: 100 | FL26: 100 | FM26: 100 | FN26: 100 | FO26: 67 | FP26: 0 | FQ26: 0 | FR26: 33 | FS26: 100 | FT26: 67 | FU26: 100 | FV26: 100 | FW26: 33 | FX26: 33 | FY26: 100 | FZ26: 0 | GA26: 0 | GB26: 0 | GC26: 0 | GD26: 0 | GE26: 0 | GF26: 0 | GG26: 100 | GH26: 100 | GI26: 100 | GJ26: 100 | GK26: 100 | GL26: 0 | GM26: 0 | GN26: 0 | GO26: 33 | GP26: 0 | GQ26: 0 | GR26: 100 | GS26: 100 | GT26: 100 | GU26: 100 | GV26: 33 | GW26: 33 | GX26: 0 | GY26: 0 | GZ26: 0 | HA26: 0 | HB26: 0 | HC26: 0 | HD26: 0 | HE26: 0 | HF26: 0 | HG26: 0 | HH26: 0 | HI26: 33 | HJ26: 0 | HK26: 0 | HL26: 0 | HM26: 100 | HN26: 100 | HO26: 0 | HP26: 100 | HQ26: 100 | HR26: 67 | HS26: 33 | HT26: 0 | HU26: 67 | HV26: 33 | HW26: 0 | HX26: 1 | HY26: 1 | HZ26: 1 | IA26: 1 | IB26: 1 | IC26: 1 | ID26: 1 | IE26: 1 | IF26: 1
A27: Argentina | B27: ARG | C27: 2015 | D27: Latin America & Caribbean | E27: South America | F27: 59.2407 | G27: 59 | H27: Limited (41-60) | I27: Limited (41-60) | J27: Insufficient (0-60) | K27: Middle Quintile | O27: 30 | P27: 30 | Q27: Weak | R27: 91.75 | S27: 92 | T27: Strong | X27: 27.125 | Y27: 27 | Z27: Minimal | AA27: PW | AB27: PW | AC27: PW | AD27: PW | AE27: NP | AF27: PW | AG27: PW | AH27: NP | AI27: 1 | AJ27: 1 | AK27: 1 | AL27: 0 | AM27: 1 | AN27: 0 | AO27: 1 | AP27: 1 | AQ27: 27.6667 | AR27: 28 | AS27: Minimal (21-40) | AT27: 64.113197 | AU27: 64 | AV27: Substantial (61-80 | AW27: 94.5 | AX27: 95 | AY27: Extensive (81-100) | AZ27: 0 | BA27: 0 | BB27: Scant or None (0-20) | BC27: 81.444397 | BD27: 81 | BE27: Extensive (81-100) | BF27: 0 | BG27: 0 | BH27: Scant or None (0-20) | BI27: 85.785698 | BJ27: 86 | BK27: Extensive (81-100) | BL27: 47.5714 | BM27: 48 | BN27: Limited (41-60) | CD27: 100 | CE27: 100 | CF27: 0 | CG27: 100 | CH27: 100 | CI27: 100 | CJ27: 0 | CK27: 0 | CL27: 100 | CM27: 100 | CN27: 0 | CO27: 0 | CP27: 67 | CQ27: 33 | CR27: 67 | CS27: 0 | CT27: 33 | CU27: 33 | CV27: 100 | CW27: 100 | CX27: 100 | CY27: 100 | CZ27: 100 | DA27: 100 | DB27: 100 | DC27: 100 | DD27: 100 | DE27: 100 | DF27: 100 | DG27: 100 | DH27: 33 | DI27: 100 | DJ27: 67 | DK27: 100 | DL27: 33 | DM27: 67 | DN27: 100 | DO27: 33 | DP27: 33 | DQ27: 33 | DR27: 0 | DS27: 33 | DT27: 0 | DV27: 100 | DW27: 0 | DX27: 33 | DY27: 0 | DZ27: 67 | EA27: 100 | EB27: 33 | EC27: 100 | ED27: 100 | EE27: 33 | EF27: 33 | EG27: 0 | EH27: 33 | EI27: 0 | EJ27: 100 | EK27: 100 | EL27: 100 | EM27: 100 | EN27: 67 | EO27: 0 | EP27: 0 | EQ27: 0 | ER27: 0 | ES27: 100 | ET27: 100 | EU27: 100 | EV27: 100 | EW27: 100 | EX27: 100 | EY27: 33 | EZ27: 0 | FA27: 0 | FB27: 0 | FC27: 0 | FD27: 0 | FE27: 0 | FF27: 0 | FG27: 0 | FH27: 0 | FI27: 100 | FJ27: 100 | FK27: 100 | FL27: 100 | FM27: 100 | FN27: 100 | FO27: 100 | FP27: 0 | FQ27: 67 | FR27: 67 | FS27: 100 | FT27: 67 | FU27: 100 | FV27: 100 | FW27: 67 | FX27: 33 | FY27: 100 | FZ27: 0 | GA27: 0 | GB27: 33 | GC27: 0 | GD27: 0 | GE27: 100 | GF27: 100 | GG27: 67 | GH27: 0 | GI27: 0 | GJ27: 0 | GK27: 0 | GM27: 0 | GN27: 100 | GO27: 67 | GP27: 100 | GQ27: 100 | GR27: 100 | GS27: 0 | GT27: 0 | GU27: 0 | GV27: 0 | GW27: 0 | GX27: 0 | GY27: 67 | GZ27: 0 | HA27: 0 | HB27: 67 | HC27: 67 | HD27: 0 | HE27: 100 | HF27: 33 | HP27: 67 | HQ27: 100 | HR27: 100 | HS27: 100 | HT27: 0 | HU27: 100 | HV27: 33 | HW27: 0 | HX27: 1 | HY27: 1 | HZ27: 1 | IA27: 1 | IB27: 1 | IC27: 1 | ID27: 1 | IE27: 1 | IF27: 1
A28: Argentina | B28: ARG | C28: 2012 | D28: Latin America & Caribbean | E28: South America | F28: 50.021301 | G28: 50 | H28: Limited (41-60) | I28: Limited (41-60) | J28: Insufficient (0-60) | K28: Middle Quintile | O28: 29.9 | P28: 30 | Q28: Weak | R28: 75 | S28: 75 | T28: Strong | X28: 30.5 | Y28: 31 | Z28: Weak | AA28: IU | AB28: PW | AC28: PW | AD28: PW | AE28: NP | AF28: PW | AG28: PW | AH28: NP | AI28: 0 | AJ28: 1 | AK28: 1 | AL28: 0 | AM28: 1 | AN28: 0 | AO28: 1 | AP28: 1 | AQ28: 0 | AR28: 0 | AS28: Scant or None (0-20) | AT28: 54.386002 | AU28: 54 | AV28: Limited (41-60) | AW28: 100 | AX28: 100 | AY28: Extensive (81-100) | AZ28: 0 | BA28: 0 | BB28: Scant or None (0-20) | BC28: 95.875 | BD28: 96 | BE28: Extensive (81-100) | BF28: 0 | BG28: 0 | BH28: Scant or None (0-20) | BI28: 50.099998 | BJ28: 50 | BK28: Limited (41-60) | BL28: 33.4286 | BM28: 33 | BN28: Minimal (21-40) | CD28: 100 | CI28: 100 | CL28: 100 | CM28: 100 | CQ28: 67 | CR28: 100 | CS28: 0 | CT28: 67 | CU28: 0 | CW28: 0 | CX28: 0 | DA28: 0 | DD28: 0 | DG28: 0 | DH28: 0 | DI28: 0 | DJ28: 67 | DL28: 67 | DN28: 100 | DO28: 33 | DP28: 33 | DQ28: 0 | DR28: 0 | DS28: 33 | DT28: 0 | DV28: 100 | DW28: 0 | DX28: 100 | DY28: 0 | EA28: 100 | EB28: 0 | EC28: 100 | ED28: 100 | EE28: 0 | EO28: 0 | EP28: 0 | EQ28: 0 | ER28: 0 | EU28: 100 | EW28: 100 | EX28: 100 | EZ28: 100 | FA28: 0 | FB28: 0 | FE28: 0 | FI28: 67 | FL28: 67 | FP28: 0 | FQ28: 67 | FR28: 0 | FS28: 33 | FT28: 67 | FW28: 67 | FX28: 100 | FY28: 0 | FZ28: 0 | GA28: 0 | GB28: 0 | GC28: 33 | GD28: 33 | GE28: 100 | GG28: 67 | GH28: 0 | GI28: 0 | GJ28: 33 | GK28: 0 | GM28: 33 | GN28: 100 | GP28: 100 | GQ28: 100 | GR28: 33 | GS28: 0 | GT28: 0 | GV28: 0 | GW28: 0 | GX28: 0 | GY28: 33 | GZ28: 33 | HA28: 33 | HB28: 67 | HE28: 100 | HF28: 33 | HP28: 0 | HQ28: 100 | HS28: 100 | HU28: 100 | HV28: 0 | HW28: 0 | HX28: 1 | HY28: 1 | HZ28: 1 | IA28: 1 | IB28: 1 | IC28: 1 | ID28: 1 | IE28: 1 | IF28: 1
A29: Argentina | B29: ARG | C29: 2010 | D29: Latin America & Caribbean | E29: South America | F29: 56.384602 | G29: 56 | H29: Limited (41-60) | I29: Limited (41-60) | J29: Insufficient (0-60) | K29: Middle Quintile | O29: 41.666698 | P29: 42 | Q29: Moderate | R29: 46.700001 | S29: 47 | T29: Moderate | AA29: NP | AB29: PW | AC29: PW | AD29: PW | AE29: NP | AF29: PW | AG29: IU | AH29: NP | AI29: 0 | AJ29: 1 | AK29: 1 | AL29: 0 | AM29: 1 | AN29: 0 | AO29: 1 | AP29: 0 | AQ29: 0 | AR29: 0 | AS29: Scant or None (0-20) | AT29: 60.444401 | AU29: 60 | AV29: Limited (41-60) | AW29: 100 | AX29: 100 | AY29: Extensive (81-100) | AZ29: 0 | BA29: 0 | BB29: Scant or None (0-20) | BC29: 95.875 | BD29: 96 | BE29: Extensive (81-100) | BF29: 0 | BG29: 0 | BH29: Scant or None (0-20) | BI29: 53.299999 | BJ29: 53 | BK29: Limited (41-60) | BL29: 23.8571 | BM29: 24 | BN29: Minimal (21-40) | CD29: 100 | CI29: 100 | CL29: 100 | CM29: 100 | CQ29: 67 | CR29: 100 | CS29: 0 | CT29: 33 | CU29: 0 | CW29: 33 | CX29: 100 | DA29: 100 | DD29: 100 | DG29: 100 | DH29: 67 | DI29: 100 | DJ29: 67 | DL29: 33 | DN29: 33 | DO29: 0 | DP29: 33 | DQ29: 0 | DR29: 0 | DS29: 33 | DT29: 0 | DV29: 100 | DW29: 0 | DX29: 33 | DY29: 0 | EA29: 33 | EB29: 67 | EC29: 33 | ED29: 100 | EE29: 0 | EO29: 0 | EU29: 100 | EW29: 100 | EX29: 100 | EZ29: 100 | FA29: 0 | FB29: 0 | FE29: 0 | FI29: 67 | FL29: 67 | FP29: 0 | FQ29: 67 | FR29: 33 | FS29: 33 | FT29: 33 | FW29: 0 | FX29: 100 | FY29: 0 | FZ29: 0 | GA29: 0 | GD29: 33 | GE29: 100 | GG29: 67 | GH29: 0 | GK29: 0 | GL29: 100 | GM29: 100 | GN29: 67 | GP29: 100 | GQ29: 100 | GR29: 33 | GY29: 33 | GZ29: 67 | HA29: 0 | HB29: 0 | HP29: 0 | HQ29: 100 | HS29: 100 | HU29: 100 | HV29: 0 | HW29: 0 | HX29: 1 | HY29: 1 | HZ29: 1 | IA29: 1 | IB29: 1 | IC29: 1 | ID29: 1 | IE29: 1 | IF29: 1
A30: Argentina | B30: ARG | C30: 2008 | D30: Latin America & Caribbean | E30: South America | F30: 56.021999 | G30: 56 | H30: Limited (41-60) | I30: Limited (41-60) | J30: Insufficient (0-60) | K30: Middle Quintile | O30: 41.666698 | P30: 42 | Q30: Moderate | R30: 46.700001 | S30: 47 | T30: Moderate | AA30: NP | AB30: PW | AC30: PW | AD30: PW | AE30: NP | AF30: PW | AG30: IU | AH30: NP | AI30: 0 | AJ30: 1 | AK30: 1 | AL30: 0 | AM30: 1 | AN30: 0 | AO30: 1 | AP30: 0 | AQ30: 0 | AR30: 0 | AS30: Scant or None (0-20) | AT30: 61.055599 | AU30: 61 | AV30: Substantial (61-80 | AW30: 100 | AX30: 100 | AY30: Extensive (81-100) | AZ30: 0 | BA30: 0 | BB30: Scant or None (0-20) | BC30: 87.625 | BD30: 88 | BE30: Extensive (81-100) | BF30: 0 | BG30: 0 | BH30: Scant or None (0-20) | BI30: 53.299999 | BJ30: 53 | BK30: Limited (41-60) | BL30: 23.8571 | BM30: 24 | BN30: Minimal (21-40) | CD30: 100 | CI30: 100 | CL30: 100 | CM30: 100 | CQ30: 0 | CR30: 100 | CS30: 0 | CT30: 33 | CU30: 0 | CW30: 33 | CX30: 100 | DA30: 100 | DD30: 100 | DG30: 100 | DH30: 33 | DI30: 100 | DJ30: 33 | DL30: 67 | DN30: 33 | DO30: 0 | DP30: 33 | DQ30: 0 | DR30: 0 | DS30: 33 | DT30: 0 | DV30: 100 | DW30: 0 | DX30: 33 | DY30: 0 | EA30: 33 | EB30: 67 | EC30: 33 | ED30: 100 | EE30: 0 | EO30: 0 | EU30: 100 | EW30: 100 | EX30: 67 | EZ30: 100 | FA30: 0 | FB30: 0 | FE30: 0 | FI30: 67 | FL30: 67 | FP30: 0 | FQ30: 67 | FR30: 33 | FS30: 33 | FT30: 33 | FW30: 0 | FX30: 100 | FY30: 0 | FZ30: 0 | GA30: 0 | GD30: 33 | GE30: 100 | GG30: 67 | GH30: 0 | GK30: 0 | GL30: 100 | GM30: 100 | GN30: 67 | GP30: 100 | GQ30: 100 | GR30: 33 | GY30: 33 | GZ30: 67 | HA30: 0 | HB30: 0 | HP30: 0 | HQ30: 100 | HS30: 67 | HU30: 100 | HV30: 0 | HW30: 0 | HX30: 1 | HY30: 1 | HZ30: 1 | IA30: 1 | IB30: 1 | IC30: 1 | ID30: 1 | IE30: 1 | IF30: 1
A31: Argentina | B31: ARG | C31: 2006 | D31: Latin America & Caribbean | E31: South America | F31: 39.826099 | G31: 40 | H31: Minimal (21-40) | I31: Low (0-40) | J31: Insufficient (0-60) | K31: Middle Quintile | O31: 33.333302 | P31: 33 | Q31: Weak | R31: 33.375 | S31: 33 | T31: Weak | AA31: IU | AB31: PW | AC31: PW | AD31: PW | AE31: NP | AF31: PW | AG31: IU | AH31: NP | AI31: 0 | AJ31: 1 | AK31: 1 | AL31: 0 | AM31: 1 | AN31: 0 | AO31: 1 | AP31: 0 | AQ31: 0 | AR31: 0 | AS31: Scant or None (0-20) | AT31: 44.799999 | AU31: 45 | AV31: Limited (41-60) | AW31: 100 | AX31: 100 | AY31: Extensive (81-100) | AZ31: 0 | BA31: 0 | BB31: Scant or None (0-20) | BC31: 66.75 | BD31: 67 | BE31: Substantial (61-80 | BF31: 0 | BG31: 0 | BH31: Scant or None (0-20) | BI31: 26.5 | BJ31: 27 | BK31: Minimal (21-40) | BL31: 0 | BM31: 0 | BN31: Scant or None (0-20) | CD31: 100 | CI31: 100 | CL31: 100 | CM31: 100 | CQ31: 33 | CR31: 67 | CS31: 33 | CT31: 33 | CU31: 0 | CW31: 33 | CX31: 67 | DA31: 0 | DD31: 67 | DG31: 0 | DH31: 0 | DI31: 0 | DJ31: 67 | DL31: 33 | DN31: 33 | DO31: 0 | DP31: 33 | DQ31: 33 | DR31: 0 | DS31: 33 | DT31: 0 | DU31: 0 | DV31: 33 | DW31: 33 | DX31: 33 | DY31: 33 | EA31: 67 | EB31: 0 | EC31: 33 | ED31: 67 | EE31: 0 | EO31: 0 | EU31: 67 | EW31: 100 | EX31: 67 | EZ31: 33 | FA31: 0 | FB31: 0 | FE31: 0 | FI31: 33 | FL31: 33 | FP31: 0 | FQ31: 33 | FR31: 0 | FS31: 0 | FT31: 33 | FW31: 0 | FX31: 0 | FY31: 0 | FZ31: 0 | GA31: 0 | GD31: 33 | GE31: 100 | GG31: 67 | GH31: 0 | GK31: 0 | GL31: 0 | GM31: 0 | GN31: 67 | GP31: 100 | GQ31: 100 | GR31: 0 | GY31: 33 | GZ31: 67 | HA31: 0 | HB31: 0 | HP31: 0 | HQ31: 100 | HS31: 67 | HU31: 100 | HV31: 0 | HW31: 0 | HX31: 1 | HY31: 1 | HZ31: 1 | IA31: 1 | IB31: 1 | IC31: 1 | ID31: 1 | IE31: 1 | IF31: 1
A32: Bolivia | B32: BOL | C32: 2025 | D32: Latin America & Caribbean | E32: South America | F32: 11.009434 | G32: 11 | H32: Scant or None (0-20) | I32: Low (0-40) | J32: Insufficient (0-60) | K32: Bottom Quintile | L32: 38.888889 | M32: 39 | N32: Weak (0-40) | O32: 33.333333 | P32: 33 | Q32: Weak (0-40) | R32: 50 | S32: 50 | T32: Limited (41-60) | U32: 0 | V32: 0 | W32: Weak (0-40) | X32: 12.944444 | Y32: 13 | Z32: Few or no opportunities (0-40) | AA32: IU | AB32: IU | AC32: PW | AD32: IU | AE32: NP | AF32: PW | AG32: NP | AH32: PW | AI32: 0 | AJ32: 0 | AK32: 1 | AL32: 1 | AM32: 0 | AN32: 0 | AO32: 1 | AP32: 0 | AQ32: 0 | AR32: 0 | AS32: Scant or None (0-20) | AT32: 0 | AU32: 0 | AV32: Scant or None (0-20) | AW32: 83.5 | AX32: 84 | AY32: Extensive (81-100) | AZ32: 41.5 | BA32: 42 | BB32: Limited (41-60) | BC32: 0 | BD32: 0 | BE32: Scant or None (0-20) | BF32: 0 | BG32: 0 | BH32: Scant or None (0-20) | BI32: 30.769231 | BJ32: 31 | BK32: Minimal (21-40) | BL32: 16.666667 | BM32: 17 | BN32: Scant or None (0-20) | BO32: d | BP32: d | BQ32: b | BR32: d | BS32: d | BT32: c | BU32: d | BV32: c | BW32: c | BX32: e | BY32: c | BZ32: d | CA32: e | CB32: d | CC32: e | CD32: 0 | CE32: 0 | CF32: 0 | CG32: 0 | CH32: 0 | CI32: 0 | CJ32: 0 | CK32: 0 | CL32: 0 | CM32: 0 | CN32: 0 | CO32: 0 | CP32: 0 | CQ32: 0 | CR32: 0 | CS32: 0 | CT32: 0 | CU32: 0 | CV32: 0 | CW32: 0 | CX32: 0 | CY32: 0 | CZ32: 0 | DA32: 0 | DB32: 0 | DC32: 0 | DD32: 0 | DE32: 0 | DF32: 0 | DG32: 0 | DH32: 0 | DI32: 0 | DK32: 0 | DL32: 0 | DM32: 0 | DN32: 0 | DO32: 0 | DP32: 0 | DQ32: 0 | DR32: 0 | DS32: 0 | DT32: 0 | DU32: 0 | DV32: 0 | DW32: 0 | DX32: 0 | DY32: 0 | DZ32: 0 | EA32: 0 | EB32: 0 | EC32: 0 | ED32: 0 | EE32: 0 | EF32: 0 | EG32: 0 | EH32: 0 | EI32: 0 | EJ32: 67 | EK32: 100 | EL32: 100 | EM32: 100 | EN32: 67 | EO32: 100 | EP32: 33 | EQ32: 0 | ER32: 33 | ES32: 0 | ET32: 0 | EU32: 0 | EV32: 0 | EW32: 0 | EX32: 0 | EY32: 0 | EZ32: 0 | FA32: 0 | FB32: 0 | FC32: 0 | FD32: 0 | FE32: 0 | FF32: 0 | FG32: 0 | FH32: 0 | FI32: 0 | FJ32: 67 | FK32: 33 | FL32: 0 | FM32: 100 | FN32: 67 | FO32: 0 | FP32: 0 | FQ32: 0 | FR32: 0 | FS32: 0 | FU32: 100 | FV32: 100 | FW32: 0 | FY32: 0 | FZ32: 0 | GA32: 0 | GB32: 0 | GC32: 0 | GD32: 0 | GE32: 0 | GF32: 0 | GG32: 67 | GH32: 0 | GI32: 100 | GJ32: 33 | GK32: 67 | GL32: 0 | GM32: 33 | GN32: 0 | GO32: 100 | GP32: 0 | GQ32: 0 | GR32: 0 | GS32: 100 | GT32: 67 | GU32: 100 | GV32: 33 | GW32: 0 | GX32: 0 | GY32: 0 | GZ32: 0 | HA32: 33 | HB32: 0 | HC32: 67 | HD32: 0 | HE32: 0 | HF32: 0 | HG32: 0 | HH32: 0 | HI32: 0 | HJ32: 0 | HK32: 0 | HL32: 0 | HM32: 100 | HN32: 33 | HO32: 0 | HP32: 0 | HQ32: 0 | HR32: 67 | HS32: 0 | HT32: 0 | HU32: 33 | HV32: 0 | HW32: 0 | HX32: 0 | HY32: 1 | HZ32: 1 | IA32: 1 | IB32: 1 | IC32: 1 | ID32: 1 | IE32: 1 | IF32: 1
A33: Bolivia | B33: BOL | C33: 2023 | D33: Latin America & Caribbean | E33: South America | F33: 10.715596 | G33: 11 | H33: Scant or None (0-20) | I33: Low (0-40) | J33: Insufficient (0-60) | K33: Bottom Quintile | L33: 40.722222 | M33: 41 | N33: Limited (41-60) | O33: 36.083333 | P33: 36 | Q33: Weak (0-40) | R33: 50 | S33: 50 | T33: Limited (41-60) | U33: 0 | V33: 0 | W33: Weak (0-40) | X33: 14.777778 | Y33: 15 | Z33: Few or no opportunities (0-40) | AA33: IU | AB33: IU | AC33: PW | AD33: IU | AE33: NP | AF33: PW | AG33: NP | AH33: PL | AI33: 0 | AJ33: 0 | AK33: 1 | AL33: 0 | AM33: 0 | AN33: 0 | AO33: 1 | AP33: 0 | AQ33: 0 | AR33: 0 | AS33: Scant or None (0-20) | AT33: 1.8518519 | AU33: 2 | AV33: Scant or None (0-20) | AW33: 83.5 | AX33: 84 | AY33: Extensive (81-100) | AZ33: 0 | BA33: 0 | BB33: Scant or None (0-20) | BC33: 0 | BD33: 0 | BE33: Scant or None (0-20) | BF33: 0 | BG33: 0 | BH33: Scant or None (0-20) | BI33: 33.357143 | BJ33: 33 | BK33: Minimal (21-40) | BL33: 14.285714 | BM33: 14 | BN33: Scant or None (0-20) | BO33: d | BP33: d | BQ33: b | BR33: d | BS33: d | BT33: b | BU33: d | BV33: c | BW33: c | BX33: e | BY33: c | BZ33: d | CA33: e | CB33: d | CD33: 0 | CE33: 0 | CF33: 0 | CG33: 0 | CH33: 0 | CI33: 0 | CJ33: 0 | CK33: 0 | CL33: 0 | CM33: 0 | CN33: 0 | CO33: 0 | CP33: 0 | CQ33: 0 | CR33: 0 | CS33: 0 | CT33: 0 | CU33: 0 | CV33: 0 | CW33: 0 | CX33: 0 | CY33: 0 | CZ33: 0 | DA33: 0 | DB33: 0 | DC33: 0 | DD33: 0 | DE33: 0 | DF33: 0 | DG33: 0 | DH33: 0 | DI33: 0 | DJ33: 0 | DK33: 0 | DL33: 0 | DM33: 0 | DN33: 0 | DO33: 0 | DP33: 0 | DQ33: 0 | DR33: 0 | DS33: 0 | DT33: 0 | DU33: 0 | DV33: 0 | DW33: 0 | DX33: 0 | DY33: 0 | DZ33: 0 | EA33: 0 | EB33: 0 | EC33: 0 | ED33: 100 | EE33: 0 | EF33: 0 | EG33: 0 | EH33: 0 | EI33: 0 | EJ33: 67 | EK33: 100 | EL33: 100 | EM33: 100 | EN33: 67 | EO33: 0 | EP33: 0 | EQ33: 0 | ER33: 0 | ES33: 0 | ET33: 0 | EU33: 0 | EV33: 0 | EW33: 0 | EX33: 0 | EY33: 0 | EZ33: 0 | FA33: 0 | FB33: 0 | FC33: 0 | FD33: 0 | FE33: 0 | FF33: 0 | FG33: 0 | FH33: 0 | FI33: 0 | FJ33: 67 | FK33: 33 | FL33: 0 | FM33: 100 | FN33: 67 | FO33: 0 | FP33: 33 | FQ33: 0 | FR33: 0 | FS33: 0 | FT33: 0 | FU33: 100 | FV33: 100 | FW33: 0 | FX33: 0 | FY33: 0 | FZ33: 0 | GA33: 0 | GB33: 0 | GC33: 0 | GD33: 0 | GE33: 0 | GF33: 0 | GG33: 67 | GH33: 67 | GI33: 100 | GJ33: 33 | GK33: 33 | GL33: 0 | GM33: 33 | GN33: 0 | GO33: 100 | GP33: 0 | GQ33: 0 | GR33: 0 | GS33: 100 | GT33: 67 | GU33: 100 | GV33: 33 | GW33: 0 | GX33: 0 | GY33: 0 | GZ33: 0 | HA33: 33 | HB33: 0 | HC33: 67 | HD33: 0 | HE33: 0 | HF33: 33 | HG33: 0 | HH33: 0 | HI33: 0 | HJ33: 0 | HK33: 0 | HL33: 0 | HM33: 100 | HN33: 33 | HO33: 0 | HP33: 0 | HQ33: 0 | HR33: 67 | HS33: 0 | HT33: 0 | HU33: 67 | HV33: 0 | HW33: 0 | HX33: 0 | HY33: 1 | HZ33: 1 | IA33: 1 | IB33: 1 | IC33: 1 | ID33: 1 | IE33: 1 | IF33: 1
A34: Bolivia | B34: BOL | C34: 2021 | D34: Latin America & Caribbean | E34: South America | F34: 20.462264 | G34: 20 | H34: Scant or None (0-20) | I34: Low (0-40) | J34: Insufficient (0-60) | K34: 2nd Quintile | L34: 48.166667 | M34: 48 | N34: Limited (41-60) | O34: 38.916667 | P34: 39 | Q34: Weak (0-40) | R34: 66.666667 | S34: 67 | T34: Adequate (61-100) | U34: 0 | V34: 0 | W34: Weak (0-40) | X34: 20.333333 | Y34: 20 | Z34: Few or no opportunities (0-40) | AA34: IU | AB34: PW | AC34: PW | AD34: IU | AE34: NP | AF34: PW | AG34: NP | AH34: PL | AI34: 0 | AJ34: 1 | AK34: 1 | AL34: 0 | AM34: 0 | AN34: 0 | AO34: 1 | AP34: 0 | AQ34: 0 | AR34: 0 | AS34: Scant or None (0-20) | AT34: 21.173077 | AU34: 21 | AV34: Minimal (21-40) | AW34: 89 | AX34: 89 | AY34: Extensive (81-100) | AZ34: 0 | BA34: 0 | BB34: Scant or None (0-20) | BC34: 0 | BD34: 0 | BE34: Scant or None (0-20) | BF34: 0 | BG34: 0 | BH34: Scant or None (0-20) | BI34: 33.384615 | BJ34: 33 | BK34: Minimal (21-40) | BL34: 14.285714 | BM34: 14 | BN34: Scant or None (0-20) | BO34: d | BP34: c | BQ34: a | BR34: d | BS34: d | BT34: b | BU34: d | BV34: c | BW34: e | BX34: e | BY34: c | BZ34: d | CA34: e | CB34: d | CD34: 100 | CE34: 0 | CF34: 0 | CG34: 100 | CH34: 100 | CI34: 0 | CJ34: 0 | CK34: 0 | CL34: 0 | CM34: 100 | CN34: 0 | CO34: 0 | CP34: 67 | CQ34: 0 | CR34: 67 | CS34: 0 | CT34: 0 | CU34: 0 | CV34: 0 | CW34: 0 | CX34: 0 | CY34: 0 | CZ34: 0 | DA34: 0 | DB34: 0 | DC34: 0 | DD34: 0 | DE34: 0 | DF34: 0 | DG34: 0 | DH34: 0 | DI34: 0 | DL34: 67 | DM34: 0 | DN34: 67 | DO34: 0 | DP34: 0 | DQ34: 0 | DR34: 67 | DS34: 33 | DT34: 0 | DU34: 67 | DV34: 33 | DW34: 67 | DX34: 0 | DY34: 0 | DZ34: 0 | EA34: 0 | EB34: 0 | EC34: 33 | ED34: 100 | EE34: 0 | EF34: 0 | EG34: 0 | EH34: 0 | EI34: 0 | EJ34: 67 | EK34: 100 | EL34: 100 | EM34: 100 | EN34: 67 | EO34: 0 | EP34: 0 | EQ34: 0 | ER34: 0 | ES34: 0 | ET34: 0 | EU34: 0 | EV34: 0 | EW34: 0 | EX34: 0 | EY34: 0 | EZ34: 0 | FA34: 0 | FB34: 0 | FC34: 0 | FD34: 0 | FE34: 0 | FF34: 0 | FG34: 0 | FH34: 0 | FI34: 0 | FJ34: 67 | FK34: 33 | FL34: 0 | FM34: 100 | FN34: 67 | FO34: 0 | FP34: 0 | FQ34: 0 | FR34: 0 | FS34: 0 | FU34: 100 | FV34: 100 | FW34: 0 | FX34: 0 | FY34: 0 | FZ34: 0 | GA34: 0 | GB34: 0 | GC34: 0 | GD34: 0 | GE34: 0 | GF34: 0 | GG34: 67 | GH34: 67 | GI34: 100 | GJ34: 33 | GK34: 67 | GL34: 0 | GM34: 33 | GN34: 0 | GO34: 100 | GP34: 0 | GQ34: 0 | GR34: 100 | GS34: 100 | GT34: 67 | GU34: 100 | GV34: 33 | GW34: 0 | GX34: 0 | GY34: 0 | GZ34: 0 | HA34: 33 | HB34: 0 | HC34: 67 | HD34: 0 | HE34: 0 | HF34: 33 | HG34: 0 | HH34: 0 | HI34: 0 | HJ34: 0 | HK34: 0 | HL34: 0 | HM34: 100 | HN34: 33 | HO34: 100 | HP34: 0 | HQ34: 33 | HR34: 100 | HS34: 0 | HT34: 0 | HU34: 67 | HV34: 0 | HW34: 0 | HX34: 0 | HY34: 1 | HZ34: 1 | IA34: 1 | IB34: 1 | IC34: 1 | ID34: 1 | IE34: 1 | IF34: 1
A35: Bolivia | B35: BOL | C35: 2019 | D35: Latin America & Caribbean | E35: South America | F35: 12.342593 | G35: 12 | H35: Scant or None (0-20) | I35: Low (0-40) | J35: Insufficient (0-60) | K35: Bottom Quintile | L35: 44.388889 | M35: 44 | N35: Limited (41-60) | O35: 33.25 | P35: 33 | Q35: Weak (0-40) | R35: 66.666667 | S35: 67 | T35: Adequate (61-100) | U35: 0 | V35: 0 | W35: Weak (0-40) | X35: 14.777778 | Y35: 15 | Z35: Few or no opportunities (0-40) | AA35: NP | AB35: IU | AC35: PW | AD35: IU | AE35: NP | AF35: PW | AG35: NP | AH35: PL | AI35: 0 | AJ35: 0 | AK35: 1 | AL35: 0 | AM35: 0 | AN35: 0 | AO35: 1 | AP35: 0 | AQ35: 0 | AR35: 0 | AS35: Scant or None (0-20) | AT35: 0 | AU35: 0 | AV35: Scant or None (0-20) | AW35: 89 | AX35: 89 | AY35: Extensive (81-100) | AZ35: 0 | BA35: 0 | BB35: Scant or None (0-20) | BC35: 0 | BD35: 0 | BE35: Scant or None (0-20) | BF35: 0 | BG35: 0 | BH35: Scant or None (0-20) | BI35: 53.769231 | BJ35: 54 | BK35: Limited (41-60) | BL35: 14.285714 | BM35: 14 | BN35: Scant or None (0-20) | BO35: d | BP35: d | BQ35: a | BR35: d | BS35: d | BT35: c | BU35: d | BV35: d | BW35: c | BX35: e | BY35: c | BZ35: d | CA35: e | CB35: d | CD35: 0 | CE35: 0 | CF35: 0 | CG35: 0 | CH35: 0 | CI35: 0 | CJ35: 0 | CK35: 0 | CL35: 0 | CM35: 0 | CN35: 0 | CO35: 0 | CP35: 0 | CQ35: 0 | CR35: 0 | CS35: 0 | CT35: 0 | CU35: 0 | CV35: 0 | CW35: 0 | CX35: 0 | CY35: 0 | CZ35: 0 | DA35: 0 | DB35: 0 | DC35: 0 | DD35: 0 | DE35: 0 | DF35: 0 | DG35: 0 | DH35: 0 | DI35: 0 | DJ35: 0 | DK35: 0 | DL35: 0 | DM35: 0 | DN35: 0 | DO35: 0 | DP35: 0 | DQ35: 0 | DR35: 0 | DS35: 0 | DT35: 0 | DU35: 0 | DV35: 0 | DW35: 0 | DX35: 0 | DY35: 0 | DZ35: 0 | EA35: 0 | EB35: 0 | EC35: 0 | ED35: 0 | EE35: 0 | EF35: 0 | EG35: 0 | EH35: 0 | EI35: 0 | EJ35: 67 | EK35: 100 | EL35: 100 | EM35: 100 | EN35: 67 | EO35: 0 | EP35: 0 | EQ35: 0 | ER35: 0 | ES35: 0 | ET35: 0 | EU35: 0 | EV35: 0 | EW35: 0 | EX35: 0 | EY35: 0 | EZ35: 0 | FA35: 0 | FB35: 0 | FC35: 0 | FD35: 0 | FE35: 0 | FF35: 0 | FG35: 0 | FH35: 0 | FI35: 100 | FJ35: 67 | FK35: 33 | FL35: 100 | FM35: 100 | FN35: 100 | FO35: 33 | FP35: 33 | FQ35: 0 | FR35: 0 | FS35: 0 | FU35: 100 | FV35: 100 | FW35: 0 | FX35: 0 | FY35: 0 | FZ35: 0 | GA35: 0 | GB35: 0 | GC35: 0 | GD35: 0 | GE35: 0 | GF35: 0 | GG35: 33 | GH35: 67 | GI35: 100 | GJ35: 33 | GK35: 33 | GL35: 0 | GM35: 33 | GN35: 0 | GO35: 100 | GP35: 0 | GQ35: 0 | GR35: 100 | GS35: 100 | GT35: 67 | GU35: 100 | GV35: 33 | GW35: 0 | GX35: 0 | GY35: 0 | GZ35: 0 | HA35: 33 | HB35: 0 | HC35: 67 | HD35: 0 | HE35: 0 | HF35: 33 | HG35: 0 | HH35: 0 | HI35: 0 | HJ35: 0 | HK35: 0 | HL35: 0 | HM35: 100 | HN35: 33 | HO35: 0 | HP35: 0 | HQ35: 0 | HR35: 100 | HS35: 0 | HT35: 0 | HU35: 33 | HV35: 0 | HW35: 0 | HX35: 0 | HY35: 1 | HZ35: 1 | IA35: 1 | IB35: 1 | IC35: 1 | ID35: 1 | IE35: 1 | IF35: 1
A36: Bolivia | B36: BOL | C36: 2017 | D36: Latin America & Caribbean | E36: South America | F36: 10.194444 | G36: 10 | H36: Scant or None (0-20) | I36: Low (0-40) | J36: Insufficient (0-60) | K36: Bottom Quintile | L36: 48.111111 | M36: 48 | N36: Limited (41-60) | O36: 41.666667 | P36: 42 | Q36: Limited (41-60) | R36: 61 | S36: 61 | T36: Adequate (61-100) | U36: 0 | V36: 0 | W36: Weak (0-40) | X36: 12.944444 | Y36: 13 | Z36: Few or No (0-40) | AA36: NP | AB36: IU | AC36: PW | AD36: PL | AE36: NP | AF36: PW | AG36: NP | AH36: PW | AI36: 0 | AJ36: 0 | AK36: 1 | AL36: 1 | AM36: 0 | AN36: 0 | AO36: 1 | AP36: 0 | AQ36: 0 | AR36: 0 | AS36: Scant or None (0-20) | AT36: 0 | AU36: 0 | AV36: Scant or None (0-20) | AW36: 77.833333 | AX36: 78 | AY36: Substantial (61-80 | AZ36: 41.75 | BA36: 42 | BB36: Limited (41-60) | BC36: 0 | BD36: 0 | BE36: Scant or None (0-20) | BF36: 0 | BG36: 0 | BH36: Scant or None (0-20) | BI36: 28.230769 | BJ36: 28 | BK36: Minimal (21-40) | BL36: 14.285714 | BM36: 14 | BN36: Scant or None (0-20) | BO36: d | BP36: d | BQ36: c | BR36: d | BS36: d | BT36: c | BU36: d | CD36: 0 | CE36: 0 | CF36: 0 | CG36: 0 | CH36: 0 | CI36: 0 | CJ36: 0 | CK36: 0 | CL36: 0 | CM36: 0 | CN36: 0 | CO36: 0 | CP36: 0 | CQ36: 0 | CR36: 0 | CS36: 0 | CT36: 0 | CU36: 0 | CV36: 0 | CW36: 0 | CX36: 0 | CY36: 0 | CZ36: 0 | DA36: 0 | DB36: 0 | DC36: 0 | DD36: 0 | DE36: 0 | DF36: 0 | DG36: 0 | DH36: 0 | DI36: 0 | DJ36: 0 | DK36: 0 | DL36: 0 | DM36: 0 | DN36: 0 | DO36: 0 | DP36: 0 | DQ36: 0 | DR36: 0 | DS36: 0 | DT36: 0 | DU36: 0 | DV36: 0 | DW36: 0 | DX36: 0 | DY36: 0 | DZ36: 0 | EA36: 0 | EB36: 0 | EC36: 0 | ED36: 0 | EE36: 0 | EF36: 0 | EG36: 0 | EH36: 0 | EI36: 0 | EJ36: 67 | EK36: 100 | EL36: 100 | EM36: 100 | EN36: 67 | EO36: 67 | EP36: 67 | EQ36: 0 | ER36: 33 | ES36: 0 | ET36: 0 | EU36: 0 | EV36: 0 | EW36: 0 | EX36: 0 | EY36: 0 | EZ36: 0 | FA36: 0 | FB36: 0 | FC36: 0 | FD36: 0 | FE36: 0 | FF36: 0 | FG36: 0 | FH36: 0 | FI36: 0 | FJ36: 67 | FK36: 0 | FL36: 0 | FM36: 100 | FN36: 67 | FO36: 0 | FP36: 0 | FQ36: 0 | FR36: 0 | FS36: 0 | FU36: 100 | FV36: 100 | FW36: 0 | FX36: 0 | FY36: 0 | FZ36: 0 | GA36: 0 | GB36: 0 | GC36: 0 | GD36: 0 | GE36: 0 | GF36: 0 | GG36: 67 | GH36: 100 | GI36: 67 | GJ36: 33 | GK36: 33 | GL36: 0 | GM36: 33 | GN36: 67 | GO36: 100 | GP36: 0 | GQ36: 0 | GR36: 100 | GS36: 100 | GT36: 33 | GU36: 100 | GV36: 33 | GW36: 0 | GX36: 0 | GY36: 0 | GZ36: 0 | HA36: 33 | HB36: 0 | HC36: 67 | HD36: 0 | HE36: 0 | HF36: 0 | HG36: 0 | HH36: 0 | HI36: 0 | HJ36: 0 | HK36: 0 | HL36: 0 | HM36: 100 | HN36: 33 | HO36: 0 | HP36: 0 | HQ36: 0 | HR36: 33 | HS36: 0 | HT36: 0 | HU36: 33 | HV36: 0 | HW36: 0 | HX36: 0 | HY36: 1 | HZ36: 1 | IA36: 1 | IB36: 1 | IC36: 1 | ID36: 1 | IE36: 1 | IF36: 1
A37: Bolivia | B37: BOL | C37: 2015 | D37: Latin America & Caribbean | E37: South America | F37: 16.8349 | G37: 17 | H37: Scant or None (0-20) | I37: Low (0-40) | J37: Insufficient (0-60) | K37: Bottom Quintile | O37: 57.727299 | P37: 58 | Q37: Moderate | R37: 58.25 | S37: 58 | T37: Moderate | X37: 0 | Y37: 0 | Z37: No | AA37: IU | AB37: IU | AC37: PW | AD37: PW | AE37: NP | AF37: PW | AG37: PW | AH37: NP | AI37: 0 | AJ37: 0 | AK37: 1 | AL37: 0 | AM37: 1 | AN37: 0 | AO37: 1 | AP37: 1 | AQ37: 0 | AR37: 0 | AS37: Scant or None (0-20) | AT37: 0 | AU37: 0 | AV37: Scant or None (0-20) | AW37: 83.5 | AX37: 84 | AY37: Extensive (81-100) | AZ37: 0 | BA37: 0 | BB37: Scant or None (0-20) | BC37: 74.222198 | BD37: 74 | BE37: Substantial (61-80 | BF37: 0 | BG37: 0 | BH37: Scant or None (0-20) | BI37: 33.285702 | BJ37: 33 | BK37: Minimal (21-40) | BL37: 28.5714 | BM37: 29 | BN37: Minimal (21-40) | CD37: 0 | CE37: 0 | CF37: 0 | CG37: 0 | CH37: 0 | CI37: 0 | CJ37: 0 | CK37: 0 | CL37: 0 | CM37: 0 | CN37: 0 | CO37: 0 | CP37: 0 | CQ37: 0 | CR37: 0 | CS37: 0 | CT37: 0 | CU37: 0 | CV37: 0 | CW37: 0 | CX37: 0 | CY37: 0 | CZ37: 0 | DA37: 0 | DB37: 0 | DC37: 0 | DD37: 0 | DE37: 0 | DF37: 0 | DG37: 0 | DH37: 0 | DI37: 0 | DJ37: 0 | DK37: 0 | DL37: 0 | DM37: 0 | DN37: 0 | DO37: 0 | DP37: 0 | DQ37: 0 | DR37: 0 | DS37: 0 | DT37: 0 | DU37: 0 | DV37: 0 | DW37: 0 | DX37: 0 | DY37: 0 | DZ37: 0 | EA37: 0 | EB37: 0 | EC37: 0 | ED37: 0 | EE37: 0 | EF37: 0 | EG37: 0 | EH37: 0 | EI37: 0 | EJ37: 67 | EK37: 100 | EL37: 100 | EM37: 100 | EN37: 67 | EO37: 0 | EP37: 0 | EQ37: 0 | ER37: 0 | ES37: 67 | ET37: 67 | EU37: 100 | EV37: 100 | EW37: 33 | EX37: 100 | EY37: 67 | EZ37: 67 | FA37: 0 | FB37: 0 | FC37: 0 | FD37: 0 | FE37: 0 | FF37: 0 | FG37: 0 | FH37: 0 | FI37: 100 | FJ37: 33 | FK37: 0 | FL37: 100 | FM37: 100 | FN37: 33 | FO37: 0 | FP37: 0 | FQ37: 0 | FR37: 0 | FS37: 0 | FT37: 0 | FU37: 0 | FV37: 100 | FW37: 33 | FX37: 0 | FY37: 0 | FZ37: 0 | GA37: 0 | GB37: 0 | GC37: 0 | GD37: 0 | GE37: 67 | GF37: 67 | GG37: 67 | GH37: 67 | GI37: 67 | GJ37: 100 | GK37: 100 | GL37: 100 | GM37: 0 | GN37: 100 | GO37: 33 | GP37: 100 | GQ37: 0 | GR37: 0 | GS37: 0 | GT37: 0 | GU37: 0 | GV37: 0 | GW37: 0 | GX37: 0 | GY37: 0 | GZ37: 0 | HA37: 0 | HB37: 0 | HC37: 0 | HD37: 0 | HE37: 0 | HF37: 0 | HP37: 0 | HQ37: 0 | HR37: 67 | HS37: 67 | HT37: 0 | HU37: 100 | HV37: 67 | HW37: 0 | HX37: 0 | HY37: 1 | HZ37: 1 | IA37: 1 | IB37: 1 | IC37: 1 | ID37: 1 | IE37: 1 | IF37: 1
A38: Bolivia | B38: BOL | C38: 2012 | D38: Latin America & Caribbean | E38: South America | F38: 11.9368 | G38: 12 | H38: Scant or None (0-20) | I38: Low (0-40) | J38: Insufficient (0-60) | K38: Bottom Quintile | O38: 45.454498 | P38: 45 | Q38: Moderate | R38: 75 | S38: 75 | T38: Strong | X38: 2.75 | Y38: 3 | Z38: Weak | AA38: IU | AB38: IU | AC38: PW | AD38: PW | AE38: NP | AF38: PW | AG38: PW | AH38: NP | AI38: 0 | AJ38: 0 | AK38: 1 | AL38: 0 | AM38: 1 | AN38: 0 | AO38: 1 | AP38: 1 | AQ38: 0 | AR38: 0 | AS38: Scant or None (0-20) | AT38: 1.72414 | AU38: 2 | AV38: Scant or None (0-20) | AW38: 100 | AX38: 100 | AY38: Extensive (81-100) | AZ38: 0 | BA38: 0 | BB38: Scant or None (0-20) | BC38: 79.375 | BD38: 79 | BE38: Substantial (61-80 | BF38: 0 | BG38: 0 | BH38: Scant or None (0-20) | BI38: 13.3 | BJ38: 13 | BK38: Scant or None (0-20) | BL38: 23.7143 | BM38: 24 | BN38: Minimal (21-40) | CD38: 0 | CI38: 0 | CL38: 0 | CM38: 0 | CQ38: 0 | CR38: 0 | CS38: 0 | CT38: 0 | CU38: 0 | CW38: 0 | CX38: 0 | DA38: 0 | DD38: 0 | DG38: 0 | DH38: 0 | DI38: 0 | DJ38: 0 | DL38: 0 | DN38: 0 | DO38: 0 | DP38: 0 | DQ38: 0 | DR38: 0 | DS38: 0 | DT38: 0 | DU38: 0 | DV38: 0 | DW38: 0 | DX38: 0 | DY38: 0 | EA38: 0 | EB38: 0 | EC38: 0 | ED38: 0 | EE38: 0 | EO38: 0 | EP38: 0 | EQ38: 0 | ER38: 0 | EU38: 67 | EW38: 67 | EX38: 67 | EZ38: 67 | FA38: 0 | FB38: 0 | FE38: 0 | FI38: 0 | FL38: 33 | FP38: 0 | FQ38: 0 | FR38: 0 | FS38: 0 | FT38: 0 | FW38: 33 | FX38: 0 | FY38: 0 | FZ38: 0 | GA38: 0 | GB38: 0 | GC38: 0 | GD38: 0 | GE38: 67 | GG38: 67 | GH38: 0 | GI38: 33 | GJ38: 100 | GK38: 100 | GL38: 100 | GM38: 33 | GN38: 100 | GP38: 100 | GQ38: 0 | GR38: 67 | GS38: 0 | GT38: 0 | GV38: 0 | GW38: 0 | GX38: 0 | GY38: 33 | GZ38: 0 | HA38: 0 | HB38: 0 | HE38: 0 | HF38: 0 | HP38: 0 | HQ38: 67 | HS38: 100 | HU38: 100 | HV38: 100 | HW38: 0 | HX38: 0 | HY38: 1 | HZ38: 1 | IA38: 1 | IB38: 1 | IC38: 1 | ID38: 1 | IE38: 1 | IF38: 1
A39: Bolivia | B39: BOL | C39: 2010 | D39: Latin America & Caribbean | E39: South America | F39: 13.413 | G39: 13 | H39: Scant or None (0-20) | I39: Low (0-40) | J39: Insufficient (0-60) | K39: Bottom Quintile | O39: 41.666698 | P39: 42 | Q39: Moderate | R39: 36.599998 | S39: 37 | T39: Moderate | AA39: IU | AB39: IU | AC39: PW | AD39: PW | AE39: IU | AF39: PW | AG39: PW | AH39: NP | AI39: 0 | AJ39: 0 | AK39: 1 | AL39: 0 | AM39: 1 | AN39: 0 | AO39: 1 | AP39: 1 | AQ39: 0 | AR39: 0 | AS39: Scant or None (0-20) | AT39: 0 | AU39: 0 | AV39: Scant or None (0-20) | AW39: 100 | AX39: 100 | AY39: Extensive (81-100) | AZ39: 0 | BA39: 0 | BB39: Scant or None (0-20) | BC39: 91.75 | BD39: 92 | BE39: Extensive (81-100) | BF39: 0 | BG39: 0 | BH39: Scant or None (0-20) | BI39: 10 | BJ39: 10 | BK39: Scant or None (0-20) | BL39: 28.5714 | BM39: 29 | BN39: Minimal (21-40) | CD39: 0 | CI39: 0 | CL39: 0 | CM39: 0 | CQ39: 0 | CR39: 0 | CS39: 0 | CT39: 0 | CU39: 0 | CW39: 0 | CX39: 0 | DA39: 0 | DD39: 0 | DG39: 0 | DH39: 0 | DI39: 0 | DJ39: 0 | DL39: 0 | DN39: 0 | DO39: 0 | DP39: 0 | DQ39: 0 | DR39: 0 | DS39: 0 | DT39: 0 | DU39: 0 | DV39: 0 | DW39: 0 | DX39: 0 | DY39: 0 | EA39: 0 | EB39: 0 | EC39: 0 | ED39: 0 | EE39: 0 | EO39: 0 | EU39: 100 | EW39: 67 | EX39: 100 | EZ39: 100 | FA39: 0 | FB39: 0 | FE39: 0 | FI39: 0 | FL39: 0 | FP39: 0 | FQ39: 0 | FR39: 0 | FS39: 0 | FT39: 0 | FW39: 67 | FX39: 0 | FY39: 100 | FZ39: 0 | GA39: 0 | GD39: 0 | GE39: 67 | GG39: 0 | GH39: 0 | GK39: 100 | GL39: 100 | GM39: 33 | GN39: 100 | GP39: 100 | GQ39: 0 | GR39: 67 | GY39: 33 | GZ39: 0 | HA39: 0 | HB39: 0 | HP39: 0 | HQ39: 67 | HS39: 100 | HU39: 67 | HV39: 33 | HW39: 0 | HX39: 0 | HY39: 1 | HZ39: 1 | IA39: 1 | IB39: 1 | IC39: 1 | ID39: 1 | IE39: 1 | IF39: 1
A40: Bolivia | B40: BOL | C40: 2008 | D40: Latin America & Caribbean | E40: South America | F40: 6.52174 | G40: 7 | H40: Scant or None (0-20) | I40: Low (0-40) | J40: Insufficient (0-60) | K40: Bottom Quintile | O40: 25 | P40: 25 | Q40: Weak | R40: 39.900002 | S40: 40 | T40: Moderate | AA40: IU | AB40: IU | AC40: HC | AD40: PW | AE40: IU | AF40: PW | AG40: NP | AH40: NP | AI40: 0 | AJ40: 0 | AK40: 1 | AL40: 0 | AM40: 1 | AN40: 0 | AO40: 1 | AP40: 0 | AQ40: 0 | AR40: 0 | AS40: Scant or None (0-20) | AT40: 0 | AU40: 0 | AV40: Scant or None (0-20) | AW40: 100 | AX40: 100 | AY40: Extensive (81-100) | AZ40: 0 | BA40: 0 | BB40: Scant or None (0-20) | BC40: 20.875 | BD40: 21 | BE40: Minimal (21-40) | BF40: 0 | BG40: 0 | BH40: Scant or None (0-20) | BI40: 16.700001 | BJ40: 17 | BK40: Scant or None (0-20) | BL40: 9.4285698 | BM40: 9 | BN40: Scant or None (0-20) | CD40: 0 | CI40: 0 | CL40: 0 | CM40: 0 | CQ40: 0 | CR40: 0 | CS40: 0 | CT40: 0 | CU40: 0 | CW40: 0 | CX40: 0 | DA40: 0 | DD40: 0 | DG40: 0 | DH40: 0 | DI40: 0 | DJ40: 0 | DL40: 0 | DN40: 0 | DO40: 0 | DP40: 0 | DQ40: 0 | DR40: 0 | DS40: 0 | DT40: 0 | DU40: 0 | DV40: 0 | DW40: 0 | DX40: 0 | DY40: 0 | EA40: 0 | EB40: 0 | EC40: 0 | ED40: 0 | EE40: 0 | EO40: 0 | EU40: 0 | EW40: 67 | EX40: 0 | EZ40: 33 | FA40: 0 | FB40: 0 | FE40: 0 | FI40: 0 | FL40: 0 | FP40: 0 | FQ40: 0 | FR40: 0 | FS40: 0 | FT40: 0 | FW40: 33 | FX40: 33 | FY40: 0 | FZ40: 0 | GA40: 0 | GD40: 0 | GE40: 67 | GG40: 0 | GH40: 0 | GK40: 0 | GL40: 100 | GM40: 33 | GN40: 100 | GP40: 100 | GQ40: 33 | GR40: 67 | GY40: 33 | GZ40: 0 | HA40: 0 | HB40: 0 | HP40: 0 | HQ40: 67 | HS40: 0 | HU40: 100 | HV40: 0 | HW40: 0 | HX40: 0 | HY40: 1 | HZ40: 1 | IA40: 1 | IB40: 1 | IC40: 1 | ID40: 1 | IE40: 1 | IF40: 1
A41: Bolivia | B41: BOL | C41: 2006 | D41: Latin America & Caribbean | E41: South America | F41: 20.6413 | G41: 21 | H41: Minimal (21-40) | I41: Low (0-40) | J41: Insufficient (0-60) | K41: 2nd Quintile | O41: 50 | P41: 50 | Q41: Moderate | R41: 41.625 | S41: 42 | T41: Moderate | AA41: IU | AB41: PW | AC41: PW | AD41: IU | AE41: NP | AF41: PW | AG41: PW | AH41: NP | AI41: 0 | AJ41: 1 | AK41: 1 | AL41: 0 | AM41: 0 | AN41: 0 | AO41: 1 | AP41: 1 | AQ41: 0 | AR41: 0 | AS41: Scant or None (0-20) | AT41: 21.799999 | AU41: 22 | AV41: Minimal (21-40) | AW41: 100 | AX41: 100 | AY41: Extensive (81-100) | AZ41: 0 | BA41: 0 | BB41: Scant or None (0-20) | BC41: 0 | BD41: 0 | BE41: Scant or None (0-20) | BF41: 0 | BG41: 0 | BH41: Scant or None (0-20) | BI41: 40 | BJ41: 40 | BK41: Minimal (21-40) | BL41: 25 | BM41: 25 | BN41: Minimal (21-40) | CD41: 100 | CI41: 100 | CL41: 100 | CM41: 100 | CQ41: 33 | CR41: 67 | CS41: 0 | CT41: 0 | CU41: 0 | CW41: 0 | CX41: 0 | DA41: 0 | DD41: 0 | DG41: 0 | DH41: 0 | DI41: 0 | DJ41: 0 | DL41: 100 | DN41: 67 | DO41: 33 | DP41: 0 | DQ41: 0 | DR41: 0 | DS41: 0 | DT41: 0 | DU41: 100 | DV41: 33 | DW41: 100 | DX41: 0 | DY41: 0 | EA41: 0 | EB41: 0 | EC41: 33 | ED41: 0 | EE41: 0 | EO41: 0 | EU41: 0 | EW41: 0 | EX41: 0 | EZ41: 0 | FA41: 0 | FB41: 0 | FE41: 0 | FI41: 100 | FL41: 100 | FP41: 0 | FQ41: 0 | FR41: 0 | FS41: 0 | FT41: 0 | FW41: 0 | FX41: 0 | FY41: 100 | FZ41: 0 | GA41: 33 | GD41: 0 | GE41: 100 | GG41: 100 | GH41: 0 | GK41: 100 | GL41: 100 | GM41: 33 | GN41: 100 | GP41: 100 | GQ41: 67 | GR41: 0 | GY41: 0 | GZ41: 67 | HA41: 0 | HB41: 0 | HP41: 0 | HQ41: 100 | HS41: 0 | HU41: 100 | HV41: 0 | HW41: 0 | HX41: 0 | HY41: 1 | HZ41: 1 | IA41: 1 | IB41: 1 | IC41: 1 | ID41: 1 | IE41: 1 | IF41: 1
A42: Bosnia and Herzegovina | B42: BIH | C42: 2025 | D42: Eastern Europe & Central Asia | E42: Western Balkans & Turkiye | F42: 29.757282 | G42: 30 | H42: Minimal (21-40) | I42: Low (0-40) | J42: Insufficient (0-60) | K42: 2nd Quintile | L42: 48.111111 | M42: 48 | N42: Limited (41-60) | O42: 24.916667 | P42: 25 | Q42: Weak (0-40) | R42: 94.5 | S42: 95 | T42: Adequate (61-100) | U42: 0 | V42: 0 | W42: Weak (0-40) | X42: 7.3888889 | Y42: 7 | Z42: Few or no opportunities (0-40) | AA42: PL | AB42: PW | AC42: PW | AD42: PL | AE42: NP | AF42: PW | AG42: PW | AH42: PW | AI42: 0 | AJ42: 1 | AK42: 1 | AL42: 1 | AM42: 0 | AN42: 0 | AO42: 1 | AP42: 1 | AQ42: 0 | AR42: 0 | AS42: Scant or None (0-20) | AT42: 27.98 | AU42: 28 | AV42: Minimal (21-40) | AW42: 50 | AX42: 50 | AY42: Limited (41-60) | AZ42: 50 | BA42: 50 | BB42: Limited (41-60) | BC42: 0 | BD42: 0 | BE42: Scant or None (0-20) | BF42: 0 | BG42: 0 | BH42: Scant or None (0-20) | BI42: 53.769231 | BJ42: 54 | BK42: Limited (41-60) | BL42: 77.833333 | BM42: 78 | BN42: Substantial (61-80) | BO42: d | BP42: c | BQ42: a | BR42: d | BS42: d | BT42: a | BU42: b | BV42: a | BW42: e | BX42: e | BY42: a | BZ42: d | CA42: e | CB42: e | CC42: e | CD42: 100 | CE42: 0 | CF42: 0 | CG42: 100 | CH42: 100 | CI42: 100 | CJ42: 0 | CK42: 0 | CL42: 0 | CM42: 67 | CN42: 0 | CO42: 0 | CP42: 33 | CQ42: 0 | CR42: 67 | CS42: 0 | CT42: 33 | CU42: 33 | CV42: 67 | CW42: 100 | CX42: 0 | CY42: 0 | CZ42: 0 | DA42: 0 | DB42: 100 | DC42: 33 | DD42: 0 | DE42: 0 | DF42: 0 | DG42: 0 | DH42: 0 | DI42: 0 | DL42: 100 | DM42: 0 | DO42: 0 | DP42: 0 | DQ42: 0 | DS42: 0 | DT42: 0 | DU42: 0 | DV42: 0 | DW42: 100 | DX42: 33 | DY42: 0 | DZ42: 33 | EA42: 67 | EB42: 0 | EC42: 0 | ED42: 100 | EE42: 0 | EF42: 0 | EG42: 0 | EH42: 0 | EI42: 0 | EJ42: 67 | EK42: 0 | EL42: 100 | EM42: 33 | EN42: 0 | EO42: 67 | EP42: 33 | EQ42: 67 | ER42: 33 | ES42: 0 | ET42: 0 | EU42: 0 | EV42: 0 | EW42: 0 | EX42: 0 | EY42: 0 | EZ42: 0 | FA42: 0 | FB42: 0 | FC42: 0 | FD42: 0 | FE42: 0 | FF42: 0 | FG42: 0 | FH42: 0 | FI42: 100 | FJ42: 100 | FK42: 33 | FL42: 100 | FM42: 100 | FN42: 33 | FO42: 33 | FP42: 0 | FQ42: 0 | FR42: 0 | FS42: 0 | FU42: 100 | FV42: 100 | FW42: 100 | FY42: 100 | FZ42: 0 | GA42: 100 | GB42: 0 | GC42: 0 | GD42: 0 | GE42: 0 | GF42: 33 | GG42: 0 | GH42: 0 | GI42: 100 | GJ42: 33 | GK42: 0 | GL42: 0 | GM42: 0 | GN42: 0 | GO42: 0 | GP42: 100 | GQ42: 33 | GR42: 100 | GS42: 100 | GT42: 100 | GU42: 100 | GV42: 67 | GW42: 100 | GX42: 0 | GY42: 0 | GZ42: 0 | HA42: 0 | HB42: 0 | HC42: 0 | HD42: 0 | HE42: 0 | HF42: 0 | HG42: 0 | HH42: 0 | HI42: 33 | HJ42: 0 | HK42: 0 | HL42: 0 | HM42: 100 | HN42: 0 | HO42: 0 | HP42: 0 | HQ42: 33 | HR42: 100 | HS42: 0 | HT42: 0 | HU42: 100 | HV42: 67 | HW42: 0 | HX42: 0 | HY42: 1 | HZ42: 1 | IA42: 1 | IB42: 1 | IC42: 1 | ID42: 1 | IE42: 1 | IF42: 1
A43: Bosnia and Herzegovina | B43: BIH | C43: 2023 | D43: Eastern Europe & Central Asia | E43: Western Balkans & Turkiye | F43: 27.495146 | G43: 27 | H43: Minimal (21-40) | I43: Low (0-40) | J43: Insufficient (0-60) | K43: 2nd Quintile | L43: 51.833333 | M43: 52 | N43: Limited (41-60) | O43: 30.5 | P43: 31 | Q43: Weak (0-40) | R43: 94.5 | S43: 95 | T43: Adequate (61-100) | U43: 0 | V43: 0 | W43: Weak (0-40) | X43: 7.3888889 | Y43: 7 | Z43: Few or no opportunities (0-40) | AA43: IU | AB43: PW | AC43: PW | AD43: PL | AE43: NP | AF43: PW | AG43: PW | AH43: PL | AI43: 0 | AJ43: 1 | AK43: 1 | AL43: 0 | AM43: 0 | AN43: 0 | AO43: 1 | AP43: 1 | AQ43: 0 | AR43: 0 | AS43: Scant or None (0-20) | AT43: 27.98 | AU43: 28 | AV43: Minimal (21-40) | AW43: 50 | AX43: 50 | AY43: Limited (41-60) | AZ43: 0 | BA43: 0 | BB43: Scant or None (0-20) | BC43: 0 | BD43: 0 | BE43: Scant or None (0-20) | BF43: 0 | BG43: 0 | BH43: Scant or None (0-20) | BI43: 51.230769 | BJ43: 51 | BK43: Limited (41-60) | BL43: 77.833333 | BM43: 78 | BN43: Substantial (61-80 | BO43: d | BP43: c | BQ43: a | BR43: d | BS43: d | BT43: b | BU43: b | BV43: c | BW43: e | BX43: e | BY43: a | BZ43: d | CA43: e | CB43: e | CD43: 100 | CE43: 0 | CF43: 0 | CG43: 100 | CH43: 100 | CI43: 100 | CJ43: 0 | CK43: 0 | CL43: 0 | CM43: 67 | CN43: 0 | CO43: 0 | CP43: 33 | CQ43: 0 | CR43: 67 | CS43: 0 | CT43: 33 | CU43: 100 | CV43: 0 | CW43: 0 | CX43: 0 | CY43: 67 | CZ43: 0 | DA43: 0 | DB43: 0 | DC43: 0 | DD43: 0 | DE43: 100 | DF43: 33 | DG43: 0 | DH43: 0 | DI43: 0 | DL43: 100 | DM43: 0 | DO43: 0 | DP43: 0 | DQ43: 0 | DS43: 0 | DT43: 0 | DU43: 33 | DV43: 0 | DW43: 100 | DX43: 33 | DY43: 0 | DZ43: 33 | EA43: 67 | EB43: 0 | EC43: 0 | ED43: 100 | EE43: 0 | EF43: 0 | EG43: 0 | EH43: 0 | EI43: 0 | EJ43: 67 | EK43: 0 | EL43: 100 | EM43: 33 | EN43: 0 | EO43: 0 | EP43: 0 | EQ43: 0 | ER43: 0 | ES43: 0 | ET43: 0 | EU43: 0 | EV43: 0 | EW43: 0 | EX43: 0 | EY43: 0 | EZ43: 0 | FA43: 0 | FB43: 0 | FC43: 0 | FD43: 0 | FE43: 0 | FF43: 0 | FG43: 0 | FH43: 0 | FI43: 100 | FJ43: 100 | FK43: 33 | FL43: 100 | FM43: 100 | FN43: 33 | FO43: 33 | FP43: 0 | FQ43: 0 | FR43: 0 | FS43: 0 | FU43: 100 | FV43: 100 | FW43: 100 | FY43: 100 | FZ43: 0 | GA43: 100 | GB43: 0 | GC43: 0 | GD43: 0 | GE43: 0 | GF43: 33 | GG43: 0 | GH43: 0 | GI43: 100 | GJ43: 33 | GK43: 33 | GL43: 0 | GM43: 0 | GN43: 0 | GO43: 0 | GP43: 100 | GQ43: 67 | GR43: 100 | GS43: 100 | GT43: 100 | GU43: 100 | GV43: 67 | GW43: 100 | GX43: 0 | GY43: 0 | GZ43: 0 | HA43: 0 | HB43: 0 | HC43: 0 | HD43: 0 | HE43: 0 | HF43: 0 | HG43: 0 | HH43: 0 | HI43: 33 | HJ43: 0 | HK43: 0 | HL43: 0 | HM43: 100 | HN43: 0 | HO43: 0 | HP43: 0 | HQ43: 33 | HR43: 100 | HS43: 0 | HT43: 0 | HU43: 67 | HV43: 67 | HW43: 0 | HX43: 0 | HY43: 1 | HZ43: 1 | IA43: 1 | IB43: 1 | IC43: 1 | ID43: 1 | IE43: 1 | IF43: 1
A44: Bosnia and Herzegovina | B44: BIH | C44: 2021 | D44: Eastern Europe & Central Asia | E44: Western Balkans & Turkiye | F44: 32.349515 | G44: 32 | H44: Minimal (21-40) | I44: Low (0-40) | J44: Insufficient (0-60) | K44: 2nd Quintile | L44: 57.388889 | M44: 57 | N44: Limited (41-60) | O44: 38.833333 | P44: 39 | Q44: Weak (0-40) | R44: 94.5 | S44: 95 | T44: Adequate (61-100) | U44: 0 | V44: 0 | W44: Weak (0-40) | X44: 9.2222222 | Y44: 9 | Z44: Few or no opportunities (0-40) | AA44: PW | AB44: PW | AC44: PW | AD44: PL | AE44: NP | AF44: PW | AG44: PW | AH44: PL | AI44: 1 | AJ44: 1 | AK44: 1 | AL44: 0 | AM44: 0 | AN44: 0 | AO44: 1 | AP44: 1 | AQ44: 66.666667 | AR44: 67 | AS44: Substantial (61-80 | AT44: 29.32 | AU44: 29 | AV44: Minimal (21-40) | AW44: 50 | AX44: 50 | AY44: Limited (41-60) | AZ44: 0 | BA44: 0 | BB44: Scant or None (0-20) | BC44: 0 | BD44: 0 | BE44: Scant or None (0-20) | BF44: 0 | BG44: 0 | BH44: Scant or None (0-20) | BI44: 53.769231 | BJ44: 54 | BK44: Limited (41-60) | BL44: 77.833333 | BM44: 78 | BN44: Substantial (61-80 | BO44: c | BP44: c | BQ44: b | BR44: d | BS44: d | BT44: a | BU44: b | BV44: e | BW44: e | BX44: e | BY44: a | BZ44: d | CA44: e | CB44: e | CD44: 100 | CE44: 0 | CF44: 0 | CG44: 100 | CH44: 100 | CI44: 100 | CJ44: 0 | CK44: 0 | CL44: 0 | CM44: 67 | CN44: 0 | CO44: 0 | CP44: 33 | CQ44: 0 | CR44: 67 | CS44: 0 | CT44: 100 | CU44: 100 | CV44: 67 | CW44: 0 | CX44: 0 | CY44: 0 | CZ44: 0 | DA44: 0 | DB44: 100 | DC44: 33 | DD44: 0 | DE44: 0 | DF44: 0 | DG44: 0 | DH44: 0 | DI44: 0 | DL44: 100 | DM44: 0 | DO44: 0 | DP44: 0 | DQ44: 0 | DS44: 0 | DT44: 0 | DU44: 33 | DV44: 0 | DW44: 100 | DX44: 33 | DY44: 0 | DZ44: 33 | EA44: 67 | EB44: 0 | EC44: 0 | ED44: 100 | EE44: 67 | EF44: 100 | EG44: 100 | EH44: 0 | EI44: 100 | EJ44: 67 | EK44: 0 | EL44: 100 | EM44: 33 | EN44: 33 | EO44: 0 | EP44: 0 | EQ44: 0 | ER44: 0 | ES44: 0 | ET44: 0 | EU44: 0 | EV44: 0 | EW44: 0 | EX44: 0 | EY44: 0 | EZ44: 0 | FA44: 0 | FB44: 0 | FC44: 0 | FD44: 0 | FE44: 0 | FF44: 0 | FG44: 0 | FH44: 0 | FI44: 100 | FJ44: 100 | FK44: 33 | FL44: 100 | FM44: 100 | FN44: 33 | FO44: 33 | FP44: 0 | FQ44: 0 | FR44: 0 | FS44: 0 | FU44: 100 | FV44: 100 | FW44: 100 | FY44: 100 | FZ44: 0 | GA44: 100 | GB44: 0 | GC44: 0 | GD44: 0 | GE44: 0 | GF44: 33 | GG44: 0 | GH44: 0 | GI44: 100 | GJ44: 100 | GK44: 33 | GL44: 0 | GM44: 0 | GN44: 0 | GO44: 0 | GP44: 100 | GQ44: 100 | GR44: 100 | GS44: 100 | GT44: 100 | GU44: 100 | GV44: 67 | GW44: 100 | GX44: 0 | GY44: 0 | GZ44: 0 | HA44: 0 | HB44: 0 | HC44: 0 | HD44: 0 | HE44: 0 | HF44: 0 | HG44: 0 | HH44: 0 | HI44: 33 | HJ44: 0 | HK44: 0 | HL44: 33 | HM44: 100 | HN44: 0 | HO44: 0 | HP44: 33 | HQ44: 33 | HR44: 67 | HS44: 0 | HT44: 0 | HU44: 100 | HV44: 67 | HW44: 0 | HX44: 0 | HY44: 1 | HZ44: 1 | IA44: 1 | IB44: 1 | IC44: 1 | ID44: 1 | IE44: 1 | IF44: 1
A45: Bosnia and Herzegovina | B45: BIH | C45: 2019 | D45: Eastern Europe & Central Asia | E45: Western Balkans & Turkiye | F45: 33.330097 | G45: 33 | H45: Minimal (21-40) | I45: Low (0-40) | J45: Insufficient (0-60) | K45: 2nd Quintile | L45: 51.777778 | M45: 52 | N45: Limited (41-60) | O45: 33.25 | P45: 33 | Q45: Weak (0-40) | R45: 88.833333 | S45: 89 | T45: Adequate (61-100) | U45: 0 | V45: 0 | W45: Weak (0-40) | X45: 7.3888889 | Y45: 7 | Z45: Few or no opportunities (0-40) | AA45: PW | AB45: PW | AC45: PW | AD45: PL | AE45: NP | AF45: PW | AG45: PW | AH45: NP | AI45: 1 | AJ45: 1 | AK45: 1 | AL45: 0 | AM45: 0 | AN45: 0 | AO45: 1 | AP45: 1 | AQ45: 77.833333 | AR45: 78 | AS45: Substantial (61-80 | AT45: 29.32 | AU45: 29 | AV45: Minimal (21-40) | AW45: 50 | AX45: 50 | AY45: Limited (41-60) | AZ45: 0 | BA45: 0 | BB45: Scant or None (0-20) | BC45: 0 | BD45: 0 | BE45: Scant or None (0-20) | BF45: 0 | BG45: 0 | BH45: Scant or None (0-20) | BI45: 51.230769 | BJ45: 51 | BK45: Limited (41-60) | BL45: 89 | BM45: 89 | BN45: Extensive (81-100) | BO45: a | BP45: c | BQ45: b | BR45: d | BS45: d | BT45: b | BU45: b | BV45: e | BW45: e | BX45: e | BY45: a | BZ45: d | CA45: e | CB45: e | CD45: 100 | CE45: 0 | CF45: 0 | CG45: 100 | CH45: 100 | CI45: 100 | CJ45: 0 | CK45: 0 | CL45: 0 | CM45: 67 | CN45: 0 | CO45: 0 | CP45: 33 | CQ45: 0 | CR45: 67 | CS45: 0 | CT45: 100 | CU45: 100 | CV45: 67 | CW45: 0 | CX45: 0 | CY45: 0 | CZ45: 0 | DA45: 0 | DB45: 100 | DC45: 33 | DD45: 0 | DE45: 0 | DF45: 0 | DG45: 0 | DH45: 0 | DI45: 0 | DL45: 100 | DM45: 0 | DO45: 0 | DP45: 0 | DQ45: 0 | DS45: 0 | DT45: 0 | DU45: 33 | DV45: 0 | DW45: 100 | DX45: 33 | DY45: 0 | DZ45: 33 | EA45: 67 | EB45: 0 | EC45: 0 | ED45: 100 | EE45: 67 | EF45: 100 | EG45: 100 | EH45: 0 | EI45: 100 | EJ45: 67 | EK45: 0 | EL45: 100 | EM45: 33 | EN45: 33 | EO45: 0 | EP45: 0 | EQ45: 0 | ER45: 0 | ES45: 0 | ET45: 0 | EU45: 0 | EV45: 0 | EW45: 0 | EX45: 0 | EY45: 0 | EZ45: 0 | FA45: 0 | FB45: 0 | FC45: 0 | FD45: 0 | FE45: 0 | FF45: 0 | FG45: 0 | FH45: 0 | FI45: 100 | FJ45: 100 | FK45: 33 | FL45: 100 | FM45: 100 | FN45: 33 | FO45: 33 | FP45: 0 | FQ45: 0 | FR45: 0 | FS45: 0 | FU45: 100 | FV45: 100 | FW45: 100 | FY45: 100 | FZ45: 67 | GA45: 100 | GB45: 0 | GC45: 0 | GD45: 0 | GE45: 0 | GF45: 33 | GG45: 0 | GH45: 33 | GI45: 100 | GJ45: 100 | GK45: 33 | GL45: 0 | GM45: 0 | GN45: 0 | GO45: 0 | GP45: 100 | GQ45: 0 | GR45: 100 | GS45: 100 | GT45: 100 | GU45: 100 | GV45: 33 | GW45: 100 | GX45: 0 | GY45: 0 | GZ45: 0 | HA45: 0 | HB45: 0 | HC45: 0 | HD45: 0 | HE45: 0 | HF45: 0 | HG45: 0 | HH45: 0 | HI45: 33 | HJ45: 0 | HK45: 0 | HL45: 0 | HM45: 100 | HN45: 0 | HO45: 0 | HP45: 100 | HQ45: 33 | HR45: 67 | HS45: 0 | HT45: 0 | HU45: 67 | HV45: 67 | HW45: 0 | HX45: 0 | HY45: 1 | HZ45: 1 | IA45: 1 | IB45: 1 | IC45: 1 | ID45: 1 | IE45: 1 | IF45: 1
A46: Bosnia and Herzegovina | B46: BIH | C46: 2017 | D46: Eastern Europe & Central Asia | E46: Western Balkans & Turkiye | F46: 34.61165 | G46: 35 | H46: Minimal (21-40) | I46: Low (0-40) | J46: Insufficient (0-60) | K46: 2nd Quintile | L46: 64.777778 | M46: 65 | N46: Adequate (61-100) | O46: 49.916667 | P46: 50 | Q46: Limited (41-60) | R46: 94.5 | S46: 95 | T46: Adequate (61-100) | U46: 0 | V46: 0 | W46: Weak (0-40) | X46: 9.2222222 | Y46: 9 | Z46: Few or No (0-40) | AA46: PW | AB46: PW | AC46: PW | AD46: PL | AE46: NP | AF46: PW | AG46: PW | AH46: NP | AI46: 1 | AJ46: 1 | AK46: 1 | AL46: 0 | AM46: 0 | AN46: 0 | AO46: 1 | AP46: 1 | AQ46: 77.666667 | AR46: 78 | AS46: Substantial (61-80 | AT46: 28.64 | AU46: 29 | AV46: Minimal (21-40) | AW46: 66.666667 | AX46: 67 | AY46: Substantial (61-80 | AZ46: 0 | BA46: 0 | BB46: Scant or None (0-20) | BC46: 0 | BD46: 0 | BE46: Scant or None (0-20) | BF46: 0 | BG46: 0 | BH46: Scant or None (0-20) | BI46: 56.384615 | BJ46: 56 | BK46: Limited (41-60) | BL46: 89 | BM46: 89 | BN46: Extensive (81-100) | BO46: a | BP46: c | BQ46: a | BR46: d | BS46: d | BT46: b | BU46: b | CD46: 100 | CE46: 0 | CF46: 0 | CG46: 100 | CH46: 100 | CI46: 0 | CJ46: 0 | CK46: 0 | CL46: 100 | CM46: 100 | CN46: 0 | CO46: 0 | CP46: 33 | CQ46: 0 | CR46: 33 | CS46: 0 | CT46: 100 | CU46: 100 | CV46: 67 | CW46: 0 | CX46: 0 | CY46: 0 | CZ46: 0 | DA46: 0 | DB46: 100 | DC46: 100 | DD46: 0 | DE46: 0 | DF46: 0 | DG46: 0 | DH46: 0 | DI46: 0 | DL46: 100 | DM46: 0 | DO46: 0 | DP46: 0 | DQ46: 0 | DS46: 0 | DT46: 0 | DU46: 33 | DV46: 0 | DW46: 100 | DX46: 33 | DY46: 0 | DZ46: 0 | EA46: 0 | EB46: 0 | EC46: 0 | ED46: 100 | EE46: 33 | EF46: 100 | EG46: 100 | EH46: 33 | EI46: 100 | EJ46: 67 | EK46: 0 | EL46: 100 | EM46: 100 | EN46: 33 | EO46: 0 | EP46: 0 | EQ46: 0 | ER46: 0 | ES46: 0 | ET46: 0 | EU46: 0 | EV46: 0 | EW46: 0 | EX46: 0 | EY46: 0 | EZ46: 0 | FA46: 0 | FB46: 0 | FC46: 0 | FD46: 0 | FE46: 0 | FF46: 0 | FG46: 0 | FH46: 0 | FI46: 100 | FJ46: 100 | FK46: 33 | FL46: 100 | FM46: 100 | FN46: 100 | FO46: 33 | FP46: 0 | FQ46: 0 | FR46: 0 | FS46: 0 | FU46: 100 | FV46: 100 | FW46: 100 | FY46: 100 | FZ46: 67 | GA46: 100 | GB46: 0 | GC46: 0 | GD46: 0 | GE46: 0 | GF46: 33 | GG46: 33 | GH46: 67 | GI46: 100 | GJ46: 100 | GK46: 33 | GL46: 0 | GM46: 33 | GN46: 0 | GO46: 0 | GP46: 100 | GQ46: 100 | GR46: 100 | GS46: 100 | GT46: 100 | GU46: 100 | GV46: 67 | GW46: 100 | GX46: 0 | GY46: 0 | GZ46: 0 | HA46: 0 | HB46: 0 | HC46: 0 | HD46: 0 | HE46: 0 | HF46: 0 | HG46: 0 | HH46: 0 | HI46: 33 | HJ46: 0 | HK46: 0 | HL46: 33 | HM46: 100 | HN46: 0 | HO46: 0 | HP46: 100 | HQ46: 33 | HR46: 100 | HS46: 0 | HT46: 0 | HU46: 67 | HV46: 67 | HW46: 0 | HX46: 0 | HY46: 1 | HZ46: 1 | IA46: 1 | IB46: 1 | IC46: 1 | ID46: 1 | IE46: 1 | IF46: 1
A47: Bosnia and Herzegovina | B47: BIH | C47: 2015 | D47: Eastern Europe & Central Asia | E47: Western Balkans & Turkiye | F47: 43.25 | G47: 43 | H47: Limited (41-60) | I47: Limited (41-60) | J47: Insufficient (0-60) | K47: Middle Quintile | O47: 36.599998 | P47: 37 | Q47: Weak | R47: 83.25 | S47: 83 | T47: Strong | X47: 22.875 | Y47: 23 | Z47: Minimal | AA47: PW | AB47: PW | AC47: PW | AD47: PW | AE47: NP | AF47: PW | AG47: PW | AH47: NP | AI47: 1 | AJ47: 1 | AK47: 1 | AL47: 0 | AM47: 1 | AN47: 0 | AO47: 1 | AP47: 1 | AQ47: 72.166702 | AR47: 72 | AS47: Substantial (61-80 | AT47: 35.254902 | AU47: 35 | AV47: Minimal (21-40) | AW47: 66.666702 | AX47: 67 | AY47: Substantial (61-80 | AZ47: 0 | BA47: 0 | BB47: Scant or None (0-20) | BC47: 66.666702 | BD47: 67 | BE47: Substantial (61-80 | BF47: 0 | BG47: 0 | BH47: Scant or None (0-20) | BI47: 56.384602 | BJ47: 56 | BK47: Limited (41-60) | BL47: 89 | BM47: 89 | BN47: Extensive (81-100) | CD47: 100 | CE47: 0 | CF47: 0 | CG47: 100 | CH47: 100 | CI47: 100 | CJ47: 0 | CK47: 0 | CL47: 100 | CM47: 100 | CN47: 0 | CO47: 0 | CP47: 33 | CQ47: 0 | CR47: 33 | CS47: 0 | CT47: 100 | CU47: 100 | CV47: 67 | CW47: 100 | CX47: 0 | CY47: 0 | CZ47: 100 | DA47: 0 | DB47: 100 | DC47: 100 | DD47: 0 | DE47: 0 | DF47: 0 | DG47: 0 | DH47: 0 | DI47: 0 | DL47: 100 | DM47: 0 | DN47: 0 | DO47: 0 | DP47: 0 | DQ47: 0 | DS47: 0 | DT47: 0 | DU47: 33 | DV47: 0 | DW47: 100 | DX47: 33 | DY47: 0 | DZ47: 0 | EA47: 33 | EB47: 33 | EC47: 0 | ED47: 100 | EE47: 33 | EF47: 100 | EG47: 100 | EH47: 33 | EI47: 100 | EJ47: 67 | EK47: 0 | EL47: 100 | EM47: 100 | EN47: 33 | EO47: 0 | EP47: 0 | EQ47: 0 | ER47: 0 | ES47: 67 | ET47: 33 | EU47: 100 | EV47: 100 | EW47: 100 | EX47: 100 | EY47: 33 | EZ47: 0 | FA47: 0 | FB47: 0 | FC47: 0 | FD47: 0 | FE47: 0 | FF47: 0 | FG47: 0 | FH47: 0 | FI47: 100 | FJ47: 67 | FK47: 33 | FL47: 100 | FM47: 100 | FN47: 100 | FO47: 33 | FP47: 0 | FQ47: 0 | FR47: 0 | FS47: 0 | FU47: 100 | FV47: 100 | FW47: 100 | FY47: 100 | FZ47: 67 | GA47: 100 | GB47: 0 | GC47: 33 | GD47: 33 | GE47: 33 | GF47: 67 | GG47: 100 | GH47: 0 | GI47: 0 | GJ47: 100 | GL47: 0 | GM47: 100 | GN47: 100 | GO47: 33 | GP47: 100 | GQ47: 100 | GR47: 0 | GS47: 67 | GT47: 0 | GU47: 0 | GV47: 33 | GW47: 0 | GX47: 0 | GY47: 0 | GZ47: 0 | HA47: 0 | HB47: 0 | HC47: 33 | HD47: 33 | HE47: 100 | HF47: 0 | HP47: 67 | HQ47: 33 | HR47: 100 | HS47: 67 | HT47: 0 | HU47: 100 | HV47: 67 | HW47: 0 | HX47: 0 | HY47: 1 | HZ47: 1 | IA47: 1 | IB47: 1 | IC47: 1 | ID47: 1 | IE47: 1 | IF47: 1
A48: Bosnia and Herzegovina | B48: BIH | C48: 2012 | D48: Eastern Europe & Central Asia | E48: Western Balkans & Turkiye | F48: 49.820202 | G48: 50 | H48: Limited (41-60) | I48: Limited (41-60) | J48: Insufficient (0-60) | K48: Middle Quintile | O48: 42.363602 | P48: 42 | Q48: Moderate | R48: 100 | S48: 100 | T48: Strong | X48: 19.4167 | Y48: 19 | Z48: Weak | AA48: PW | AB48: PW | AC48: PW | AD48: HC | AE48: NP | AF48: PW | AG48: PW | AH48: NP | AI48: 1 | AJ48: 1 | AK48: 1 | AL48: 0 | AM48: 1 | AN48: 0 | AO48: 1 | AP48: 1 | AQ48: 100 | AR48: 100 | AS48: Extensive (81-100) | AT48: 47.518501 | AU48: 48 | AV48: Limited (41-60) | AW48: 33 | AX48: 33 | AY48: Minimal (21-40) | AZ48: 0 | BA48: 0 | BB48: Scant or None (0-20) | BC48: 70.875 | BD48: 71 | BE48: Substantial (61-80 | BF48: 0 | BG48: 0 | BH48: Scant or None (0-20) | BI48: 48.222198 | BJ48: 48 | BK48: Limited (41-60) | BL48: 89 | BM48: 89 | BN48: Extensive (81-100) | CD48: 100 | CI48: 100 | CL48: 100 | CM48: 100 | CQ48: 33 | CR48: 33 | CS48: 0 | CT48: 67 | CU48: 100 | CW48: 100 | CX48: 100 | DA48: 0 | DD48: 100 | DG48: 0 | DH48: 0 | DI48: 0 | DL48: 0 | DP48: 0 | DQ48: 0 | DS48: 0 | DT48: 0 | DU48: 33 | DV48: 33 | DW48: 100 | DX48: 67 | DY48: 0 | EA48: 67 | EB48: 67 | EC48: 0 | ED48: 100 | EE48: 100 | EO48: 0 | EP48: 0 | EQ48: 0 | ER48: 0 | EU48: 100 | EW48: 100 | EX48: 100 | EZ48: 33 | FA48: 0 | FB48: 0 | FE48: 0 | FI48: 100 | FL48: 100 | FP48: 100 | FQ48: 0 | FR48: 0 | FS48: 0 | FW48: 100 | FY48: 100 | FZ48: 67 | GA48: 100 | GB48: 0 | GC48: 33 | GD48: 33 | GE48: 0 | GG48: 100 | GH48: 0 | GI48: 0 | GJ48: 100 | GK48: 100 | GL48: 0 | GM48: 100 | GN48: 100 | GP48: 100 | GQ48: 100 | GR48: 0 | GS48: 67 | GT48: 0 | GV48: 33 | GW48: 0 | GX48: 0 | GY48: 0 | GZ48: 0 | HA48: 0 | HB48: 0 | HE48: 100 | HF48: 0 | HP48: 100 | HQ48: 0 | HS48: 67 | HU48: 67 | HV48: 67 | HW48: 0 | HX48: 0 | HY48: 1 | HZ48: 1 | IA48: 1 | IB48: 1 | IC48: 1 | ID48: 1 | IE48: 1 | IF48: 1
A49: Bosnia and Herzegovina | B49: BIH | C49: 2010 | D49: Eastern Europe & Central Asia | E49: Western Balkans & Turkiye | F49: 44.329399 | G49: 44 | H49: Limited (41-60) | I49: Limited (41-60) | J49: Insufficient (0-60) | K49: Middle Quintile | O49: 33.25 | P49: 33 | Q49: Weak | R49: 93.400002 | S49: 93 | T49: Strong | AA49: PW | AB49: PW | AC49: PW | AD49: PW | AE49: NP | AF49: PW | AG49: PW | AH49: NP | AI49: 1 | AJ49: 1 | AK49: 1 | AL49: 0 | AM49: 1 | AN49: 0 | AO49: 1 | AP49: 1 | AQ49: 100 | AR49: 100 | AS49: Extensive (81-100) | AT49: 31.32 | AU49: 31 | AV49: Minimal (21-40) | AW49: 33 | AX49: 33 | AY49: Minimal (21-40) | AZ49: 0 | BA49: 0 | BB49: Scant or None (0-20) | BC49: 75.125 | BD49: 75 | BE49: Substantial (61-80 | BF49: 0 | BG49: 0 | BH49: Scant or None (0-20) | BI49: 48.222198 | BJ49: 48 | BK49: Limited (41-60) | BL49: 94.5 | BM49: 95 | BN49: Extensive (81-100) | CD49: 100 | CI49: 0 | CL49: 100 | CM49: 100 | CQ49: 67 | CR49: 33 | CS49: 0 | CT49: 67 | CU49: 0 | CW49: 0 | CX49: 100 | DA49: 0 | DD49: 100 | DG49: 0 | DH49: 0 | DI49: 0 | DP49: 0 | DQ49: 0 | DS49: 0 | DT49: 0 | DU49: 33 | DV49: 0 | DW49: 100 | DX49: 33 | DY49: 0 | EA49: 0 | EB49: 0 | EC49: 0 | ED49: 100 | EE49: 100 | EO49: 0 | EU49: 100 | EW49: 100 | EX49: 100 | EZ49: 67 | FA49: 0 | FB49: 0 | FE49: 0 | FI49: 67 | FL49: 100 | FP49: 0 | FQ49: 0 | FR49: 0 | FS49: 0 | FW49: 100 | FY49: 100 | FZ49: 67 | GA49: 100 | GD49: 33 | GE49: 33 | GG49: 100 | GH49: 0 | GK49: 100 | GL49: 0 | GM49: 100 | GN49: 100 | GP49: 100 | GQ49: 100 | GR49: 0 | GY49: 0 | GZ49: 0 | HA49: 0 | HB49: 0 | HP49: 100 | HQ49: 33 | HS49: 67 | HU49: 100 | HV49: 100 | HW49: 0 | HX49: 0 | HY49: 1 | HZ49: 1 | IA49: 1 | IB49: 1 | IC49: 1 | ID49: 1 | IE49: 1 | IF49: 1
A50: Bosnia and Herzegovina | B50: BIH | C50: 2008 | D50: Eastern Europe & Central Asia | E50: Western Balkans & Turkiye | F50: 44.209301 | G50: 44 | H50: Limited (41-60) | I50: Limited (41-60) | J50: Insufficient (0-60) | K50: Middle Quintile | O50: 44.416698 | P50: 44 | Q50: Moderate | R50: 90 | S50: 90 | T50: Strong | AA50: PW | AB50: HC | AC50: PW | AD50: PW | AE50: NP | AF50: PW | AG50: PW | AH50: NP | AI50: 1 | AJ50: 1 | AK50: 1 | AL50: 0 | AM50: 1 | AN50: 0 | AO50: 1 | AP50: 1 | AQ50: 100 | AR50: 100 | AS50: Extensive (81-100) | AT50: 33.333302 | AU50: 33 | AV50: Minimal (21-40) | AW50: 67 | AX50: 67 | AY50: Substantial (61-80 | AZ50: 0 | BA50: 0 | BB50: Scant or None (0-20) | BC50: 66.75 | BD50: 67 | BE50: Substantial (61-80 | BF50: 0 | BG50: 0 | BH50: Scant or None (0-20) | BI50: 48.222198 | BJ50: 48 | BK50: Limited (41-60) | BL50: 88.833298 | BM50: 89 | BN50: Extensive (81-100) | CD50: 100 | CI50: 0 | CL50: 100 | CM50: 100 | CQ50: 100 | CR50: 100 | CS50: 67 | CT50: 0 | CU50: 0 | CW50: 0 | CX50: 0 | DA50: 0 | DD50: 0 | DG50: 0 | DH50: 0 | DI50: 0 | DP50: 0 | DQ50: 0 | DR50: 0 | DS50: 0 | DT50: 0 | DU50: 33 | DV50: 0 | DW50: 100 | DX50: 0 | DY50: 0 | EA50: 0 | EB50: 0 | EC50: 0 | ED50: 67 | EE50: 100 | EO50: 0 | EU50: 100 | EW50: 100 | EX50: 100 | EZ50: 0 | FA50: 0 | FB50: 0 | FE50: 0 | FI50: 67 | FL50: 67 | FP50: 0 | FQ50: 33 | FR50: 0 | FS50: 0 | FW50: 100 | FY50: 100 | FZ50: 33 | GA50: 100 | GD50: 33 | GE50: 67 | GG50: 100 | GH50: 100 | GK50: 100 | GL50: 0 | GM50: 100 | GN50: 100 | GP50: 100 | GQ50: 100 | GR50: 0 | GY50: 33 | GZ50: 0 | HA50: 0 | HB50: 33 | HP50: 100 | HQ50: 67 | HS50: 67 | HU50: 100 | HV50: 100 | HW50: 0 | HX50: 0 | HY50: 1 | HZ50: 1 | IA50: 1 | IB50: 1 | IC50: 1 | ID50: 1 | IE50: 1 | IF50: 1
A51: Brazil | B51: BRA | C51: 2025 | D51: Latin America & Caribbean | E51: South America | F51: 82.880734 | G51: 83 | H51: Extensive (81-100) | I51: Sufficient (61-100) | J51: Sufficient (61-100) | K51: Top Quintile | L51: 75.888889 | M51: 76 | N51: Adequate (61-100) | O51: 75 | P51: 75 | Q51: Adequate (61-100) | R51: 77.666667 | S51: 78 | T51: Adequate (61-100) | U51: 75 | V51: 75 | W51: Adequate (61-100) | X51: 55.444444 | Y51: 55 | Z51: Limited opportunities (41-60) | AA51: PW | AB51: PW | AC51: PW | AD51: PW | AE51: PW | AF51: PW | AG51: PW | AH51: PW | AI51: 1 | AJ51: 1 | AK51: 1 | AL51: 1 | AM51: 1 | AN51: 1 | AO51: 1 | AP51: 1 | AQ51: 89 | AR51: 89 | AS51: Extensive (81-100) | AT51: 76.537037 | AU51: 77 | AV51: Substantial (61-80) | AW51: 94.5 | AX51: 95 | AY51: Extensive (81-100) | AZ51: 58.25 | BA51: 58 | BB51: Limited (41-60) | BC51: 100 | BD51: 100 | BE51: Extensive (81-100) | BF51: 77.888889 | BG51: 78 | BH51: Substantial (61-80) | BI51: 90.428571 | BJ51: 90 | BK51: Extensive (81-100) | BL51: 100 | BM51: 100 | BN51: Extensive (81-100) | BO51: a | BP51: a | BQ51: a | BR51: a | BS51: a | BT51: a | BU51: a | BV51: e | BW51: e | BX51: e | BY51: e | BZ51: e | CA51: e | CB51: e | CC51: e | CD51: 100 | CE51: 100 | CF51: 100 | CG51: 100 | CH51: 100 | CI51: 100 | CJ51: 0 | CK51: 33 | CL51: 100 | CM51: 100 | CN51: 100 | CO51: 67 | CP51: 100 | CQ51: 100 | CR51: 100 | CS51: 100 | CT51: 33 | CU51: 100 | CV51: 100 | CW51: 100 | CX51: 100 | CY51: 100 | CZ51: 100 | DA51: 100 | DB51: 100 | DC51: 67 | DD51: 100 | DE51: 100 | DF51: 100 | DG51: 100 | DH51: 100 | DI51: 100 | DJ51: 33 | DK51: 100 | DL51: 100 | DM51: 100 | DN51: 100 | DO51: 33 | DP51: 0 | DQ51: 0 | DR51: 0 | DS51: 67 | DT51: 0 | DU51: 67 | DV51: 67 | DW51: 67 | DX51: 33 | DY51: 0 | DZ51: 33 | EA51: 100 | EB51: 100 | EC51: 33 | ED51: 100 | EE51: 100 | EF51: 67 | EG51: 67 | EH51: 100 | EI51: 100 | EJ51: 100 | EK51: 100 | EL51: 100 | EM51: 100 | EN51: 67 | EO51: 100 | EP51: 33 | EQ51: 67 | ER51: 33 | ES51: 100 | ET51: 100 | EU51: 100 | EV51: 100 | EW51: 100 | EX51: 100 | EY51: 100 | EZ51: 100 | FA51: 100 | FB51: 100 | FC51: 67 | FD51: 0 | FE51: 100 | FF51: 100 | FG51: 67 | FH51: 67 | FI51: 100 | FJ51: 100 | FK51: 100 | FL51: 100 | FM51: 100 | FN51: 100 | FO51: 100 | FP51: 100 | FQ51: 33 | FR51: 100 | FS51: 100 | FT51: 33 | FU51: 100 | FV51: 100 | FW51: 100 | FX51: 100 | FY51: 100 | FZ51: 100 | GA51: 100 | GB51: 100 | GC51: 100 | GD51: 67 | GE51: 33 | GF51: 100 | GG51: 100 | GH51: 33 | GI51: 67 | GJ51: 100 | GK51: 100 | GL51: 100 | GM51: 67 | GN51: 100 | GO51: 100 | GP51: 33 | GQ51: 0 | GR51: 100 | GS51: 100 | GT51: 100 | GU51: 100 | GV51: 33 | GW51: 33 | GX51: 33 | GY51: 100 | GZ51: 33 | HA51: 33 | HB51: 100 | HC51: 33 | HD51: 100 | HE51: 100 | HF51: 100 | HG51: 0 | HH51: 100 | HI51: 33 | HJ51: 0 | HK51: 0 | HL51: 0 | HM51: 100 | HN51: 33 | HO51: 100 | HP51: 100 | HQ51: 100 | HR51: 100 | HS51: 100 | HT51: 100 | HU51: 100 | HV51: 100 | HW51: 0 | HX51: 1 | HY51: 1 | HZ51: 1 | IA51: 1 | IB51: 1 | IC51: 1 | ID51: 1 | IE51: 1 | IF51: 1
